Workbook

Sheet 2026-2027
A1: Sr no | B1: Date | C1: Company Name | D1: Location | E1: State | F1: Product Type | G1: Capacity / Specs | H1: Phone | I1: Email | J1: Inquiry Status | K1: Contact Person | L1: Lead Source | M1: Lead Owner | N1: Quotation No | O1: Quotation Date | P1: Order Value | Q1: Quotation Status | R1: PO DATE | S1: Order Analysis | T1: Remarks
A2: =ROW()-1 -> 1 | B2: 46070 | C2: EKA MOBILITY SOLUTIONS | D2: Chakan | E2: Maharashtra | F2: Jib Crane | G2: pankaj.damare@ekamobility.com' | I2: pankaj.damare@ekamobility.com' | J2: WIN | K2: Pankaj Damare | L2: MAIL | M2: RAVI | N2: FEB-JC06SV | O2: 46070 | P2: 560000 | Q2: PO Received | R2: 46162
A3: =ROW()-1 -> 2 | B3: 46070 | C3: EKA MOBILITY SOLUTIONS | D3: Chakan | E3: Maharashtra | F3: LCS | G3: Jib Crane of 1MT Capacity | I3: pankaj.damare@ekamobility.com' | J3: WIN | K3: Pankaj Damare | L3: MAIL | M3: RAVI | N3: FEB-JC06SV | O3: 46070 | P3: 560000 | Q3: PO Received | R3: 46171
A4: =ROW()-1 -> 3 | B4: 46076 | C4: MAHINDRA & MAHINDRA LTD | D4: Chakan | E4: Maharashtra | F4: Underslung | G4: Underslung Crane of 2MT Capacity | H4: 9637834272 | I4: <DANE.AMOL@mahindra.com> | J4: WIN | K4: DANE AMOL' | L4: MAIL | M4: SAKSHI | N4: FEB-05 23/2/27 | O4: 46076 | P4: 243000 | Q4: PO Received | R4: 46170
A5: =ROW()-1 -> 4 | B5: 46113 | C5: A | D5: Dharni | E5: Maharashtra | F5: Gantry Crane | G5: Portable Gantry Crane | H5: 8080534980 | I5: Dharni, Maharashtra, India | J5: CLOSED | K5: NITESH LAXMAN SEMALKAR | L5: INDIAMART | M5: VIVEK | T5: next week
A6: =ROW()-1 -> 5 | B6: 46113 | C6: A | D6: Thane | E6: Maharashtra | F6: Goliath | G6: Goliath crane | H6: 9324210241 | I6: naveenagrawal2007@gmail.com | J6: LOST | K6: naveen agarwal | L6: TRADEINDIA | M6: VIVEK
A7: =ROW()-1 -> 6 | B7: 46113 | C7: A | E7: Others | F7: Hoist | G7: 2 Ton Electric Chain Hoist | H7: 9146215901 | I7: dangat9666@gmail.com | J7: NOT INTERESTED | K7: bhi | L7: INDIAMART | M7: SAKSHI
A8: =ROW()-1 -> 7 | B8: 46113 | C8: Craftsman Automation | F8: Jib Crane | G8: QUOTATION SHARED | I8: esd_craneu3 <esd_craneu3@craftsmanautomation.com> | J8: QUOTATION SHARED | K8: S.Kanagaraj | L8: MAIL | M8: SAKSHI | N8: 04-CRAFTSMAN-JC-500KG | O8: 46113 | P8: 205000 | Q8: Quotation Sent
A9: =ROW()-1 -> 8 | B9: 46113 | C9: Cummins Generator Technologies India Pvt Ltd | D9: Ranjangoan | E9: Maharashtra | F9: EOT Crane | G9: EXISTING CUS. | H9: 9146185214 | I9: <sandeep.naikare@cummins.com> | J9: QUOTATION SHARED | K9: Sandeep Naikare | L9: EXISTING CUS. | M9: MALLESH | N9: 100/2026-2027 mallesh sir | O9: 46115 | P9: 2597001 | Q9: In Progress
A10: =ROW()-1 -> 9 | B10: 46113 | C10: EKA Mobility Solutions | D10: Pithampur | E10: Tamil Nadu | F10: Manipulator | G10: 7-EKA MOBILITY-PITHAMPUR-05/04/26 | I10: anil.m@ekamobility.com' | J10: PO EXPECTED | K10: Anil Malviya | L10: EXISTING CUS. | M10: RAVI | N10: 7-EKA MOBILITY-PITHAMPUR-05/04/26 | O10: 46116 | P10: 6192000 | Q10: In Progress
A11: =ROW()-1 -> 10 | B11: 46113 | C11: Electrofab Engineering Services Pvt.Ltd | D11: Pimpri Chinchwad | E11: Maharashtra | F11: EOT Crane | G11: crane | H11: 7249020866 | I11: atharvpasalkar146@gmail.com | J11: NOT INTERESTED | K11: athrv | L11: INDIAMART | M11: VIVEK
A12: =ROW()-1 -> 11 | B12: 46113 | C12: Emerson Process Management (India) Pvt. Ltd | D12: Chakan | E12: Maharashtra | F12: EOT Crane | G12: high cost | H12: 9765559037 | I12: <Raviprasad.Savkar@Emerson.com> | J12: CLOSED | K12: Savakar Raviprasad | L12: EXISTING CUS. | M12: RAVI | N12: 06-EMERSON -5TSGEOT | O12: 46115 | P12: 1967125.5 | Q12: Closed | S12: high cost
A13: =ROW()-1 -> 12 | B13: 46113 | C13: KSB India Ltd | D13: Ahmednagar | E13: Maharashtra | F13: EOT Crane | G13: high cost | H13: 9970951430 | I13: <Jaywant.Sutar@ksb.com> | J13: CLOSED | K13: Sutar Jaywant' | L13: EXISTING CUS. | M13: RAVI | N13: 07-KSBLTD-5TSGEOT | O13: 46115 | P13: 1971559.8 | Q13: Closed
A14: =ROW()-1 -> 13 | B14: 46113 | C14: KSB LIMITED | D14: Ahmednagar | E14: Maharashtra | F14: Jib Crane | G14: of Jib Crane of 1MT Capacity | H14: 9970951430 | I14: <Jaywant.Sutar@ksb.com> | J14: WIN | K14: Sutar Jaywant' | L14: EXISTING CUS. | M14: RAVI | N14: 57-KSBLTD-1TJIBCRANE | O14: 46113 | P14: 560000 | Q14: PO Received | R14: 46162
A15: =ROW()-1 -> 14 | B15: 46113 | C15: MITTAL TRADERS | D15: Howrah | E15: Others | F15: EOT Crane | G15: eot cranes | H15: 9007847150 | I15: mohitmitt@gmail.com | J15: NOT INTERESTED | K15: mohit mittal | L15: TRADEINDIA | M15: VIVEK
A16: =ROW()-1 -> 15 | B16: 46113 | C16: SANDVIK COROMANT INDIA PVT. LTD | D16: Dapodi | E16: Maharashtra | F16: Others | G16: Winch for 1T Capacity | H16: 9767350574 | I16: KIRAN NALAGE <kiran.nalage@sandvik.com> | J16: QUOTATION SHARED | K16: Kiran Nalage | L16: REFRENCE | M16: MALLESH | N16: 05/SANDVIK-WINCH-1-04-26 | O16: 46113 | P16: 450000 | Q16: Clarification Pending
A17: =ROW()-1 -> 16 | B17: 46114 | C17: A | D17: Barrackpore | E17: Others | F17: EOT Crane | G17: heavy duty hydra crane | H17: 9883612877 | J17: FAKE | K17: anand gupta | L17: TRADEINDIA | M17: VIVEK
A18: =ROW()-1 -> 17 | B18: 46114 | C18: INFINITE ENERGY PVT. LTD | D18: faridabad | E18: Haryana | F18: Jib Crane | G18: jib crane | H18: 9212084932 | J18: CLOSED | K18: naval | L18: TRADEINDIA | M18: VIVEK | N18: 27-INFINITEENGG- 1T WJC | O18: 46125 | P18: 995000 | Q18: Closed
A19: =ROW()-1 -> 18 | B19: 46114 | C19: Na | D19: Pune | E19: Maharashtra | F19: EOT Crane | G19: Industrial cranes | H19: 7385604099 | J19: FAKE | K19: nagesh talwar | L19: TRADEINDIA | M19: VIVEK
A20: =ROW()-1 -> 19 | B20: 46114 | C20: Singh Fabrication | D20: Pune | E20: Maharashtra | F20: Hoist | G20: hoist | H20: 8766460470 | I20: sshambhussingh08893@gmail.com | J20: CLOSED | K20: Shambhu Singh | L20: INDIAMART | M20: SAKSHI
A21: =ROW()-1 -> 20 | B21: 46115 | C21: A | D21: Chakan | E21: Maharashtra | F21: Hoist | G21: Wire Rope Hoist | H21: 8591226468 | I21: NA | J21: NOT INTERESTED | K21: VAISHALI | L21: INDIAMART | M21: SAKSHI
A22: =ROW()-1 -> 21 | B22: 46115 | C22: A J Enterprise | D22: Meerut | E22: Uttar Pradesh | F22: EOT Crane | G22: Electric Overhead Crane | H22: 9997306071 | I22: gufrankhanjanimeerut@gmail.com | J22: CLOSED | K22: Gufran Khan | L22: INDIAMART | M22: VIVEK
A23: =ROW()-1 -> 22 | B23: 46115 | C23: Aakruti Tooling | D23: Moi | E23: Maharashtra | F23: EOT Crane | G23: Portable Gantry Cranes | I23: -aakrutitooling@gmail.com | J23: CLOSED | K23: nilesh aher | L23: REFRENCE | M23: VIVEK | N23: 11-AAKRUTI-EOT-12.5T-MOI-05/04/26 | O23: 46117 | P23: 2029583.8 | Q23: Quotation Sent
A24: =ROW()-1 -> 23 | B24: 46115 | C24: Aarya And Company | D24: Aurangabad | E24: Maharashtra | F24: Gantry Crane | G24: Portable Gantry Cranes | H24: 9960238973 | I24: chetanyelikar@yahoo.in | J24: NOT INTERESTED | K24: Chetan Yelikar | L24: INDIAMART | M24: VIVEK
A25: =ROW()-1 -> 24 | B25: 46115 | C25: Application Eng. | D25: bhosari | E25: Maharashtra | F25: Others | G25: 8-ENERGYGS-HOIST -5 & 10T-04/04/26 | I25: <applicationengg@impregseal.com> | J25: QUOTATION SHARED | L25: REFRENCE | M25: VIVEK | N25: 9-ApplicationEngg-LCS-500kg1T -05/04/26 | O25: 46116 | P25: 807957 | Q25: Quotation Sent
A26: =ROW()-1 -> 25 | B26: 46115 | C26: EKA MOBILITY SOLUTIONS | D26: Pithampur | E26: Madhya Pradesh | F26: EOT Crane | G26: yuvraj_kate84@rediffmail.com | J26: WIN | L26: MAIL | M26: RAVI | N26: 31-EKA-3MT SGEOT | P26: 7060392 | Q26: PO Received | R26: 46174
A27: =ROW()-1 -> 26 | B27: 46115 | C27: ENERSYS THERMAL LTD | E27: Maharashtra | F27: Others | G27: Perfect Machine Tools Corporation Limited | I27: enersys.pune@gmail.com | J27: QUOTATION SHARED | K27: NA | L27: INDIAMART | M27: VIVEK | N27: 8-ENERGYGS-HOIST -5 & 10T-04/04/26 | O27: 46116 | P27: 684000 | Q27: Quotation Sent
A28: =ROW()-1 -> 27 | B28: 46115 | C28: Ho Company | D28: Indapur | E28: Maharashtra | F28: Hoist | G28: Electric Hoists | H28: 9923625798 | I28: yuvraj_kate84@rediffmail.com | J28: FULFILLED | K28: Kate Yuvraj | L28: INDIAMART | M28: SAKSHI
A29: =ROW()-1 -> 28 | B29: 46115 | C29: Perfect Machine Tools Corporation Limited | D29: Sahibabad | E29: Uttar Pradesh | F29: Manipulator | G29: Manipulators | H29: 9370556327 | I29: pmtdel@pmtcoltd.com | J29: LOST | K29: S.K. Kapoor | L29: INDIAMART | M29: RAVI
A30: =ROW()-1 -> 29 | B30: 46115 | D30: Coimbatore | E30: Tamil Nadu | F30: Hoist | G30: 2 Ton Electric Chain Hoist | H30: 7708636022 | I30: nsnkarthik12@gmail.com | J30: NOT INTERESTED | K30: RAJENDRAN KARTHIK | L30: INDIAMART | M30: SAKSHI
A31: =ROW()-1 -> 30 | B31: 46116 | C31: A | E31: Uttar Pradesh | F31: Hoist | G31: Electric Chain Hoist | H31: 9850103500 | I31: coolatul1994@gmail.com | J31: NOT INTERESTED | K31: atul | L31: INDIAMART | M31: SAKSHI
A32: =ROW()-1 -> 31 | B32: 46116 | C32: A | D32: mumbai | E32: Uttar Pradesh | F32: Hoist | G32: hoist | H32: 9561900219 | I32: arjunkurhade66967@gmail.com | J32: NOT INTERESTED | K32: arjun | L32: INDIAMART | M32: SAKSHI
A33: =ROW()-1 -> 32 | B33: 46116 | C33: Andriya Shipping | D33: Thoothukudi | E33: Tamil Nadu | F33: Jib Crane | G33: Pillar Mounted Jib Crane | H33: 7397256036 | I33: andriyashipping@gmail.com | J33: FAKE | K33: kaushik | L33: INDIAMART | M33: VIVEK
A34: =ROW()-1 -> 33 | B34: 46116 | C34: horizontal boring machine job work | D34: Rajkot | E34: Gujarat | F34: EOT Crane | G34: Single Girder Cranes | H34: 6351590630 | I34: basirboghara26@gmail.com | J34: NOT INTERESTED | K34: Arsh Boghara | L34: INDIAMART | M34: VIVEK
A35: =ROW()-1 -> 34 | B35: 46116 | C35: mohamaad safik contractor | D35: Jodhpur | E35: Rajasthan | F35: Manipulator | G35: Overhead Mounted Manipulator | H35: 9694664945 | I35: mohmmad.aslam04@gmail.com | J35: FAKE | K35: aslam | L35: INDIAMART | M35: VIVEK
A36: =ROW()-1 -> 35 | B36: 46116 | C36: S B Engineering | D36: Brahma Nagar | E36: Karnataka | F36: Hoist | G36: Electric Hoists | H36: 9606739416 | I36: shubhamwadekar35968@gmail.com | J36: NOT INTERESTED | K36: shubham | L36: INDIAMART | M36: SAKSHI
A37: =ROW()-1 -> 36 | B37: 46116 | C37: Shiv Enterprises | E37: Maharashtra | F37: Hoist | G37: 1 Ton Electric Chain Hoist | H37: 9158772627 | I37: arvinddandwate2@gmail.com | J37: FAKE | K37: anita | L37: INDIAMART | M37: SAKSHI
A38: =ROW()-1 -> 37 | B38: 46116 | C38: Sri Mahalakshmi Engineering Works | D38: Prashanthi nagar | E38: Telangana | F38: Hoist | G38: Heavy Duty Wire Rope Hoist | H38: 9440860225 | I38: srimahalakshmi216@gmail.com | J38: NOT INTERESTED | K38: Santhosh | L38: INDIAMART | M38: SAKSHI | T38: n discussion
A39: =ROW()-1 -> 38 | B39: 46116 | C39: Universal Marketing Services | E39: Uttar Pradesh | F39: Hoist | G39: 3 Ton Electric Wire Rope Hoist | H39: 9443114544 | I39: umsscales@gmail.com | J39: NOT INTERESTED | K39: Ahilan Natarajan | L39: INDIAMART | M39: SAKSHI
A40: =ROW()-1 -> 39 | B40: 46117 | C40: CLF PROJECTS PVT LTD | D40: Pune | E40: Maharashtra | F40: EOT Crane | G40: Devendra Bonde | I40: purchase.infra@clfprojects.com' | J40: CLOSED | L40: REFRENCE | M40: MALLESH | N40: 10-CLF PROJECTS-15/5T-05/041/26 | O40: 46117 | P40: 6820905 | Q40: Closed
A41: =ROW()-1 -> 40 | B41: 46118 | C41: Buildchem | D41: Sangamner | E41: Maharashtra | F41: Gantry Crane | G41: Portable Gantry Crane | H41: 9324811919 | I41: support@buildcheminfra.com | J41: FAKE | K41: gite | L41: INDIAMART | M41: VIVEK
A42: =ROW()-1 -> 41 | B42: 46118 | C42: Kamsiddha Engineers And Fabricators | D42: Chikhli | E42: Maharashtra | F42: Hoist | G42: S. H. Engineers | H42: 9637320354 | I42: kamsiddha.eng@gmail.com | J42: WIN | K42: Devendra Bonde | L42: INDIAMART | M42: SAKSHI | N42: 15-RE-KAMSIDDHA-5T Hoist | O42: 46119 | P42: 440800 | Q42: PO Received | R42: 46162
A43: =ROW()-1 -> 42 | B43: 46118 | C43: Marketing Plus | D43: Noida | E43: Uttar Pradesh | F43: Jib Crane | G43: Pillar Mounted Jib Crane | H43: 8130300040 | I43: marketingplus.gg@gmail.com | J43: FAKE | K43: Rahul Babbar | L43: INDIAMART | M43: VIVEK
A44: =ROW()-1 -> 43 | B44: 46118 | C44: PMI Coaches Pvt Ltd | D44: Pune | E44: Maharashtra | F44: Jib Crane | G44: Pillar Mounted Jib Crane | H44: 9158899611 | I44: AVINASHJAIN59@GMAIL.COM | J44: CLOSED | K44: avinash jain | L44: INDIAMART | M44: VIVEK
A45: =ROW()-1 -> 44 | B45: 46118 | C45: S. H. Engineers | D45: Baramati | E45: Maharashtra | F45: Hoist | G45: Electric Wire Rope Hoist | H45: 9765356786 | I45: waseem.shikalkar@gmail.com | J45: NOT INTERESTED | K45: Waseem Shikalkar | L45: INDIAMART | M45: SAKSHI
A46: =ROW()-1 -> 45 | B46: 46118 | C46: Vertex Elevators India | D46: Pune | E46: Maharashtra | F46: Hoist | G46: Electric Chain Hoist | H46: 7776076665 | I46: NA | J46: CLOSED | K46: Pramod Kinge | L46: INDIAMART | M46: SAKSHI
A47: =ROW()-1 -> 46 | B47: 46119 | C47: BOMAG INDIA PVT LTD | D47: Pune | E47: Maharashtra | F47: Others | G47: 14-EEPOS-1MT CH -07/04/26 | H47: 8956613645 | I47: rajiv.gaikwad@dynapac.com' | J47: CLOSED | K47: Vaibhav | L47: EXISTING CUS. | M47: RAVI | N47: 13/BOMAG/D&ICRANE-06/04/26 | O47: 46120 | P47: 415000 | Q47: Closed
A48: =ROW()-1 -> 47 | B48: 46119 | C48: EEPOS INDIA | D48: Pune | E48: Maharashtra | F48: Hoist | G48: gayatri Agritech | H48: 7722050915 | I48: <akash@eeposcranes.co.in> | J48: QUOTATION SHARED | K48: Akash Subhedar | L48: MAIL | M48: SAKSHI | N48: 14-EEPOS-1T CH | O48: 46120 | P48: 132594 | Q48: Quotation Sent
A49: =ROW()-1 -> 48 | B49: 46119 | C49: EEPOS INDIA | D49: Pune | E49: Maharashtra | F49: Hoist | G49: Chain Hoist | H49: 7758036720 | I49: r' <bhagyashri@eeposcranes.co.in> | J49: WIN | K49: Bhagyashri Kumbha | L49: EXISTING CUS. | M49: SAKSHI | N49: 14-EEPOS-1MT CH -07/04/26 | O49: 46119 | P49: 126280 | Q49: PO Received | R49: 46162
A50: =ROW()-1 -> 49 | B50: 46119 | C50: Endo Kogyo India Pvt. Ltd | D50: Pune | E50: Maharashtra | F50: Jib Crane | G50: Pillar Mounted Jib Crane 250 Kg | H50: 8600120115 | I50: eki1@endo-india.co.in | J50: QUOTATION SHARED | K50: Akshay Salunkhe | L50: MAIL | M50: RAVI | N50: 23-ENDO-JC 250KG | O50: 46120 | P50: 414000 | Q50: Quotation Sent
A51: =ROW()-1 -> 50 | B51: 46119 | C51: gayatri Agritech | D51: gayatri Agritech | E51: Maharashtra | F51: Jib Crane | G51: Heavy Duty Jib Crane | H51: 8857033592 | I51: shinde.abhay333@gmail.com | J51: NOT INTERESTED | K51: abhay | L51: INDIAMART | M51: VIVEK
A52: =ROW()-1 -> 51 | B52: 46119 | C52: HI TECH MACHINES TOOLS | D52: Mandi Gobindgarh | E52: Punjab | F52: EOT Crane | G52: eot crane | H52: 9780400793 | J52: NOT INTERESTED | K52: Jagdeep Singh | L52: TRADEINDIA | M52: VIVEK
A53: =ROW()-1 -> 52 | B53: 46119 | C53: HYOSUNG T & D INDIA PVT LTD | D53: Pune | E53: Maharashtra | F53: Jib Crane | G53: Parker Hannifin India Pvt Ltd | I53: haidarali.darveshi@hyosung.com' | J53: QUOTATION SHARED | K53: haidrali | L53: INDIAMART | M53: VIVEK | N53: 15-HT&DIPL-JC500kg -07/04/27 | O53: 46119 | P53: 555000 | Q53: Quotation Sent
A54: =ROW()-1 -> 53 | B54: 46119 | C54: Irle Kay Jay Rolls Pvt. Ltd. | D54: Panchkula | E54: Haryana | F54: EOT Crane | H54: 8968593098 | I54: purchase@ikjrolls.com | J54: CLOSED | L54: TRADEINDIA
A55: =ROW()-1 -> 54 | B55: 46119 | C55: KAMSIDHA ENGNEERING & FABRICATIONS | D55: Pune | E55: Maharashtra | F55: LCS | G55: purchase@xpertmhe.com | H55: 9637320354 | I55: kamsiddha.lif@gmail.com' | J55: QUOTATION SHARED | K55: Devendra Bonde | L55: INDIAMART | M55: VIVEK | N55: 18-KE&F-500KG-LCS SYSTEM | O55: 46119 | P55: 311316.6 | Q55: Quotation Sent
A56: =ROW()-1 -> 55 | B56: 46119 | C56: Liftsafe Cranes India Pvt. Ltd | D56: Pune | E56: Maharashtra | F56: LCS | G56: Ludhiana | H56: 9503218504 | I56: <liftsafesales@gmail.com> | J56: QUOTATION SHARED | K56: Pratiksha | L56: MAIL | M56: RAVI | N56: 16/LIFESAFE-LCS0.5T-07/04/26 | O56: 46119 | P56: 1672022.1 | Q56: Discussion Ongoing
A57: =ROW()-1 -> 56 | B57: 46119 | C57: Parker Hannifin India Pvt Ltd | D57: Mumbai | E57: Maharashtra | F57: Manipulator | G57: Industrial Manipulator for Material Lifting | I57: NA | J57: LOST | K57: soham | L57: INDIAMART | M57: RAVI
A58: =ROW()-1 -> 57 | B58: 46119 | C58: sri satguru enterprises | D58: Pune | E58: Maharashtra | F58: EOT Crane | G58: crane | I58: NA | J58: FAKE | K58: Nanasaheb Dnynoba Bagade | L58: INDIAMART | M58: VIVEK
A59: =ROW()-1 -> 58 | B59: 46119 | C59: xpert material handling | D59: Pune | E59: Maharashtra | F59: Hoist | G59: Electric Chain Hoist 2000kg | H59: 7769969765 | I59: purchase@xpertmhe.com | J59: CLOSED | K59: Madan R | L59: INDIAMART | M59: SAKSHI | N59: 32-XPERT 2MT CHAINHOIST | O59: 46138 | P59: 197742 | Q59: On Hold
A60: =ROW()-1 -> 59 | B60: 46119 | D60: Ludhiana | E60: Punjab | F60: Hoist | G60: Electric Chain Hoist | I60: baljeetsainibaljeetkaur5008@gmail.com | J60: FAKE | K60: NA | L60: INDIAMART | M60: SAKSHI
A61: =ROW()-1 -> 60 | B61: 46119 | D61: Tirunelveli | E61: Tamil Nadu | F61: Hoist | G61: Motorized Chain Hoist | H61: 9842020245 | I61: NA | J61: CLOSED | K61: NA | L61: INDIAMART | M61: SAKSHI
A62: =ROW()-1 -> 61 | B62: 46120 | C62: CG GLOBAL | D62: Mandideep | E62: Madhya Pradesh | F62: Others | G62: Electric Wire Rope Hoist of 5MT Capacity | H62: 7020865996 | I62: ram.padulkar@cgglobal.com | J62: QUOTATION SHARED | K62: Ram PPadulkar. | L62: EXISTING CUS. | M62: MALLESH | N62: 71-CG GLOBAL-ELEC PANEL | O62: 46136 | P62: 475000 | Q62: In Progress
A63: =ROW()-1 -> 62 | B63: 46120 | C63: Deccan Electro Works | D63: kolhpur | E63: Maharashtra | F63: Jib Crane | G63: jib crane | H63: 9370694025 | I63: raste.deccan@gmail.com | J63: LOST | K63: Avinash Raste Wasudeo | L63: TRADEINDIA | M63: VIVEK
A64: =ROW()-1 -> 63 | B64: 46120 | C64: GKN DRIVING LINE | D64: Lonikand | E64: Maharashtra | F64: Hoist | G64: gayatri Agritech | J64: QUOTATION SHARED | L64: REFRENCE | M64: VIVEK | N64: 21-GKN-DRIVE LINE -JC 250KG | O64: 46121 | P64: 390000 | Q64: Clarification Pending | T64: No update
A65: =ROW()-1 -> 64 | B65: 46120 | C65: Jay Malhar Tredars | D65: Pune | E65: Maharashtra | F65: EOT Crane | G65: Single Beam EOT Crane | H65: 9764000241 | I65: NA | J65: NOT INTERESTED | K65: anil | L65: INDIAMART | M65: VIVEK
A66: =ROW()-1 -> 65 | B66: 46120 | C66: Mane Kancor Ingredients Pvt | D66: karnataka | E66: Telangana | F66: Hoist | G66: Electric Wire Rope Hoist of 5MT Capacity | H66: 9567698052 | I66: S Prabath <Prabath.S@MANE.com> | J66: QUOTATION SHARED | K66: Prabath S | L66: MAIL | M66: SAKSHI | N66: 106-MANE KANCOR-HOIST- 1MT- 6-4-2026 | O66: 46118 | P66: 1450000
A67: =ROW()-1 -> 66 | B67: 46120 | C67: Nav Preet Transmission | D67: Nav Preet Transmission | E67: Maharashtra | F67: EOT Crane | G67: Industrial EOT Cranes | H67: 9730558867 | I67: shindeabhishek004@gmail.com | J67: LOST | K67: abhishek | L67: INDIAMART | M67: VIVEK
A68: =ROW()-1 -> 67 | B68: 46120 | C68: TECH EXPERT INDIA LTD | D68: Pune | E68: Maharashtra | F68: Others | G68: 24-Liftsafepvtltd-LCS SYSTEM500kg | I68: purchase2 (Techexpert)' <purchase2@techexpertindia.com> | J68: QUOTATION SHARED | K68: Ajay Nalawade | L68: MAIL | M68: SAKSHI | N68: 22-TECHEXPERT-TRANSFERTROLLEY | O68: 46120 | P68: 550000 | Q68: Discussion Ongoing
A69: =ROW()-1 -> 68 | B69: 46120 | C69: WATSON & CHALIN INDIA PVT. LTD | D69: Pune | E69: Maharashtra | F69: LCS | G69: Yash Borade | H69: 9890039131 | I69: Lashkare Deepak' <dlashkare@hendrickson-intl.com> | J69: CLOSED | K69: Deepak lashkare | L69: MAIL | M69: SAKSHI | N69: 22-HENDRICKSON-LCS1T-08/26 | O69: 46120 | P69: 913101.8 | Q69: Closed
A70: =ROW()-1 -> 69 | B70: 46120 | E70: Others | F70: EOT Crane | G70: Heavy duty cranes | H70: 7373390090 | J70: FAKE | K70: Allauddin Shaikh | L70: TRADEINDIA | M70: VIVEK | T70: Discussion Ongoing
A71: =ROW()-1 -> 70 | B71: 46121 | C71: Arhan Technology | D71: Pune | E71: Maharashtra | F71: LCS | J71: QUOTATION SHARED | L71: MAIL | M71: RAVI | N71: 23-ARHAN-02T-LCS SS | O71: 46122 | P71: 635000 | Q71: Discussion Ongoing
A72: =ROW()-1 -> 71 | B72: 46121 | C72: Bothara Communication | D72: Nashik | E72: Maharashtra | F72: Hoist | G72: hoist | H72: 9403565656 | I72: pareshb56@yahoo.co.in | J72: CLOSED | K72: Paresh Ventures | L72: INDIAMART | M72: SAKSHI
A73: =ROW()-1 -> 72 | B73: 46121 | C73: Liftsafe Cranes India Pvt. Ltd. | D73: Pune | E73: Maharashtra | F73: LCS | G73: LCS | I73: liftsafesales <liftsafesales@gmail.com> | J73: QUOTATION SHARED | L73: MAIL | M73: RAVI | N73: 24-Liftsafepvtltd-LCS SYSTEM500kg | O73: 46124 | P73: 2112645.7
A74: =ROW()-1 -> 73 | B74: 46121 | C74: SAARLOHA Advanced Materials Pvt. Ltd | D74: mudhawa | E74: Maharashtra | F74: Hoist | G74: Prathamesh | H74: 20-66215363 | I74: <yash.borade@saarloha.com> | J74: QUOTATION SHARED | K74: Yash Borade | L74: MAIL | M74: MALLESH | N74: 23-SAARLOHA-1T-CH-10/04/26 | O74: 46122 | P74: 155284 | Q74: Quotation Sent | S74: invalid
A75: =ROW()-1 -> 74 | B75: 46121 | D75: surat | E75: Gujarat | F75: EOT Crane | G75: heavy duty eot cranes | H75: 9924546462 | I75: weldcare@yahoo.com | J75: NOT INTERESTED | L75: TRADEINDIA | M75: VIVEK
A76: =ROW()-1 -> 75 | B76: 46121 | D76: Ghaziabad | E76: Uttar Pradesh | F76: Manipulator | G76: Industrial Pneumatic Manipulator | H76: 7835907263 | I76: NA | J76: LOST | K76: NA | L76: INDIAMART | M76: RAVI
A77: =ROW()-1 -> 76 | B77: 46122 | C77: EKA Mobility Solutions | D77: KOREGOAN BHIMA | E77: Maharashtra | F77: LCS | G77: m_k_jaiswal@rediffmail.com | I77: <Lakshya.Malhotra@ekamobility.com> | J77: PO EXPECTED | K77: Lashya Malhotra | L77: MAIL | M77: RAVI | N77: 25-RE EKA-LCS SS-2MT | O77: 46122 | P77: 1070000 | Q77: Quotation Sent
A78: =ROW()-1 -> 77 | B78: 46122 | C78: JK Tyre | D78: Mysore | E78: Karnataka | F78: Hoist | G78: 1 Ton Factory Electric Chain Hoist | I78: dbcoe.chiefeng@gmail.com | J78: FAKE | K78: NA | L78: INDIAMART | M78: SAKSHI
A79: =ROW()-1 -> 78 | B79: 46122 | C79: New Company - Prathamesh | D79: Pune | E79: Maharashtra | F79: EOT Crane | H79: 9702282453 | J79: FULFILLED | K79: Prathamesh | L79: TRADEINDIA | M79: VIVEK
A80: =ROW()-1 -> 79 | B80: 46122 | C80: New Company-None | E80: Others | F80: EOT Crane | H80: 9767035430 | J80: FAKE | L80: TRADEINDIA | M80: VIVEK
A81: =ROW()-1 -> 80 | B81: 46122 | C81: numbermasking-inquiry-28972635 | E81: Others | F81: EOT Crane | H81: 8866146055 | J81: FAKE | L81: TRADEINDIA | M81: VIVEK
A82: =ROW()-1 -> 81 | B82: 46122 | C82: PRESS METAL INDUSTRIES | D82: NASHIK | E82: Maharashtra | F82: LCS | G82: nvranade@bajajauto.co.in | I82: mayur@pressmetal.co.in' | J82: LOST | K82: Mayur | L82: INDIAMART | M82: VIVEK | N82: 20-PMI- LCS SYSTEM 500KG | O82: 46122 | P82: 673124.25 | Q82: Quotation Sent
A83: =ROW()-1 -> 82 | B83: 46122 | C83: Project 2.0 | D83: Pune | E83: Maharashtra | F83: Gantry Crane | G83: Portable Gantry Crane | H83: 9921993346 | I83: NA | J83: FAKE | K83: NA | L83: INDIAMART | M83: VIVEK
A84: =ROW()-1 -> 83 | B84: 46123 | C84: CSEB | D84: Korba, Chhattisgarh, India | E84: Chhattisgarh | F84: Jib Crane | G84: Niranjan Shimpale (KPCL)' <niranjan.shimpale@kirloskar.com> | H84: 9826697787 | I84: m_k_jaiswal@rediffmail.com | J84: NOT INTERESTED | K84: Manoj | L84: INDIAMART | M84: VIVEK
A85: =ROW()-1 -> 84 | B85: 46123 | C85: Sri Lalitha Enterprises Industries (P) Limited | D85: Peddapuram | E85: Andhra Pradesh | F85: EOT Crane | H85: 9494154547 | I85: lalitharice@gmail.com | J85: NOT INTERESTED | K85: Mr. Srinivas | L85: TRADEINDIA | M85: VIVEK
A86: =ROW()-1 -> 85 | B86: 46124 | C86: CUMMINS REFERENCE | D86: AHEMEDNAGAR | E86: Maharashtra | F86: Jib Crane | G86: Omkar | H86: 9422225589 | J86: CLOSED | K86: GANESH KHOLER | L86: REFRENCE | M86: MALLESH
A87: =ROW()-1 -> 86 | B87: 46124 | C87: EKA Mobility Solutions | D87: Pithampur | E87: Tamil Nadu | F87: Manipulator | G87: mayur@pressmetal.co.in' | I87: Shubhadeep Dutta' <shubhadeep.dutta@ekamobility.com> | J87: PO EXPECTED | K87: Shubhadeep | L87: MAIL | M87: RAVI | N87: 31-EML-PITHAMPUR-3TSGEOT | O87: 46124 | P87: 37771073 | Q87: Quotation Sent
A88: =ROW()-1 -> 87 | B88: 46125 | C88: BAJAJ AUTO | D88: Pune | E88: Maharashtra | F88: Others | G88: Shivangi Rolling Mill Pvt. Ltd. | H88: 9881717449 | I88: nvranade@bajajauto.co.in | J88: QUOTATION SHARED | K88: Nilesh Ranade | L88: MAIL | M88: MALLESH | N88: 34-BAJAJAUTO-CRANE TRANVERSE- | O88: 46125 | P88: 130640 | Q88: Quotation Sent
A89: =ROW()-1 -> 88 | B89: 46125 | C89: Datta Industries | D89: Pune | E89: Maharashtra | F89: Gantry Crane | G89: Sanoj kumar | H89: 9112920002 | I89: lankeshjagadale@gmail.com | J89: NOT INTERESTED | K89: Lankesh Arjun Jagdale | L89: INDIAMART | M89: VIVEK
A90: =ROW()-1 -> 89 | B90: 46125 | C90: Kirloskar Pneumatics Co Ltd | D90: Hadapsar | E90: Maharashtra | F90: EOT Crane | H90: 9765444390 | I90: Niranjan Shimpale (KPCL)' <niranjan.shimpale@kirloskar.com> | J90: PO EXPECTED | K90: Niranjan Shimple | L90: MAIL | M90: RAVI | N90: 28-KPCL-SGEOT5T | O90: 46125 | P90: 1591413.2 | Q90: Quotation Sent
A91: =ROW()-1 -> 90 | B91: 46125 | C91: Kirloskar Pneumatics Co Ltd | D91: Hadapsar | E91: Maharashtra | F91: Hoist | H91: 9765444391 | I91: Niranjan Shimpale (KPCL)' <niranjan.shimpale@kirloskar.com> | J91: PO EXPECTED | K91: Niranjan Shimple | L91: MAIL | M91: RAVI | N91: 30-KPCL-WR HOIST 1T | O91: 46125 | P91: 412985 | Q91: Quotation Sent
A92: =ROW()-1 -> 91 | B92: 46125 | C92: New Company-Akash Tapadar | D92: Nagaon | E92: Assam | F92: Jib Crane | H92: 7896329983 | J92: NOT INTERESTED | K92: Akash Tapadar | L92: TRADEINDIA | M92: VIVEK
A93: =ROW()-1 -> 92 | B93: 46125 | C93: New Company-Akash Tapadar | D93: Nagaon,India | E93: Assam | F93: Jib Crane | H93: 7896329983 | J93: FAKE | K93: Akash Tapadar | L93: TRADEINDIA | M93: VIVEK
A94: =ROW()-1 -> 93 | B94: 46125 | C94: New Company-Omkar | D94: Pune | E94: Maharashtra | F94: Hoist | G94: jag.141269@gmail.com | H94: 9380727062 | J94: FULFILLED | K94: Omkar | L94: TRADEINDIA | M94: SAKSHI
A95: =ROW()-1 -> 94 | B95: 46125 | C95: PRESS METAL INDUSTRIES | D95: NASHIK | E95: Maharashtra | F95: Jib Crane | G95: Wall Mounted Jib Crane of 500kg Capacity | I95: mayur@pressmetal.co.in' | J95: LOST | K95: Mayur | L95: INDIAMART | M95: VIVEK | N95: 33-PMI-WMJC-500KG | O95: 46125 | P95: 335789 | Q95: Quotation Sent
A96: =ROW()-1 -> 95 | B96: 46125 | C96: SHAMKUMAR Mourya | D96: Satara | E96: Maharashtra | F96: Hoist | G96: Orgogroup | H96: 7350928634 | I96: shammorya10@gmail.com | J96: NOT INTERESTED | K96: SHAMKUMAR Mourya | L96: INDIAMART | M96: SAKSHI
A97: =ROW()-1 -> 96 | B97: 46125 | C97: Shivangi Rolling Mill Pvt. Ltd. | D97: Pithampur | E97: Madhya Pradesh | F97: EOT Crane | G97: 38-ORGO GROUP-LCS RAIL STRUCTURE | H97: 9109211469 | I97: store.purchase@shivangitmtbars.com | J97: NOT INTERESTED | K97: Suraj Rajput | L97: INDIAMART | M97: VIVEK
A98: =ROW()-1 -> 97 | B98: 46125 | C98: sky india | D98: Ghaziabad | E98: Uttar Pradesh | F98: Jib Crane | H98: 9955331208 | I98: sanojkr1988@gmail.com | J98: FULFILLED | K98: Sanoj kumar | L98: TRADEINDIA | M98: VIVEK
A99: =ROW()-1 -> 98 | B99: 46125 | C99: Super Mack | D99: Meerut, Uttar Pradesh, India | E99: Uttar Pradesh | F99: EOT Crane | G99: Niranjan Shimpale (KPCL)' <niranjan.shimpale@kirloskar.com> | H99: 9927244404 | I99: saifi.sam80@gmail.com | J99: NOT INTERESTED | K99: Sameer | L99: INDIAMART | M99: VIVEK
A100: =ROW()-1 -> 99 | B100: 46126 | C100: Cummins Generator india pvt ltd | D100: NAGAR | E100: Maharashtra | F100: Hoist | H100: 9665511982 | I100: vaibhav.randhave@cummins.com | J100: QUOTATION SHARED | K100: Vaibhav Randhave | L100: MAIL | M100: MALLESH | N100: 37-CGIL-HOIST | O100: 46133 | P100: 1545834 | Q100: Quotation Sent | T100: in process
...

Sheet 2025-2026
A1: Sr no | B1: Date | C1: Company Name | D1: Location | E1: States | F1: Product Type | G1: Capacity / Specs | H1: Phone | I1: Email | J1: Inquiry Status | K1: Contact Person | L1: Lead Source | M1: Lead Owner | N1: Quotation No | O1: Quotation Date | P1: Expected Order Value | Q1: Quotation Status | R1: Order loss Analysis | S1: Order Analysis | T1: Remarks
A2: =ROW()-1 -> 1 | B2: 46023 | C2: BAHRAIN WORKSHOP COMPANY | D2: Kingdom of Bahrain | E2: International | F2: EOT Crane | G2: SG EOT Crane of 1MT Capacity | J2: QUOTATION REQ. | K2: Ganesh Kelkar | L2: EXISTING CUS. | M2: RAVI | O2: 45992 | P2: 90125 | Q2: Discussion Ongoing
A3: =ROW()-1 -> 2 | B3: 46023 | C3: PINNACLE MOBILITY SOLUTIONS | D3: CHAKAN | E3: Maharashtra | F3: Others | G3: Supply of Man Lifter | J3: QUOTATION REQ. | K3: Lakshya malhotra | L3: EXISTING CUS. | M3: RAVI | O3: 45992 | P3: 550000 | Q3: Discussion Ongoing
A4: =ROW()-1 -> 3 | B4: 46023 | C4: ATHARVA ENTERPRISES | D4: Pune | E4: Maharashtra | F4: Monorail | G4: Monorail System of 125KG Capacity | H4: 8669660939 | I4: <atharvaenterprises9999@gmail.com> | J4: QUOTATION REQ. | K4: Rakesh sir | L4: EXISTING CUS. | M4: RAVI | O4: 45992 | P4: 1209252 | Q4: IN PROGRESS
A5: =ROW()-1 -> 4 | B5: 46023 | C5: Batliboi ltd, | D5: Pune | E5: Maharashtra | F5: EOT Crane | G5: S/G EOT crane of 3MT | J5: QUOTATION REQ. | L5: MAIL | M5: VIKRAM | O5: 45992 | P5: 2190000 | Q5: IN PROGRESS
A6: =ROW()-1 -> 5 | B6: 46024 | C6: Indo farm Equipments Pvt Ltd | D6: Solan | E6: Madhya Pradesh | F6: EOT Crane | G6: Supply of SG EOT of 2T 3T 15T | H6: 9317255092 | I6: shokenderchhillar@indofarm.in | J6: QUOTATION REQ. | K6: sondeep lohan | L6: MAIL | M6: VIKRAM | N6: SG01SV | O6: 46024 | P6: 95975955 | Q6: Discussion Ongoing
A7: =ROW()-1 -> 6 | B7: 46024 | C7: SMH Rail India Pvt Ltd | D7: Hydrabad | E7: Telangana | F7: EOT Crane | G7: Supply of SG EOT of10T | H7: 9494261947 | I7: srikanth@shmrail.com.my | J7: QUOTATION REQ. | K7: srikanth | L7: EXISTING CUS. | M7: VIVEK
A8: =ROW()-1 -> 7 | B8: 46024 | C8: Perfect Engineering | D8: Pune | E8: Maharashtra | F8: Hoist | G8: Electric Wire Rope Hoist | H8: 7620034850 | I8: mk7276164@gmail.com | J8: WIN | K8: Maaz Sir | L8: INDIAMART | M8: SAKSHI | Q8: PO Received
A9: =ROW()-1 -> 8 | B9: 46024 | C9: A | D9: Pune | E9: Maharashtra | F9: Jib Crane | H9: 9922353803 | J9: FAKE | K9: DNYANESHVAR UTTAM DIXIT | L9: INDIAMART | M9: VIKRAM
A10: =ROW()-1 -> 9 | B10: 46024 | C10: Dwarkesh Engineering Works India | D10: Gujarat | E10: Gujarat | F10: Jib Crane | H10: 7048814279 | I10: dewaircompressor@gmail.com | J10: CONTACTED | K10: sanjay patel | L10: INDIAMART | M10: VIKRAM
A11: =ROW()-1 -> 10 | B11: 46024 | C11: Bazaar Hai | D11: Jharkhand | E11: Jharkhand | F11: Gantry Crane | J11: CONTACTED | K11: Jay Shankar | L11: INDIAMART | M11: VIKRAM
A12: =ROW()-1 -> 11 | B12: 46024 | C12: IB Packaging | D12: Gujarat | E12: Gujarat | F12: Hoist | G12: electric chain hoists | H12: 9512036634 | I12: stores@ibpackaging.com | J12: CONTACTED | K12: PRAVIN PARMAR | L12: INDIAMART | M12: SAKSHI
A13: =ROW()-1 -> 12 | B13: 46024 | C13: Jignesh | D13: MUMBAI | E13: Maharashtra | F13: Hoist | G13: electric chain hoists | H13: 9920188712 | I13: jigneshkabani@gmail.com | J13: LOST | K13: Jignaesh | L13: TRADEINDIA | M13: SAKSHI
A14: =ROW()-1 -> 13 | B14: 46024 | C14: BHASKAR INDUSTRIES | D14: MUMBAI | E14: Maharashtra | F14: EOT Crane | G14: EOT Crane | H14: 9820722335 | I14: bhaskarindustries21@gmail.com | J14: CONTACTED | K14: Vivek B Boritkar | L14: TRADEINDIA | M14: VIKRAM
A15: =ROW()-1 -> 14 | B15: 46024 | C15: Arcelor Mittal Nippon Steel India | D15: Kanti | E15: Madhya Pradesh | F15: EOT Crane | G15: Eot cranes | H15: 7489916223 | I15: sahuabhishekkumar022@gmail.com | J15: CONTACTED | K15: Abhi Sahu | L15: TRADEINDIA | M15: VIKRAM
A16: =ROW()-1 -> 15 | B16: 46024 | C16: Psr enterprise | D16: Hyderabad | E16: Telangana | F16: Hoist | G16: Electric wire rope hoist | H16: 9010709926 | I16: srikanthreddy9926@gmail.com | J16: LOST | K16: Shrikant reddy | L16: TRADEINDIA | M16: SAKSHI
A17: =ROW()-1 -> 16 | B17: 46025 | C17: Advance Tooling Solution | D17: Wagholi | E17: Maharashtra | F17: LCS | G17: 500kg LCS System with Support structure | H17: 8446050108/9881207098 | I17: raut.shailendra@gmail.com | J17: QUOTATION REQ. | K17: Shailendra raut | L17: REFRENCE | M17: RAVI | N17: LCS01SV | O17: 46024 | P17: 751651 | Q17: In Progress
A18: =ROW()-1 -> 17 | B18: 46025 | C18: A | D18: Karjat, Maharashtra, India | E18: Maharashtra | F18: Hoist | G18: Electric Hoist | H18: 7798333301 | I18: sonujohare25@gmail.com | J18: FAKE | K18: Ganesh Johare | L18: INDIAMART | M18: SAKSHI
A19: =ROW()-1 -> 18 | B19: 46025 | C19: THE SECRET WONDERS | D19: Karur, Tamil Nadu, India | E19: Tamil Nadu | F19: Gantry Crane | G19: Portable Gantry Cranes | H19: 9786043717 | I19: kameshsaravanan07@gmail.com | J19: CONTACTED | K19: Kamesh | L19: INDIAMART | M19: VIKRAM
A20: =ROW()-1 -> 19 | B20: 46025 | C20: Jai Bharat Roadways Corporation | D20: 1st Floor, Office No 111, Prestige Chamber, Kalyan Street, Carnac Bunder, Masjid Bunder, Mumbai, Maharashtra, India | E20: Maharashtra | F20: Gantry Crane | G20: Gantry Crane | H20: 9820444150 | I20: gautam.4@hotmail.com | J20: FAKE | K20: Pooja Jagdish Soni | L20: INDIAMART | M20: VIKRAM
A21: =ROW()-1 -> 20 | B21: 46026 | C21: Vrushali Panels & Electricals | D21: Varve Bk Pune | E21: Maharashtra | F21: Jib Crane | G21: 2MT Jib crane floor mounted | H21: 8660418059/9270726073 | I21: vrushalipanels@outlook.com | J21: LOST | K21: Vrushali | L21: INDIAMART | M21: VIVEK | O21: 46026 | P21: 515000 | Q21: Closed
A22: =ROW()-1 -> 21 | B22: 46026 | C22: SPM Metals | D22: No.150, Mariamman Kovil Street, Tiruppur, Tamil Nadu, India | E22: Tamil Nadu | F22: Others | G22: Industrial Floor Crane | H22: 9171000693 | I22: guru.june10@gmail.com | J22: FAKE | K22: Muthu Kumar Guruprasath | L22: INDIAMART
A23: =ROW()-1 -> 22 | B23: 46026 | C23: SJM Enterprises | D23: Survey No 2/15, Electricity No.215, Pillaganahalli Village, Uttarahalli Hobli, Bengaluru, Karnataka, India | E23: Telangana | F23: Others | G23: Industrial Floor Crane | H23: 9986786082 | I23: mjsenterprises18@yahoo.com | J23: FAKE | K23: Shuiab Ahmed | L23: INDIAMART
A24: =ROW()-1 -> 23 | B24: 46026 | C24: Titus engineering | D24: Bharuch, Gujarat, India | E24: Gujarat | F24: Hoist | G24: Electrical Wire Rope Hoist | H24: 8160301117 | I24: montumoyal957@gmail.com | J24: FAKE | K24: Montu Moyal | L24: INDIAMART
A25: =ROW()-1 -> 24 | B25: 46026 | C25: A | D25: Belagavi, Karnataka, India | E25: Telangana | F25: Hoist | G25: Electric Wire Rope Hoist 1000kg | H25: 9845737295 | J25: FAKE | K25: lohar | L25: INDIAMART
A26: =ROW()-1 -> 25 | B26: 46026 | C26: Shri Durga Oil Mill Kichha | D26: Rudrapur Road Near Fci Godown Kichha Udham Singh Nagar, Rudrapur, Uttarakhand, India | E26: Uttarakhand | F26: EOT Crane | G26: Industrial Cranes, 35 Ton | H26: 7022228073 | I26: shridurgaoilmills@gmail.com | J26: FAKE | K26: Abhinav Goyal | L26: INDIAMART
A27: =ROW()-1 -> 26 | B27: 46026 | C27: Sapco Brews India Private Limited | D27: UGF -19 Ozone Center Sector 12, Faridabad, Haryana, India | E27: Haryana | F27: EOT Crane | G27: Double Girder EOT Cranes | H27: 9910016500 | I27: sapcobrews@gmail.com | J27: FAKE | K27: Shirish Pandey | L27: INDIAMART
A28: =ROW()-1 -> 27 | B28: 46026 | C28: Labtech Analytical Solutions | D28: Mumbai, Maharashtra, India | E28: Maharashtra | F28: Hoist | G28: Trolley Hoists | H28: 9930195031 | I28: dinesh.verma607@gmail.com | J28: FAKE | K28: dinesh verma | L28: INDIAMART
A29: =ROW()-1 -> 28 | B29: 46026 | C29: Varma Printing Press | D29: Shivaji Road, Parbhani, Maharashtra, India | E29: Maharashtra | F29: EOT Crane | G29: Industrial Double Girder EOT Crane | H29: 9421866770 | I29: varmapress@gmail.com | J29: FAKE | K29: kedar verma | L29: INDIAMART
A30: =ROW()-1 -> 29 | B30: 46026 | C30: Perfect Auto Body Builders | D30: K-7, Opposite Chakan Oil Mil M.I.D.C Kupwad, Sangli, Maharashtra, India | E30: Maharashtra | F30: Others | G30: End Carriage System, Capacity: 2-50 Ton | H30: 9823205298 | I30: perfect_autobody@yahoo.co.in | J30: FAKE | K30: Yunus Beg | L30: INDIAMART
A31: =ROW()-1 -> 30 | B31: 46027 | C31: A | D31: Kalinga Nagar Industrial Area, Odisha, India | E31: Odisha | F31: EOT Crane | G31: Double Girder EOT Cranes | H31: 9438434636 | I31: bijaykumarsethy19@gmail.com | J31: FAKE | K31: Bijay Kumar Sethy | L31: INDIAMART
A32: =ROW()-1 -> 31 | B32: 46027 | C32: Unicast Alloys Private Limited | D32: Flat 104, C-Block, Avinashi Road, Coimbatore, Tamil Nadu, India | E32: Tamil Nadu | F32: Others | G32: End Carriage | H32: 9842325153 | I32: vasudevan@unitedgroupcompanies.com | J32: FAKE | K32: Vasudevan | L32: INDIAMART
A33: =ROW()-1 -> 32 | B33: 46027 | C33: PMAC | D33: Chengalpattu, Tamil Nadu, India | E33: Tamil Nadu | F33: Manipulator | G33: Industrial Manipulators | H33: 8637406968 | J33: CONTACTED | K33: THANISH KUMAR R R | L33: INDIAMART
A34: =ROW()-1 -> 33 | B34: 46027 | C34: Atrico Tools Shop | D34: Greater Noida, Uttar Pradesh, India | E34: Uttar Pradesh | F34: EOT Crane | G34: Single Girder EOT Cranes, 5-10 Ton | H34: 9319067400 | I34: attrico.sales4@gmail.com | J34: LOST | K34: Nidhi Bhati | L34: INDIAMART
A35: =ROW()-1 -> 34 | B35: 46027 | C35: J P Traders | D35: GALA NO 04,MARKET YARD ROAD, GULAB APPARTMENT, NEAR PARKALE BANGLOW,BARAMATI Shop No. I- 11, Phase 2,,411009,Baramati, Baramati, Maharashtra, India | E35: Maharashtra | F35: Hoist | G35: Electric Chain Hoist | H35: 9011221000 | I35: narayanpote000@gmail.com | J35: LOST | K35: Pote Narayan | L35: INDIAMART | M35: SAKSHI | N35: JAN-HT005SV | O35: 46028 | P35: 250000 | Q35: Closed
A36: =ROW()-1 -> 35 | B36: 46027 | C36: A | D36: Gandhinagar, Gujarat, India | E36: Gujarat | F36: Hoist | G36: Wire Rope Hoists | H36: 9199714691 | J36: CONTACTED | K36: Mukesh Kumar | L36: INDIAMART | M36: SAKSHI
A37: =ROW()-1 -> 36 | B37: 46027 | C37: Pedvak Cranes Pvt. Ltd | D37: Hyderabad | E37: Telangana | F37: Hoist | G37: Electric wire rope hoist | H37: 9553546688 | I37: purchase@pedvak.com | J37: FAKE | K37: s siva Prasada rao | L37: TRADEINDIA | M37: VIKRAM
A38: =ROW()-1 -> 37 | B38: 46028 | C38: GK Service | D38: 111a Agraharam Street Vengankudi Village Mannachanallur Taluk, Tiruchirappalli, Tamil Nadu, India | E38: Tamil Nadu | F38: Jib Crane | G38: Jib Cranes | H38: 9600783068 | I38: georgewashington580@gmail.com | J38: LOST | K38: George Washington | L38: INDIAMART | M38: VIKRAM
A39: =ROW()-1 -> 38 | B39: 46028 | C39: Advanced Bolting solutions | D39: Mumbai, Maharashtra, India | E39: Maharashtra | F39: Others | G39: Portable Crane | H39: 7400485286 | I39: dhananjay.warane@absgroup.in | J39: LOST | K39: Dhananjay Warane | L39: INDIAMART | M39: VIKRAM | Q39: PO Received
A40: =ROW()-1 -> 39 | B40: 46028 | C40: SILICA INFRA PROJECT | D40: New Delhi, Delhi, India | E40: Haryana | F40: Others | G40: 10 Ton Portal Gantry Crane | H40: 9217020493 | I40: nisha@silicagroup.co.in | J40: FAKE | K40: NISHA RAJPUT | L40: INDIAMART | M40: VIKRAM
A41: =ROW()-1 -> 40 | B41: 46028 | C41: Srikar Biotech Private Limited | D41: Nacharam, Secunderabad, Telangana, India | E41: Telangana | F41: EOT Crane | G41: EOT Crane | H41: 8008801969 | I41: support@srikargroup.com | J41: FAKE | K41: sanjay | L41: INDIAMART | M41: VIKRAM
A42: =ROW()-1 -> 41 | B42: 46028 | C42: A | D42: Ahmedabad, Gujarat, India | E42: Gujarat | F42: Hoist | G42: Chain Hoist Electric | H42: 9274248553 | J42: FAKE | K42: DEV ENGINEERING | L42: INDIAMART | M42: SAKSHI
A43: =ROW()-1 -> 42 | B43: 46028 | C43: A | D43: Jamshedpur, Jharkhand, India | E43: Jharkhand | F43: EOT Crane | G43: 3 Ton Single Girder EOT Crane Manf. | H43: 9026480547 | I43: souravmishra0310@gmail.com | J43: FAKE | K43: Sourav | L43: INDIAMART | M43: VIKRAM
A44: =ROW()-1 -> 43 | B44: 46028 | C44: A | D44: Ahmedabad, Gujarat, India | E44: Gujarat | F44: Others | G44: Portable Cranes | H44: 8200861993 | J44: NOT INTERESTED | K44: gopali | L44: INDIAMART | M44: VIKRAM
A45: =ROW()-1 -> 44 | B45: 46028 | C45: The Globet Crane Industries | D45: Plot No 283, Ground Floor, Pocket - B, DSIDC Sector - 4, Bawana Industrial Area, North West Delhi,, New Delhi, Delhi, India | E45: Haryana | F45: EOT Crane | G45: Cranes, | H45: 8851348366 | I45: neerajgupta20241988@gmail.com | J45: LOST | K45: Neeraj Gupta | L45: INDIAMART | M45: VIKRAM
A46: =ROW()-1 -> 45 | B46: 46028 | C46: Skmd Electrica | F46: EOT Crane | G46: Eot cranes | H46: 9113980902 | I46: swamyss280794@gimal.com | J46: FAKE | K46: Rangaswamy s | L46: TRADEINDIA | M46: VIKRAM
A47: =ROW()-1 -> 46 | B47: 46029 | C47: Sangita industries | D47: Uran Islampur, Maharashtra, India | E47: Maharashtra | F47: Jib Crane | G47: jib crane | H47: 8080347767 | I47: abhijeetshinde3303@gmail.com | J47: NOT INTERESTED | K47: Abhijeet Shinde | L47: INDIAMART | M47: VIKRAM
A48: =ROW()-1 -> 47 | B48: 46029 | C48: Poltary | D48: Pune, Maharashtra, India | E48: Maharashtra | F48: EOT Crane | G48: Material Handling System | H48: 9890991147 | I48: ajittambe@yahoo.com | J48: FAKE | K48: ajeet | L48: INDIAMART | M48: VIKRAM
A49: =ROW()-1 -> 48 | B49: 46029 | C49: abhishek mobile | D49: Hoshangabad, Madhya Pradesh, India | E49: Madhya Pradesh | F49: LCS | G49: X Y Rail System | H49: 9340070354 | I49: rajkushwahasm@gmail.com | J49: NOT RECEIVED | K49: abhishek mobile | L49: INDIAMART | M49: VIKRAM
A50: =ROW()-1 -> 49 | B50: 46029 | C50: Vilas Transcore Limited | D50: Vadodara, Gujarat, India | E50: Gujarat | F50: LCS | G50: Kbk Light Crane System | H50: 9429314211 | I50: ashishpa23@yahoo.com | J50: NOT RECEIVED | K50: ashish patel | L50: INDIAMART | M50: VIKRAM
A51: =ROW()-1 -> 50 | B51: 46029 | C51: Earth Acquirer Engineering Corporation | D51: 111,VIHAV SUPRIMES,OPP ISKON HEIGHTS,Vadodara Building No. 207, Manjalpur,390011,Vadodara, Vadodara, Gujarat, India | E51: Gujarat | F51: EOT Crane | G51: Overhead Crane | H51: 9898036799 | I51: earthacquirer@gmail.com | J51: NOT INTERESTED | K51: Himanshu Thakkar | L51: INDIAMART | M51: VIKRAM
A52: =ROW()-1 -> 51 | B52: 46029 | C52: AV Cranes | D52: Room No. 5, Sunita Niwas, Road No 16, Kisan Nagar No 2, Near Shiv Mandir, Thane, Maharashtra, India | E52: Maharashtra | F52: EOT Crane | G52: Material Handling Systems | H52: 9892324713 | I52: tulsirao.ob@gmail.com | J52: NOT RECEIVED | K52: Tulsirao Bhaskarrao Obinindi | L52: INDIAMART | M52: VIKRAM
A53: =ROW()-1 -> 52 | B53: 46029 | C53: MAYURESH ENGINEERING | D53: Pirangut | E53: Maharashtra | F53: Hoist | G53: Pneumatic Hoist | H53: 8888060751 | I53: mayureshengineers.purchase@gmail.com | J53: LOST | K53: MAIL | L53: MAIL | M53: SAKSHI | N53: JAN-HT06SV | O53: 46029 | P53: 365268 | Q53: Closed
A54: =ROW()-1 -> 53 | B54: 46029 | C54: Siddheshwar Iron And Steel Pvt. Ltd. | D54: Plot No.29/2/B, At Post Khed, TQ Norh Solapur, Solapur, Maharashtra, India | E54: Maharashtra | F54: Others | H54: 9860710951 | I54: beskarumar@gmail.com | J54: NOT INTERESTED | K54: Umar Beskar | L54: INDIAMART
A55: =ROW()-1 -> 54 | B55: 46029 | C55: M. J. Cement Products | D55: 1223,Salgaon,Jambharmala,Mkg Road,Kudal,Sindhudurg, Kudal, Maharashtra, India | E55: Maharashtra | F55: Jib Crane | G55: Pillar Mounted Jib Crane | H55: 9765937379 | J55: NOT RECEIVED | K55: Himmat Bhimji Patel | L55: INDIAMART | M55: VIKRAM
A56: =ROW()-1 -> 55 | B56: 46029 | C56: shree krishna metal work | D56: Pune, Maharashtra, India | E56: Maharashtra | F56: Gantry Crane | G56: Industrial Gantry Crane Solutions | H56: 9156273029 | I56: abhay9156273029@gmail.com | J56: NOT RECEIVED | K56: Abhay | L56: INDIAMART | M56: VIKRAM
A57: =ROW()-1 -> 56 | B57: 46029 | C57: Yansefu Inks & Coatings Pvt. Ltd. | D57: Alwar, Rajasthan, India | E57: Rajasthan | F57: Manipulator | G57: Industrial Manipulators | H57: 9983556485 | I57: mvnn19@gmail.com | J57: NOT INTERESTED | K57: Vinod Kumar | L57: INDIAMART | M57: VIKRAM
A58: =ROW()-1 -> 57 | B58: 46029 | C58: Poltary | E58: Haryana | F58: EOT Crane | H58: 6379537625 | I58: jrctradingworkmate@gmail.com | J58: NOT RECEIVED | K58: raja | L58: INDIAMART | M58: VIVEK
A59: =ROW()-1 -> 58 | B59: 46029 | C59: Economy Process Solutions Pvt. Ltd | D59: khopoli | E59: Maharashtra | F59: Hoist | G59: Offer for Supply of CHAIN PULLY BLOCK 5 TON | H59: 8828326358 | I59: Ratish.Waghmare@economysolutions.in | J59: QUOTATION REQ. | K59: Ratish | L59: MAIL | M59: SAKSHI | N59: Jan-OQ01SV | O59: 46029 | P59: 80520 | Q59: Clarification Pending
A60: =ROW()-1 -> 59 | B60: 46029 | C60: A | D60: bihar | E60: Bihar | F60: EOT Crane | G60: Eot cranes | H60: 9006006960 | I60: deepakkumarsah6960@gmail.com | J60: FAKE | K60: deepak kumar | L60: TRADEINDIA | M60: VIVEK
A61: =ROW()-1 -> 60 | B61: 46029 | C61: A | D61: pune | E61: Maharashtra | F61: EOT Crane | G61: Eot cranes | H61: 9225658662 | J61: FAKE | K61: Balkrishna Suresh Shirke | L61: TRADEINDIA | M61: VIVEK
A62: =ROW()-1 -> 61 | B62: 46029 | C62: A | D62: Nagpur | E62: Maharashtra | F62: LCS | G62: light crane system | H62: 7774044007 | I62: rahulraju.ra2@gmail.com | J62: FAKE | K62: rahul raju | L62: TRADEINDIA | M62: VIKRAM
A63: =ROW()-1 -> 62 | B63: 46030 | C63: ACE COATING INDIA PVT LTD | D63: Bhosari | E63: Maharashtra | F63: Hoist | G63: Flame Proof Hoist | H63: 97306 21899/ 90498 11125‬ | I63: projects@aceindia.co.in' | J63: QUOTATION REQ. | K63: REFRENCE | L63: MAIL | M63: RAVI | N63: JAN-HT007SV | O63: 46030 | P63: 518221 | Q63: Quotation Sent | S63: called multiple times never received calles
A64: =ROW()-1 -> 63 | B64: 46030 | C64: A | D64: mumbai | E64: Maharashtra | F64: EOT Crane | G64: single girder eot cranes'. | H64: 9820007885 | I64: bhasin_batt@hotmail.com | J64: FAKE | K64: rajeev basin | L64: TRADEINDIA | M64: VIKRAM
A65: =ROW()-1 -> 64 | B65: 46032 | C65: shree motar garage | D65: Paranda | E65: Maharashtra | F65: EOT Crane | G65: Single girder eot cranes | H65: 9975188155 | I65: moneshwarmore7020@gmail.com | J65: FAKE | K65: moneshwar more | L65: TRADEINDIA
A66: =ROW()-1 -> 65 | B66: 46032 | C66: AEROCOM AUTOMTIVES PVT. LTD | D66: Nagpur | E66: Maharashtra | F66: Jib Crane | G66: jib crane | H66: 9372395427 | I66: kejariwaldinesh@gmail.com | J66: FAKE | K66: DINESH KEJARIWAL | L66: TRADEINDIA | M66: SAKSHI
A67: =ROW()-1 -> 66 | B67: 46032 | C67: KIRLOSKAR PNEUMATICS CO. LTD | D67: Pune | E67: Maharashtra | F67: Jib Crane | G67: Jib Crane of 1000KG Capacity | H67: 99 2242 4143 | I67: 'yogesh.patil@kirloskar.com' | J67: QUOTATION REQ. | K67: Yogesh Patil | L67: MAIL | M67: SAKSHI | N67: JAN-HT08SV | O67: 46032 | P67: 322916 | Q67: In Progress
A68: =ROW()-1 -> 67 | B68: 46032 | C68: SMH RAIL INDIA PVT LTD | D68: Hydrabad | E68: Telangana | F68: Jib Crane | G68: JibCrane of 1MT & 2MT Capacity | H68: 9494261947 | I68: srikanth@shmrail.com.my | J68: WIN | K68: Srikantha | L68: MAIL | M68: VIKRAM | N68: JAN-JC05SV | O68: 46032 | P68: 1235000 | Q68: On Hold
A69: =ROW()-1 -> 68 | B69: 46032 | C69: ENDO KOGYO INDIA LTD. | D69: Pune | E69: Maharashtra | F69: Jib Crane | G69: of Jib Crane of 250kg & 500kg Capacity | H69: 8600120115 | I69: 'Akshay Salunkhe' <eki1@endo-india.co.in> | J69: WIN | K69: Akshay | L69: MAIL | M69: RAVI | N69: JAN-JC06SV | O69: 46033 | P69: 375000 | Q69: PO Received
A70: =ROW()-1 -> 69 | B70: 46033 | C70: Datta Electricals | D70: Bhosari | E70: Maharashtra | F70: EOT Crane | G70: SG EOT Crane of 10MT Capacity | H70: 9975604234 | I70: 'Datta Electricals' <electricals@dattaenterprises.co.in> | J70: QUOTATION REQ. | K70: Mangalgatti.M.J | L70: MAIL | M70: MALLESH | N70: JAN-SG02SV | O70: 46033 | P70: 1600000 | Q70: On Hold | S70: ot receiving
A71: =ROW()-1 -> 70 | B71: 46032 | C71: Pooja Enterprises | D71: H No 5434 Kolhapur, Kolhapur, Maharashtra, India | E71: Maharashtra | F71: Hoist | G71: Wire Rope Hoists | H71: 8208307641 | I71: sankpal143@gmail.com | J71: FAKE | K71: New | L71: TRADEINDIA | M71: SAKSHI
A72: =ROW()-1 -> 71 | B72: 46033 | C72: hero cycles | D72: Bageshwar, Uttarakhand, India | E72: Uttarakhand | F72: Manipulator | G72: Pneumatic Manipulator | H72: 9068699113 | I72: kamalpandey3005@gmail.com | J72: NOT INTERESTED | K72: Kamal Pandey | L72: INDIAMART | M72: VIKRAM
A73: =ROW()-1 -> 72 | B73: 46033 | C73: A | D73: Gandhidham, Gujarat, India | E73: Gujarat | F73: Hoist | G73: 3 Ton Electric Chain Hoist | H73: 9574950253 | I73: vijaypatel.mech08@gmail.com | J73: FAKE | K73: Vijaypatel | L73: INDIAMART | M73: SAKSHI
A74: =ROW()-1 -> 73 | B74: 46034 | C74: Infofil | D74: Bharuch | E74: Gujarat | F74: Jib Crane | H74: 9227130762 | I74: nnayal@gmail.com | J74: FAKE | K74: Nirpendra Singh Nayal | L74: TRADEINDIA | M74: VIKRAM
A75: =ROW()-1 -> 74 | B75: 46034 | C75: A | D75: Perundurai | E75: Tamil Nadu | F75: Hoist | G75: ms electric chain hoist | H75: 9952128894 | J75: FAKE | K75: RAMESH NAIK | L75: TRADEINDIA | M75: SAKSHI
A76: =ROW()-1 -> 75 | B76: 46034 | C76: Mit College Of Engineering | D76: Pune, Maharashtra, India | E76: Maharashtra | F76: Monorail | G76: Industrial Monorail Crane | H76: 8484094521 | I76: abhijeet.santosh.gawade@gmail.com | J76: FAKE | K76: Abhijeet Santosh Gawade | L76: INDIAMART | M76: VIVEK
A77: =ROW()-1 -> 76 | B77: 46034 | C77: Saharsh Technocrafts | D77: 295/1/4, Bicholi Hapsi, Bicholi Hapsi Road, Indore, Madhya Pradesh, India | F77: Hoist | G77: Industrial Manipulators | H77: 9978445856 | I77: mantrisankum@rediffmail.com | J77: CONTACTED | K77: Sanjay Mantri | L77: INDIAMART | M77: VIVEK
A78: =ROW()-1 -> 77 | B78: 46034 | C78: Siddhivinayak Distributors | D78: 115,Shop, No Vighnahar, Sankul, Narayangaon, Junnar,, Pune, Maharashtra, India | E78: Maharashtra | F78: Hoist | G78: Electric Chain Hoist | H78: 9860710813 | I78: sthorat207@gmail.com | J78: FAKE | K78: Sagar Kerbhau Thorat | L78: INDIAMART | M78: SAKSHI
A79: =ROW()-1 -> 78 | B79: 46034 | C79: P. G Conversions | D79: Patel Industrial Estate, Building No. 5, Unit No. 110 Gaurai Pada, Vasai, Maharashtra, India | E79: Maharashtra | F79: Hoist | H79: 9969388306 | I79: pg_conversions@yahoo.com | J79: FAKE | K79: Aashish Goradia | L79: INDIAMART | M79: SAKSHI
A80: =ROW()-1 -> 79 | B80: 46035 | C80: Nisha Agarbaati | D80: Ahmedabad | E80: Gujarat | F80: EOT Crane | G80: EOT Crane | H80: 7622826951 | I80: vikrambhaichaudhary1994@gmail.com | J80: FAKE | K80: Rutvik Chaudhary | L80: TRADEINDIA | M80: VIKRAM
A81: =ROW()-1 -> 80 | B81: 46035 | C81: D Scon Construction Private Limited | D81: mumbai | E81: Maharashtra | F81: EOT Crane | G81: Eot crane | I81: dsconconstruction@gmail.com | J81: FAKE | K81: DIPAK SHIRKE | L81: TRADEINDIA | M81: VIKRAM
A82: =ROW()-1 -> 81 | B82: 46035 | C82: A | D82: Tirupati | E82: Andhra Pradesh | F82: EOT Crane | G82: Eot cranes | H82: 7218945619 | J82: CONTACTED | K82: Rahman Ali | L82: TRADEINDIA | M82: VIVEK
A83: =ROW()-1 -> 82 | B83: 46035 | C83: Vertex Automation System Private Limited | D83: H-39 Surajpur Industrial Area Site-c Greater Noida Gautam Buddha Nagar New Delhi, Greater Noida, Uttar Pradesh, India | E83: Uttar Pradesh | F83: Manipulator | G83: Industrial Manipulators | H83: 7053827370 | I83: gauravan92@gmail.com | J83: CONTACTED | K83: Gourav Anand | L83: INDIAMART | M83: VIKRAM
A84: =ROW()-1 -> 83 | B84: 46035 | C84: Yogi Enterprises | D84: S No 35, Dattawadi, Akurdi, Haveli, Pimpri Chinchwad, Maharashtra, India | E84: Maharashtra | F84: Gantry Crane | G84: Portable Gantry Crane | H84: 8381068403 | J84: FAKE | K84: sachin | L84: INDIAMART | M84: VIVEK
A85: =ROW()-1 -> 84 | B85: 46035 | C85: Arm welder pvt Ltd | D85: Bhosari | E85: Maharashtra | F85: Manipulator | G85: Manipulator of 400KG Capacity | H85: 7420910285 | I85: 'Swapnil Kashid' <automation.bo@armwelders.com> | J85: WIN | K85: Swapnil Kashid | L85: EXISTING CUS. | M85: VIKRAM | N85: Jan-MN01SV | O85: 46035 | P85: 1350000 | Q85: PO Received | S85: within 2-3days 23-01
A86: =ROW()-1 -> 85 | B86: 46035 | C86: WIPRO PARI | D86: VILLAGE DHANGARWADI | E86: Maharashtra | F86: Jib Crane | G86: Jib Crane of 500kg 1T & 5T | H86: 7709189528 | I86: e' <vishwajeet.b@wipropari.com> | J86: QUOTATION REQ. | K86: maruti keskar | L86: MAIL | M86: RAVI | N86: JAN-JC08SV | O86: 46035 | P86: 1480000 | Q86: Discussion Ongoing
A87: =ROW()-1 -> 86 | B87: 46035 | C87: SGP ELECTROPNEUMATICS | D87: Pune | E87: Maharashtra | F87: Jib Crane | G87: Jib Crane of 500kg 1T & 5T | H87: 9960692754 | I87: 'sales@gpe.net.in' | J87: QUOTATION REQ. | K87: Kiran | L87: MAIL | M87: RAVI | N87: JAN-JC09SV | O87: 46035 | P87: 1480000 | Q87: IN PROGRESS | S87: need tackle
A88: =ROW()-1 -> 87 | B88: 46035 | C88: PARC ROBOTICS SYSTEM PVT LTD | D88: CHAKAN PUNE | E88: Maharashtra | F88: Hoist | G88: Electric chain Hoist of 250kg | H88: 7720050063 | I88: 'parcpurchase@parcrobotics.in' | J88: WIN | K88: dnynesh | L88: REFRENCE | M88: RAVI | N88: Jan-JC09SV | O88: 46035 | P88: 83500 | Q88: PO Received
A89: =ROW()-1 -> 88 | B89: 46035 | C89: MR Nirmal Industries | D89: S no B 21,HNO 4060,Ramchandra nagar,Dhanakawadi Kolewadi Road, Jambhulwadi Lake, Jambhulwadi,411043,Pune, Pune, Maharashtra, India | E89: Maharashtra | F89: Others | G89: Electric Floor Cranes, 5 Ton | H89: 9881929797 | I89: sandypoman99@gmail.com | J89: FAKE | K89: Vishal Poman | L89: INDIAMART | M89: VIVEK | Q89: NA
A90: =ROW()-1 -> 89 | B90: 46036 | C90: BAHRAIN WORKSHOP COMPANY | D90: KINGDOM OF BAHRAIN | E90: International | F90: Others | G90: Design of Support structure of EOT Crane | I90: 'gk@bwcbah.com' | J90: WIN | K90: Ganesh | L90: MAIL | M90: RAVI | N90: JAN-OQ008SV | O90: 46036 | P90: =500*91.69 -> 45845 | Q90: PO Received
A91: =ROW()-1 -> 90 | B91: 46036 | C91: RIJ ENGINEERING PVT. LTD. (FORGE DIV.), | D91: Chakan | E91: Maharashtra | F91: Monorail | G91: Monorail System | I91: 'maint.ht@rijeng.in' | J91: WIN | K91: Dass | L91: EXISTING CUS. | M91: VIKRAM | N91: Dec-MN003SV--RE | O91: 46036 | P91: 120000 | Q91: PO Received
A92: =ROW()-1 -> 91 | B92: 46036 | C92: BAHRAIN WORKSHOP COMPANY | D92: KINGDOM OF BAHRAIN | E92: International | F92: Others | G92: Transfer trolley | I92: 'gk@bwcbah.com' | J92: QUOTATION REQ. | K92: Ganeshsir | L92: MAIL | M92: RAVI | N92: Jan-OQ09SV | O92: 46036 | P92: 12820 | Q92: IN PROGRESS
A93: =ROW()-1 -> 92 | B93: 46037 | C93: A | D93: Karnataka | E93: Telangana | F93: EOT Crane | G93: Eot cranes | H93: 7874018055 | I93: laxmichand.raigar43@gmail.com | J93: FAKE | K93: Laxmi Chand Tanwer | L93: TRADEINDIA | M93: VIKRAM
A94: =ROW()-1 -> 93 | B94: 46038 | C94: hazrat baba tajuddin trust | D94: Nagpur | E94: Maharashtra | F94: EOT Crane | G94: Electric Single Girder Eot Crane | H94: 9372443264 | I94: iqbalveljee@hotmail.com | J94: FAKE | K94: Iqbal Veljee | L94: TRADEINDIA | M94: VIVEK
A95: =ROW()-1 -> 94 | B95: 46038 | C95: Premier Rolling Shutters | D95: Erode | E95: Tamil Nadu | F95: EOT Crane | G95: EOT Crane | H95: 9842358909 | I95: babupremiershutters1099@gmail.com | J95: NOT RECEIVED | K95: Velligiri babu | L95: TRADEINDIA | M95: VIVEK
A96: =ROW()-1 -> 95 | B96: 46038 | C96: A | D96: Bellary | E96: Telangana | F96: EOT Crane | G96: industrial cranes | H96: 9945680754 | J96: FAKE | K96: abdul | L96: TRADEINDIA | M96: VIVEK | S96: FAKE
A97: =ROW()-1 -> 96 | B97: 46038 | C97: FOUNDRY EQUIPMENT ENGINEERS | D97: Kolhapur - Maharashtra | E97: Maharashtra | F97: Manipulator | G97: pneumatic manipulator | H97: 7028935010 | I97: foundryequipment77@gmail.com | J97: FAKE | K97: RAVI CHIRPUTKAR | L97: TRADEINDIA | M97: VIKRAM | S97: COMPLETED
A98: =ROW()-1 -> 97 | B98: 46038 | C98: Dhanaprakash Industrial Corporation | D98: Pimpri | E98: Maharashtra | F98: Hoist | G98: electric wire rope hoist | H98: 7248929231 | J98: FAKE | K98: sakshi shinde | L98: TRADEINDIA | M98: SAKSHI
A99: =ROW()-1 -> 98 | B99: 46038 | C99: Aomegaa Tech Fencing Industry | D99: D.No.3/35, Sundakapatti, Vadamalampatti, Krishnagiri, Tamil Nadu, India | E99: Tamil Nadu | F99: Jib Crane | G99: Jib Cranes | H99: 9025750759 | I99: kirubataniesh114@gmail.com | J99: NOT INTERESTED | K99: Kirubanandhan | L99: INDIAMART | M99: VIVEK
A100: =ROW()-1 -> 99 | B100: 46038 | C100: Sri Vinayaka Hydraulic | D100: Opp Santhi Theatre 120 3 711 P.n.road Sivasakthi Complex Tirupur, Tiruppur, Tamil Nadu, India | E100: Tamil Nadu | F100: Gantry Crane | G100: 5 Ton Single Girder Gantry Crane | H100: 9791681398 | I100: srivinayakahydraulic@gmail.com | J100: FAKE | K100: G Anandaraj | L100: INDIAMART | M100: VIVEK
...

Sheet Dashboard
B2: SALES DEPARTMENT | W2: =TODAY() -> 46197
B3: TOTAL NO LEADS | D3: TODAY | E3: YESTURDAY | F3: DAY BRFORE | H3: TOTAL VALUE: | I3: PO RECEIVED | K3: YEAR | L3: MONTH | N3: NEW LEADS
B4: ='DATA SHEET'!$S$17 -> 828 | D4: ='DATA SHEET'!L11 -> 0 | E4: ='DATA SHEET'!L12 -> 8 | F4: ='DATA SHEET'!L17 -> 11 | H4: ='DATA SHEET'!L14 -> 5.100305e+08 | I4: ='DATA SHEET'!L15 -> 33905258 | K4: ='DATA SHEET'!L16 -> 828 | L4: ='DATA SHEET'!L13 -> 287 | N4: ='DATA SHEET'!H11 -> 8

Sheet DASHBOARD (2)
AE1: APRIL
B2: CURRENT ORDER | C2: #ERROR! | D2: Target | E2: 400000000 | G2: Monthly Target | H2: =E2/12 -> 33333333 | J2: DATA SHEET | N2: ORDER TRACKER | Q2: PREVIOUS MONTHS | AE2: MAY
B3: MONTHS | C3: VALUE | D3: PLANNED | E3: DISPATCHED | F3: PENDING | G3: MONTHLY ORDER VALUE | H3: MESSAGES | J3: CONDITION | K3: ORDERS NO | L3: AMOUNT
B4: 46113 | C4: #ERROR! | D4: #ERROR! | E4: #ERROR! | F4: =D4-E4 -> #VALUE! | G4: =ABS($H$2-C4) -> #VALUE! | H4: =IF(C4<$H$2,"MORE ORDER REQUIRED", IF(C4>$H$2,"OVER ORDER", "TARGET MATCHED")) -> OVER ORDER | I4: 1 | J4: PO PENDING | K4: #ERROR! | L4: #ERROR! | N4: HOLD | O4: =COUNTIF(M17:M927,"HOLD") -> 0 | Q4: BILLED | R4: {=SUMPRODUCT((TEXT(K17:K19, "mmmm") = "August") * (M17:M19 = "DISPATCHED") * E17:E18)} -> #N/A | AE4: JULY
B5: 46143 | C5: #ERROR! | D5: #ERROR! | E5: #ERROR! | F5: =D5-E5 -> #VALUE! | G5: =ABS($H$2-C5) -> #VALUE! | H5: =IF(C5<$H$2,"MORE ORDER REQUIRED", IF(C5>$H$2,"OVER ORDER", "TARGET MATCHED")) -> OVER ORDER | I5: 2 | J5: IN DESIGN | K5: #ERROR! | L5: #ERROR! | AE5: AUGUST
B6: 46174 | C6: #ERROR! | D6: #ERROR! | E6: #ERROR! | F6: =D6-E6 -> #VALUE! | G6: =ABS($H$2-C6) -> #VALUE! | H6: =IF(C6<$H$2,"MORE ORDER REQUIRED", IF(C6>$H$2,"OVER ORDER", "TARGET MATCHED")) -> OVER ORDER | I6: 3 | J6: DISPATCHED | K6: #ERROR! | L6: #ERROR! | AE6: SEPTEMBER
B7: 46204 | C7: #ERROR! | D7: #ERROR! | E7: #ERROR! | F7: =D7-E7 -> #VALUE! | G7: =ABS($H$2-C7) -> #VALUE! | H7: =IF(C7<$H$2,"MORE ORDER REQUIRED", IF(C7>$H$2,"OVER ORDER", "TARGET MATCHED")) -> OVER ORDER | I7: 4 | J7: IN PRODUCTION | K7: #ERROR! | L7: #ERROR! | AE7: OCTOBER
B8: 46235 | C8: #ERROR! | D8: #ERROR! | E8: #ERROR! | F8: =D8-E8 -> #VALUE! | G8: =ABS($H$2-C8) -> #VALUE! | H8: =IF(C8<$H$2,"MORE ORDER REQUIRED", IF(C8>$H$2,"OVER ORDER", "TARGET MATCHED")) -> OVER ORDER | I8: 5 | J8: BILL PENDING | K8: #ERROR! | L8: #ERROR! | AE8: NOVEMBER
B9: 46266 | C9: #ERROR! | D9: #ERROR! | E9: #ERROR! | F9: =D9-E9 -> #VALUE! | G9: =ABS($H$2-C9) -> #VALUE! | H9: =IF(C9<$H$2,"MORE ORDER REQUIRED", IF(C9>$H$2,"OVER ORDER", "TARGET MATCHED")) -> OVER ORDER | I9: 6 | J9: UNDER APPROVAL | K9: #ERROR! | L9: #ERROR! | AE9: DECEMBER
B10: 46296 | C10: #ERROR! | D10: #ERROR! | E10: #ERROR! | F10: =D10-E10 -> #VALUE! | G10: =ABS($H$2-C10) -> #VALUE! | H10: =IF(C10<$H$2,"MORE ORDER REQUIRED", IF(C10>$H$2,"OVER ORDER", "TARGET MATCHED")) -> OVER ORDER | I10: 7 | J10: HOLD | K10: #ERROR! | L10: #ERROR! | AE10: JANUARY
B11: 46327 | C11: #ERROR! | D11: #ERROR! | E11: #ERROR! | F11: =D11-E11 -> #VALUE! | G11: =ABS($H$2-C11) -> #VALUE! | H11: =IF(C11<$H$2,"MORE ORDER REQUIRED", IF(C11>$H$2,"OVER ORDER", "TARGET MATCHED")) -> OVER ORDER | I11: 8 | J11: UPDATE IT | K11: #ERROR! | L11: #ERROR! | AE11: FEBRUARY
B12: 46357 | C12: #ERROR! | D12: #ERROR! | E12: #ERROR! | F12: =D12-E12 -> #VALUE! | G12: =ABS($H$2-C12) -> #VALUE! | H12: =IF(C12<$H$2,"MORE ORDER REQUIRED", IF(C12>$H$2,"OVER ORDER", "TARGET MATCHED")) -> OVER ORDER | I12: 9 | J12: ORDERED | K12: #ERROR! | L12: #ERROR! | AE12: MARCH
B13: 46388 | C13: #ERROR! | D13: #ERROR! | E13: #ERROR! | F13: =D13-E13 -> #VALUE! | G13: =ABS($H$2-C13) -> #VALUE! | H13: =IF(C13<$H$2,"MORE ORDER REQUIRED", IF(C13>$H$2,"OVER ORDER", "TARGET MATCHED")) -> OVER ORDER | I13: 10
B14: 46419 | C14: #ERROR! | D14: #ERROR! | E14: #ERROR! | F14: =D14-E14 -> #VALUE! | G14: =ABS($H$2-C14) -> #VALUE! | H14: =IF(C14<$H$2,"MORE ORDER REQUIRED", IF(C14>$H$2,"OVER ORDER", "TARGET MATCHED")) -> OVER ORDER | I14: 11 | K14: TOTAL VALUE | L14: =L12+L11+L10+L9+L8+L7+L5 -> #VALUE!
B15: 46447 | C15: #ERROR! | D15: #ERROR! | E15: #ERROR! | F15: =D15-E15 -> #VALUE! | G15: =ABS($H$2-C15) -> #VALUE! | H15: =IF(C15<$H$2,"MORE ORDER REQUIRED", IF(C15>$H$2,"OVER ORDER", "TARGET MATCHED")) -> OVER ORDER
B16: ORDERS VALUE | C16: =SUM(C4:C15) -> 0 | D16: =SUM(D4:D15) -> 0 | E16: =SUM(E4:E15) -> 0 | F16: =SUM(F4:F15) -> #VALUE! | G16: =SUM(G4:G15) -> #VALUE! | L16: =SUM('DASHBOARD (2)'!$L$4:$L$12) -> 0 | N16: TOTAL PROJECTS | O16: =SUBTOTAL(103, A17:A920) -> 0 | Q16: BILLED | R16: {=SUMPRODUCT((TEXT(K17:K19, "mmmm") = "September") * (M17:M19 = "DISPATCHED") * E17:E18)} -> #N/A
C20: NEW | D20: WIN | E20: LOST | F20: CONTACTED | G20: NOT INTERESTED | H20: SITE VISIT REQ. | I20: QUOTATION REQ. | J20: NOT RECEIVED | K20: FAKE | L20: FULFILLED

Sheet DATA SHEET
C2: STATES | D2: No | G2: SALES OVERVIEW | K2: LEAD OWNER | L2: NO | N2: 📊 Weekly Dashboard (Mon–Sun) | R2: 📊 Yearly Dashboard (Jan–Dec 2026)
C3: Andhra Pradesh | D3: =COUNTIF('2026-2027'!E:E,"Andhra Pradesh") -> 8 | G3: REFRENCE | H3: =COUNTIF('2026-2027'!L:L, G3) -> 37 | K3: MALLESH | L3: =COUNTIF('2026-2027'!M:M, K3) -> 31 | N3: Day | O3: NOS | P3: Amount Formula | R3: Month | S3: NOS | T3: Amount Formula
C4: Arunachal Pradesh | D4: =COUNTIF('2026-2027'!E:E,"Andhra Pradesh") -> 8 | G4: EXISTING CUS. | H4: =COUNTIF('2026-2027'!L:L, G4) -> 22 | K4: RAVI | L4: =COUNTIF('2026-2027'!M:M, K4) -> 128 | N4: Monday | O4: =COUNTIFS('2026-2027'!B:B, TODAY()-WEEKDAY(TODAY(),2)+1) -> 11 | P4: =SUMIFS('2026-2027'!P:P, '2026-2027'!B:B, TODAY()-WEEKDAY(TODAY(),2)+1) -> 0 | R4: 46113 | S4: =COUNTIFS('2026-2027'!B:B,">="&DATE(2026,4,1),'2026-2027'!B:B,"<="&DATE(2026,4,30)) -> 270 | T4: =SUMIFS('2026-2027'!P:P,'2026-2027'!B:B,">="&DATE(2026,4,1),'2026-2027'!B:B,"<="&DATE(2026,4,30)) -> 1.7449773e+08
C5: Assam | D5: =COUNTIF('2026-2027'!E:E,"Assam") -> 8 | G5: MAIL | H5: =COUNTIF('2026-2027'!L:L, G5) -> 149 | K5: HARSH | L5: =COUNTIF('2026-2027'!M:M, K5) -> 0 | N5: Tuesday | O5: =COUNTIFS('2026-2027'!B:B, TODAY()-WEEKDAY(TODAY(),2)+1) -> 11 | P5: =SUMIFS('2026-2027'!P:P, '2026-2027'!B:B, TODAY()-WEEKDAY(TODAY(),2)+2) -> 0 | R5: 46143 | S5: =COUNTIFS('2026-2027'!B:B,">="&DATE(2026,5,1),'2026-2027'!B:B,"<="&DATE(2026,5,31)) -> 271 | T5: =SUMIFS('2026-2027'!P:P,'2026-2027'!B:B,">="&DATE(2026,5,1),'2026-2027'!B:B,"<="&DATE(2026,5,31)) -> 1.3944894e+08
C6: Bihar | D6: =COUNTIF('2026-2027'!E:E,"Bihar") -> 5 | G6: INDIAMART | H6: =COUNTIF('2026-2027'!L:L, G6) -> 332 | K6: VIVEK | L6: =COUNTIF('2026-2027'!M:M, K6) -> 462 | N6: Wednesday | O6: =COUNTIFS('2026-2027'!B:B, TODAY()-WEEKDAY(TODAY(),2)+1) -> 11 | P6: =SUMIFS('2026-2027'!P:P, '2026-2027'!B:B, TODAY()-WEEKDAY(TODAY(),2)+3) -> 0 | R6: 46174 | S6: =COUNTIFS('2026-2027'!B:B,">="&DATE(2026,6,1),'2026-2027'!B:B,"<="&DATE(2026,6,30)) -> 287 | T6: =SUMIFS('2026-2027'!P:P,'2026-2027'!B:B,">="&DATE(2026,6,1),'2026-2027'!B:B,"<="&DATE(2026,6,30)) -> 1.9608383e+08
C7: Chhattisgarh | D7: =COUNTIF('2026-2027'!E:E,"Chhattisgarh") -> 4 | G7: OUT SOURCE | H7: =COUNTIF('2026-2027'!L:L, G7) -> 1 | K7: SAKSHI | L7: =COUNTIF('2026-2027'!M:M, K7) -> 202 | N7: Thursday | O7: =COUNTIFS('2026-2027'!B:B, TODAY()-WEEKDAY(TODAY(),2)+1) -> 11 | P7: =SUMIFS('2026-2027'!P:P, '2026-2027'!B:B, TODAY()-WEEKDAY(TODAY(),2)+4) -> 0 | R7: 46204 | S7: =COUNTIFS('2026-2027'!B:B,">="&DATE(2026,7,1),'2026-2027'!B:B,"<="&DATE(2026,7,31)) -> 0 | T7: =SUMIFS('2026-2027'!P:P,'2026-2027'!B:B,">="&DATE(2026,7,1),'2026-2027'!B:B,"<="&DATE(2026,7,31)) -> 0
C8: Goa | D8: =COUNTIF('2026-2027'!E:E,"Goa") -> 6 | G8: TRADEINDIA | H8: =COUNTIF('2026-2027'!L:L, G8) -> 290 | N8: Friday | O8: =COUNTIFS('2026-2027'!B:B, TODAY()-WEEKDAY(TODAY(),2)+1) -> 11 | P8: =SUMIFS('2026-2027'!P:P, '2026-2027'!B:B, TODAY()-WEEKDAY(TODAY(),2)+5) -> 0 | R8: 46235 | S8: =COUNTIFS('2026-2027'!B:B,">="&DATE(2026,8,1),'2026-2027'!B:B,"<="&DATE(2026,8,31)) -> 0 | T8: =SUMIFS('2026-2027'!P:P,'2026-2027'!B:B,">="&DATE(2026,8,1),'2026-2027'!B:B,"<="&DATE(2026,8,31)) -> 0
C9: Gujarat | D9: =COUNTIF('2026-2027'!E:E,"Gujarat") -> 36 | K9: DASH | N9: Saturday | O9: =COUNTIFS('2026-2027'!B:B, TODAY()-WEEKDAY(TODAY(),2)+1) -> 11 | P9: =SUMIFS('2026-2027'!P:P, '2026-2027'!B:B, TODAY()-WEEKDAY(TODAY(),2)+6) -> 0 | R9: 46266 | S9: =COUNTIFS('2026-2027'!B:B,">="&DATE(2026,9,1),'2026-2027'!B:B,"<="&DATE(2026,9,30)) -> 0 | T9: =SUMIFS('2026-2027'!P:P,'2026-2027'!B:B,">="&DATE(2026,9,1),'2026-2027'!B:B,"<="&DATE(2026,9,30)) -> 0
C10: Haryana | D10: =COUNTIF('2026-2027'!E:E,"Haryana") -> 10 | G10: INQUIRY | H10: NOS | K10: LEADS DATA | L10: VALUE | N10: Sunday | O10: =COUNTIFS('2026-2027'!B:B, TODAY()-WEEKDAY(TODAY(),2)+1) -> 11 | P10: =SUMIFS('2026-2027'!P:P, '2026-2027'!B:B, TODAY()-WEEKDAY(TODAY(),2)+7) -> 0 | R10: 46296 | S10: =COUNTIFS('2026-2027'!B:B,">="&DATE(2026,10,1),'2026-2027'!B:B,"<="&DATE(2026,10,31)) -> 0 | T10: =SUMIFS('2026-2027'!P:P,'2026-2027'!B:B,">="&DATE(2026,10,1),'2026-2027'!B:B,"<="&DATE(2026,10,31)) -> 0
C11: Himachal Pradesh | D11: =COUNTIF('2026-2027'!E:E,"Himachal Pradesh") -> 1 | G11: NEW | H11: =COUNTIF('2026-2027'!J:J, G11) -> 8 | K11: TODAY | L11: =COUNTIF('2026-2027'!B:B, TODAY()) -> 0 | N11: =SUBTOTAL(109,N4:N10) -> 0 | O11: =SUBTOTAL(109,O4:O10) -> 77 | P11: =SUM(P4:P10) -> 0 | R11: 46327 | S11: =COUNTIFS('2026-2027'!B:B,">="&DATE(2026,11,1),'2026-2027'!B:B,"<="&DATE(2026,11,30)) -> 0 | T11: =SUMIFS('2026-2027'!P:P,'2026-2027'!B:B,">="&DATE(2026,11,1),'2026-2027'!B:B,"<="&DATE(2026,11,30)) -> 0
C12: Jharkhand | D12: =COUNTIF('2026-2027'!E:E,"Jharkhand") -> 3 | G12: WIN | H12: =COUNTIF('2026-2027'!J:J, G12) -> 28 | K12: YESTURDAY | L12: =COUNTIF('2026-2027'!B:B, TODAY()-1) -> 8 | R12: 46357 | S12: =COUNTIFS('2026-2027'!B:B,">="&DATE(2026,12,1),'2026-2027'!B:B,"<="&DATE(2026,12,31)) -> 0 | T12: =SUMIFS('2026-2027'!P:P,'2026-2027'!B:B,">="&DATE(2026,12,1),'2026-2027'!B:B,"<="&DATE(2026,12,31)) -> 0
C13: Telangana | D13: =COUNTIF('2026-2027'!E:E,"Telangana") -> 35 | G13: LOST | H13: =COUNTIF('2026-2027'!J:J, G13) -> 14 | K13: MONTHS | L13: =COUNTIFS('2026-2027'!B:B, ">="&EOMONTH(TODAY(),-1)+1, '2026-2027'!B:B, "<="&EOMONTH(TODAY(),0)) -> 287 | R13: 46388 | S13: =COUNTIFS('2026-2027'!B:B,">="&DATE(2026,12,1),'2026-2027'!B:B,"<="&DATE(2026,12,31)) -> 0 | T13: =SUMIFS('2026-2027'!P:P,'2026-2027'!B:B,">="&DATE(2026,12,1),'2026-2027'!B:B,"<="&DATE(2026,12,31)) -> 0
C14: Kerala | D14: =COUNTIF('2026-2027'!E:E,"Kerala") -> 3 | G14: CONTACTED | H14: =COUNTIF('2026-2027'!J:J, G14) -> 62 | K14: TOTAL VALUE | L14: =SUM(T4:T16) -> 5.100305e+08 | R14: 46419 | S14: =COUNTIFS('2026-2027'!B:B,">="&DATE(2026,12,1),'2026-2027'!B:B,"<="&DATE(2026,12,31)) -> 0 | T14: =SUMIFS('2026-2027'!P:P,'2026-2027'!B:B,">="&DATE(2026,12,1),'2026-2027'!B:B,"<="&DATE(2026,12,31)) -> 0
C15: Madhya Pradesh | D15: =COUNTIF('2026-2027'!E:E,"Madhya Pradesh") -> 17 | G15: NOT INTERESTED | H15: =COUNTIF('2026-2027'!J:J, G15) -> 119 | K15: PO RECEIVED | L15: =SUMIFS('2026-2027'!P:P, '2026-2027'!Q:Q, "PO Received") -> 33905258 | R15: 46447 | S15: =COUNTIFS('2026-2027'!B:B,">="&DATE(2026,12,1),'2026-2027'!B:B,"<="&DATE(2026,12,31)) -> 0 | T15: =SUMIFS('2026-2027'!P:P,'2026-2027'!B:B,">="&DATE(2026,12,1),'2026-2027'!B:B,"<="&DATE(2026,12,31)) -> 0
C16: Maharashtra | D16: =COUNTIF('2026-2027'!E:E,"Maharashtra") -> 453 | G16: SITE VISIT REQ. | H16: =COUNTIF('2026-2027'!J:J, G16) -> 3 | K16: YEAR | L16: =SUBTOTAL(109,S4:S12) -> 828 | R16: 46478 | S16: =COUNTIFS('2026-2027'!B:B,">="&DATE(2026,12,1),'2026-2027'!B:B,"<="&DATE(2026,12,31)) -> 0 | T16: =SUMIFS('2026-2027'!P:P,'2026-2027'!B:B,">="&DATE(2026,12,1),'2026-2027'!B:B,"<="&DATE(2026,12,31)) -> 0
C17: Manipur | D17: =COUNTIF('2026-2027'!E:E,"Manipur") -> 0 | G17: QUOTATION REQ. | H17: =COUNTIF('2026-2027'!J:J, G17) -> 23 | K17: DAY BEFORE YESTURDAY | L17: =COUNTIF('2026-2027'!B:B, TODAY()-2) -> 11 | S17: =SUBTOTAL(109,S4:S16) -> 828 | T17: =SUBTOTAL(109,T4:T16) -> 5.100305e+08
C18: Meghalaya | D18: =COUNTIF('2026-2027'!E:E,"Meghalaya") -> 0 | G18: NOT RECEIVED | H18: =COUNTIF('2026-2027'!J:J, G18) -> 115
C19: Karnataka | D19: =COUNTIF('2026-2027'!E:E,"Karnatka") -> 0 | G19: FAKE | H19: =COUNTIF('2026-2027'!J:J, G19) -> 165 | K19: CRANE TYPES | N19: Day | O19: Week 1 NOS | P19: Week 1 Amount | Q19: Week 2 NOS | R19: Week 2 Amount | S19: Week 3 NOS | T19: Week 3 Amount | U19: Week 4 NOS | V19: Week 4 Amount
C20: Mizoram | D20: =COUNTIF('2026-2027'!E:E,"Mizoram") -> 0 | G20: FULFILLED | H20: =COUNTIF('2026-2027'!J:J, G20) -> 29 | K20: TYPES OF CRANES | L20: NOS | N20: Monday | O20: 4 | P20: ₹ 0.00 | Q20: 0 | R20: ₹ 0.00 | S20: 0 | T20: ₹ 0.00 | U20: 0 | V20: ₹ 0.00
C21: Nagaland | D21: =COUNTIF('2026-2027'!E:E,"Nagaland") -> 0 | G21: QUOTATION SHARED | H21: =COUNTIF('2026-2027'!J:J, G21) -> 174 | K21: Modification | L21: =COUNTIF('2026-2027'!F:F, K21) -> 4 | N21: Tuesday | O21: 0 | P21: ₹ 0.00 | Q21: 0 | R21: ₹ 0.00 | S21: 0 | T21: ₹ 0.00 | U21: 0 | V21: ₹ 0.00
C22: Odisha | D22: =COUNTIF('2026-2027'!E:E,"Odisha") -> 3 | G22: CLOSED | H22: =COUNTIF('2026-2027'!J:J, G22) -> 67 | K22: LCS | L22: =COUNTIF('2026-2027'!F:F, K22) -> 40 | N22: Wednesday | O22: 0 | P22: ₹ 0.00 | Q22: 0 | R22: ₹ 0.00 | S22: 0 | T22: ₹ 0.00 | U22: 0 | V22: ₹ 0.00
C23: Punjab | D23: =COUNTIF('2026-2027'!E:E,"Punjab") -> 12 | G23: PO EXPECTED | H23: =COUNTIF('2026-2027'!J:J, G23) -> 23 | K23: Monorail | L23: =COUNTIF('2026-2027'!F:F, K23) -> 2 | N23: Thursday | O23: 0 | P23: ₹ 0.00 | Q23: 0 | R23: ₹ 0.00 | S23: 0 | T23: ₹ 0.00 | U23: 0 | V23: ₹ 0.00
C24: Rajasthan | D24: =COUNTIF('2026-2027'!E:E,"Rajasthan") -> 14 | K24: EOT Crane | L24: =COUNTIF('2026-2027'!F:F, K24) -> 226 | N24: Friday | O24: 0 | P24: ₹ 0.00 | Q24: 0 | R24: ₹ 0.00 | S24: 0 | T24: ₹ 0.00 | U24: 0 | V24: ₹ 0.00
C25: Sikkim | D25: =COUNTIF('2026-2027'!E:E,"Sikkim") -> 0 | G25: QUOTATIONS | K25: Jib Crane | L25: =COUNTIF('2026-2027'!F:F, K25) -> 183 | N25: Saturday | O25: 0 | P25: ₹ 0.00 | Q25: 0 | R25: ₹ 0.00 | S25: 0 | T25: ₹ 0.00 | U25: 0 | V25: ₹ 0.00
C26: Tamil Nadu | D26: =COUNTIF('2026-2027'!E:E,"Tamil Nadu") -> 49 | G26: Quotation Status | H26: NOS | K26: Hoist | L26: =COUNTIF('2026-2027'!F:F, K26) -> 185 | N26: Sunday | O26: 0 | P26: ₹ 0.00 | Q26: 0 | R26: ₹ 0.00 | S26: 0 | T26: ₹ 0.00 | U26: 0 | V26: ₹ 0.00
C27: Tripura | D27: =COUNTIF('2026-2027'!E:E,"Tripura") -> 0 | G27: Quotation Sent | H27: =COUNTIF('2026-2027'!Q:Q, G27) -> 134 | K27: Gantry Crane | L27: =COUNTIF('2026-2027'!F:F, K27) -> 46
C28: Uttar Pradesh | D28: =COUNTIF('2026-2027'!E:E,"Uttar Pradesh") -> 33 | G28: Clarification Pending | H28: =COUNTIF('2026-2027'!Q:Q, G28) -> 14 | K28: Manipulator | L28: =COUNTIF('2026-2027'!F:F, K28) -> 32
C29: Uttarakhand | D29: =COUNTIF('2026-2027'!E:E,"Uttarakhand") -> 1 | G29: Discussion Ongoing | H29: =COUNTIF('2026-2027'!Q:Q, G29) -> 18 | K29: Scissor Lifter | L29: =COUNTIF('2026-2027'!F:F, K29) -> 2
C30: West Bengal | D30: =COUNTIF('2026-2027'!E:E,"West Bengal") -> 9 | G30: On Hold | H30: =COUNTIF('2026-2027'!Q:Q, G30) -> 2 | K30: Others | L30: =COUNTIF('2026-2027'!F:F, K30) -> 104
C31: International | D31: =COUNTIF('2026-2027'!E:E,"International") -> 12 | G31: PO Received | H31: =COUNTIF('2026-2027'!Q:Q, G31) -> 27 | K31: Underslung | L31: =COUNTIF('2026-2027'!F:F, K31) -> 3
C32: Others | D32: =COUNTIF('2026-2027'!E:E,"Others") -> 14 | G32: Closed | H32: =COUNTIF('2026-2027'!Q:Q, G32) -> 16 | K32: Goliath | L32: =COUNTIF('2026-2027'!F:F, K32) -> 1
C33: Delhi | D33: =COUNTIF('2026-2027'!E:E,"Delhi") -> 10 | G33: In Progress | H33: =COUNTIF('2026-2027'!Q:Q, G33) -> 7
C34: TOTAL LEADS | D34: =SUBTOTAL(109,'DATA SHEET'!$D$3:$D$33) -> 754 | G34: NA | H34: =COUNTIF('2026-2027'!Q:Q, G34) -> 0
K35: =G36 -> 46197
G36: =TODAY() -> 46197 | K36: SALES OVERVIEW
G37: INQUIRY | H37: NOS | K37: REFRENCE | L37: =COUNTIFS('2026-2027'!L:L, G3, '2026-2027'!B:B, $G$36) -> 0
G38: NEW | H38: =COUNTIFS('2026-2027'!J:J, G38, '2026-2027'!B:B, $G$36) -> 0 | K38: EXISTING CUS. | L38: =COUNTIFS('2026-2027'!L:L, G4, '2026-2027'!B:B, $G$36) -> 0
G39: WIN | H39: =COUNTIFS('2026-2027'!J:J, G39, '2026-2027'!B:B, $G$36) -> 0 | K39: MAIL | L39: =COUNTIFS('2026-2027'!L:L, G5, '2026-2027'!B:B, $G$36) -> 0
G40: LOST | H40: =COUNTIFS('2026-2027'!J:J, G40, '2026-2027'!B:B, $G$36) -> 0 | K40: INDIAMART | L40: =COUNTIFS('2026-2027'!L:L, G6, '2026-2027'!B:B, $G$36) -> 0
G41: CONTACTED | H41: =COUNTIFS('2026-2027'!J:J, G41, '2026-2027'!B:B, $G$36) -> 0 | K41: OUT SOURCE | L41: =COUNTIFS('2026-2027'!L:L, G7, '2026-2027'!B:B, $G$36) -> 0
G42: NOT INTERESTED | H42: =COUNTIFS('2026-2027'!J:J, G42, '2026-2027'!B:B, $G$36) -> 0 | K42: TRADEINDIA | L42: =COUNTIFS('2026-2027'!L:L, G8, '2026-2027'!B:B, $G$36) -> 0
G43: SITE VISIT REQ. | H43: =COUNTIFS('2026-2027'!J:J, G43, '2026-2027'!B:B, $G$36) -> 0
G44: QUOTATION REQ. | H44: =COUNTIFS('2026-2027'!J:J, G44, '2026-2027'!B:B, $G$36) -> 0
G45: NOT RECEIVED | H45: =COUNTIFS('2026-2027'!J:J, G45, '2026-2027'!B:B, $G$36) -> 0
G46: FAKE | H46: =COUNTIFS('2026-2027'!J:J, G46, '2026-2027'!B:B, $G$36) -> 0
G47: FULFILLED | H47: =COUNTIFS('2026-2027'!J:J, G47, '2026-2027'!B:B, $G$36) -> 0
G48: TOTAL | H48: =SUM(H38:H47) -> 0

Sheet SUMMARY
D2: DATA SHEET
D3: LEAD SOURCES | F3: NEW | G3: WIN | H3: LOST | I3: CONTACTED | J3: NOT INTERESTED | K3: SITE VISIT REQ. | L3: QUOTATION REQ. | M3: NOT RECEIVED | N3: CLOSED | O3: FAKE | P3: FULFILLED | Q3: QUOTATION SHARED
D4: DATA | E4: ='DATA SHEET'!$S$17 -> 828 | F4: =COUNTIF('2026-2027'!$J:$J,F3) -> 8 | G4: =COUNTIF('2026-2027'!$J:$J,G3) -> 28 | H4: =COUNTIF('2026-2027'!$J:$J,H3) -> 14 | I4: =COUNTIF('2026-2027'!$J:$J,I3) -> 62 | J4: =COUNTIF('2026-2027'!$J:$J,J3) -> 119 | K4: =COUNTIF('2026-2027'!$J:$J,K3) -> 3 | L4: =COUNTIF('2026-2027'!$J:$J,L3) -> 23 | M4: =COUNTIF('2026-2027'!$J:$J,M3) -> 115 | ... Q4: =COUNTIF('2026-2027'!$J:$J,Q3) -> 174
D5: REFRENCE | E5: =COUNTIF('2026-2027'!L:L, D5) -> 37 | F5: =COUNTIF('2026-2027'!$J:$J,F4) -> 0 | G5: =COUNTIF('2026-2027'!$J:$J,G4) -> 0 | H5: =COUNTIFS('2026-2027'!$L:$L,D5,'2026-2027'!$J:$J,$H$3) -> 0 | I5: =COUNTIFS('2026-2027'!$L:$L,D5,'2026-2027'!$J:$J,$I$3) -> 1 | J5: =COUNTIFS('2026-2027'!$L:$L,D5,'2026-2027'!$J:$J,$J$3) -> 1 | K5: =COUNTIFS('2026-2027'!$L:$L,D5,'2026-2027'!$J:$J,$K$3) -> 0 | L5: =COUNTIFS('2026-2027'!$L:$L,D5,'2026-2027'!$J:$J,$L$3) -> 0 | M5: =COUNTIFS('2026-2027'!$L:$L,D5,'2026-2027'!$J:$J,$M$3) -> 0 | N5: =COUNTIF('2026-2027'!$J:$J,N4) -> 0 | O5: =COUNTIFS('2026-2027'!$L:$L,D5,'2026-2027'!$J:$J,$O$3) -> 1 | P5: =COUNTIFS('2026-2027'!$L:$L,D5,'2026-2027'!$J:$J,$P$3) -> 0 | Q5: =COUNTIFS('2026-2027'!$L:$L,D5,'2026-2027'!$J:$J,$Q$3) -> 23
D6: EXISTING CUS. | E6: =COUNTIF('2026-2027'!L:L, D6) -> 22 | F6: =COUNTIF('2026-2027'!$J:$J,F5) -> 0 | G6: =COUNTIF('2026-2027'!$J:$J,G5) -> 0 | H6: =COUNTIFS('2026-2027'!$L:$L,D6,'2026-2027'!$J:$J,$H$3) -> 0 | I6: =COUNTIFS('2026-2027'!$L:$L,D6,'2026-2027'!$J:$J,$I$3) -> 0 | J6: =COUNTIFS('2026-2027'!$L:$L,D6,'2026-2027'!$J:$J,$J$3) -> 0 | K6: =COUNTIFS('2026-2027'!$L:$L,D6,'2026-2027'!$J:$J,$K$3) -> 0 | L6: =COUNTIFS('2026-2027'!$L:$L,D6,'2026-2027'!$J:$J,$L$3) -> 0 | M6: =COUNTIFS('2026-2027'!$L:$L,D6,'2026-2027'!$J:$J,$M$3) -> 0 | N6: =COUNTIF('2026-2027'!$J:$J,N5) -> 0 | O6: =COUNTIFS('2026-2027'!$L:$L,D6,'2026-2027'!$J:$J,$O$3) -> 0 | P6: =COUNTIFS('2026-2027'!$L:$L,D6,'2026-2027'!$J:$J,$P$3) -> 0 | Q6: =COUNTIFS('2026-2027'!$L:$L,D6,'2026-2027'!$J:$J,$Q$3) -> 13
D7: MAIL | E7: =COUNTIF('2026-2027'!L:L, D7) -> 149 | F7: =COUNTIF('2026-2027'!$J:$J,F6) -> 0 | G7: =COUNTIF('2026-2027'!$J:$J,G6) -> 0 | H7: =COUNTIFS('2026-2027'!$L:$L,D7,'2026-2027'!$J:$J,$H$3) -> 1 | I7: =COUNTIFS('2026-2027'!$L:$L,D7,'2026-2027'!$J:$J,$I$3) -> 0 | J7: =COUNTIFS('2026-2027'!$L:$L,D7,'2026-2027'!$J:$J,$J$3) -> 3 | K7: =COUNTIFS('2026-2027'!$L:$L,D7,'2026-2027'!$J:$J,$K$3) -> 0 | L7: =COUNTIFS('2026-2027'!$L:$L,D7,'2026-2027'!$J:$J,$L$3) -> 3 | M7: =COUNTIFS('2026-2027'!$L:$L,D7,'2026-2027'!$J:$J,$M$3) -> 0 | N7: =COUNTIF('2026-2027'!$J:$J,N6) -> 0 | O7: =COUNTIFS('2026-2027'!$L:$L,D7,'2026-2027'!$J:$J,$O$3) -> 0 | P7: =COUNTIFS('2026-2027'!$L:$L,D7,'2026-2027'!$J:$J,$P$3) -> 1 | Q7: =COUNTIFS('2026-2027'!$L:$L,D7,'2026-2027'!$J:$J,$Q$3) -> 100
D8: INDIAMART | E8: =COUNTIF('2026-2027'!L:L, D8) -> 332 | F8: =COUNTIF('2026-2027'!$J:$J,F7) -> 0 | G8: =COUNTIF('2026-2027'!$J:$J,G7) -> 0 | H8: =COUNTIFS('2026-2027'!$L:$L,D8,'2026-2027'!$J:$J,$H$3) -> 9 | I8: =COUNTIFS('2026-2027'!$L:$L,D8,'2026-2027'!$J:$J,$I$3) -> 31 | J8: =COUNTIFS('2026-2027'!$L:$L,D8,'2026-2027'!$J:$J,$J$3) -> 64 | K8: =COUNTIFS('2026-2027'!$L:$L,D8,'2026-2027'!$J:$J,$K$3) -> 2 | L8: =COUNTIFS('2026-2027'!$L:$L,D8,'2026-2027'!$J:$J,$L$3) -> 13 | M8: =COUNTIFS('2026-2027'!$L:$L,D8,'2026-2027'!$J:$J,$M$3) -> 61 | N8: =COUNTIF('2026-2027'!$J:$J,N7) -> 0 | O8: =COUNTIFS('2026-2027'!$L:$L,D8,'2026-2027'!$J:$J,$O$3) -> 71 | P8: =COUNTIFS('2026-2027'!$L:$L,D8,'2026-2027'!$J:$J,$P$3) -> 10 | Q8: =COUNTIFS('2026-2027'!$L:$L,D8,'2026-2027'!$J:$J,$Q$3) -> 34
D9: OUT SOURCE | E9: =COUNTIF('2026-2027'!L:L, D9) -> 1 | F9: =COUNTIF('2026-2027'!$J:$J,F8) -> 0 | G9: =COUNTIF('2026-2027'!$J:$J,G8) -> 0 | H9: =COUNTIFS('2026-2027'!$L:$L,D9,'2026-2027'!$J:$J,$H$3) -> 0 | I9: =COUNTIFS('2026-2027'!$L:$L,D9,'2026-2027'!$J:$J,$I$3) -> 1 | J9: =COUNTIFS('2026-2027'!$L:$L,D9,'2026-2027'!$J:$J,$J$3) -> 0 | K9: =COUNTIFS('2026-2027'!$L:$L,D9,'2026-2027'!$J:$J,$K$3) -> 0 | L9: =COUNTIFS('2026-2027'!$L:$L,D9,'2026-2027'!$J:$J,$L$3) -> 0 | M9: =COUNTIFS('2026-2027'!$L:$L,D9,'2026-2027'!$J:$J,$M$3) -> 0 | N9: =COUNTIF('2026-2027'!$J:$J,N8) -> 0 | O9: =COUNTIFS('2026-2027'!$L:$L,D9,'2026-2027'!$J:$J,$O$3) -> 0 | P9: =COUNTIFS('2026-2027'!$L:$L,D9,'2026-2027'!$J:$J,$P$3) -> 0 | Q9: =COUNTIFS('2026-2027'!$L:$L,D9,'2026-2027'!$J:$J,$Q$3) -> 0
D10: TRADEINDIA | E10: =COUNTIF('2026-2027'!L:L, D10) -> 290 | F10: =COUNTIF('2026-2027'!$J:$J,F9) -> 0 | G10: =COUNTIF('2026-2027'!$J:$J,G9) -> 0 | H10: =COUNTIFS('2026-2027'!$L:$L,D10,'2026-2027'!$J:$J,$H$3) -> 4 | I10: =COUNTIFS('2026-2027'!$L:$L,D10,'2026-2027'!$J:$J,$I$3) -> 29 | J10: =COUNTIFS('2026-2027'!$L:$L,D10,'2026-2027'!$J:$J,$J$3) -> 51 | K10: =COUNTIFS('2026-2027'!$L:$L,D10,'2026-2027'!$J:$J,$K$3) -> 1 | L10: =COUNTIFS('2026-2027'!$L:$L,D10,'2026-2027'!$J:$J,$L$3) -> 7 | M10: =COUNTIFS('2026-2027'!$L:$L,D10,'2026-2027'!$J:$J,$M$3) -> 54 | N10: =COUNTIF('2026-2027'!$J:$J,N9) -> 0 | O10: =COUNTIFS('2026-2027'!$L:$L,D10,'2026-2027'!$J:$J,$O$3) -> 93 | P10: =COUNTIFS('2026-2027'!$L:$L,D10,'2026-2027'!$J:$J,$P$3) -> 18 | Q10: =COUNTIFS('2026-2027'!$L:$L,D10,'2026-2027'!$J:$J,$Q$3) -> 4
D12: 46174
D13: LEAD SOURCES | F13: NEW | G13: WIN | H13: LOST | I13: CONTACTED | J13: NOT INTERESTED | K13: SITE VISIT REQ. | L13: QUOTATION REQ. | M13: NOT RECEIVED | N13: CLOSED | O13: FAKE | P13: FULFILLED | Q13: QUOTATION SHARED | S13: =D12 -> 46174
D14: DATA | E14: =COUNTIFS('2026-2027'!$B:$B,">="&EOMONTH($D$12,-1)+1, '2026-2027'!$B:$B,"<"&EOMONTH($D$12,0)+1) -> 287 | F14: =COUNTIFS( '2026-2027'!$J:$J,F13, '2026-2027'!$B:$B,">="&EOMONTH($D$12,-1)+1, '2026-2027'!$B:$B,"<"&EOMONTH($D$12,0)+1 ) -> 8 | G14: =COUNTIFS( '2026-2027'!$J:$J,G13, '2026-2027'!$B:$B,">="&EOMONTH($D$12,-1)+1, '2026-2027'!$B:$B,"<"&EOMONTH($D$12,0)+1 ) -> 3 | H14: =COUNTIFS( '2026-2027'!$J:$J,H13, '2026-2027'!$B:$B,">="&EOMONTH($D$12,-1)+1, '2026-2027'!$B:$B,"<"&EOMONTH($D$12,0)+1 ) -> 2 | I14: =COUNTIFS( '2026-2027'!$J:$J,I13, '2026-2027'!$B:$B,">="&EOMONTH($D$12,-1)+1, '2026-2027'!$B:$B,"<"&EOMONTH($D$12,0)+1 ) -> 38 | J14: =COUNTIFS( '2026-2027'!$J:$J,J13, '2026-2027'!$B:$B,">="&EOMONTH($D$12,-1)+1, '2026-2027'!$B:$B,"<"&EOMONTH($D$12,0)+1 ) -> 30 | K14: =COUNTIFS( '2026-2027'!$J:$J,K13, '2026-2027'!$B:$B,">="&EOMONTH($D$12,-1)+1, '2026-2027'!$B:$B,"<"&EOMONTH($D$12,0)+1 ) -> 2 | L14: =COUNTIFS( '2026-2027'!$J:$J,L13, '2026-2027'!$B:$B,">="&EOMONTH($D$12,-1)+1, '2026-2027'!$B:$B,"<"&EOMONTH($D$12,0)+1 ) -> 22 | M14: =COUNTIFS( '2026-2027'!$J:$J,M13, '2026-2027'!$B:$B,">="&EOMONTH($D$12,-1)+1, '2026-2027'!$B:$B,"<"&EOMONTH($D$12,0)+1 ) -> 54 | ... Q14: =COUNTIFS( '2026-2027'!$J:$J,Q13, '2026-2027'!$B:$B,">="&EOMONTH($D$12,-1)+1, '2026-2027'!$B:$B,"<"&EOMONTH($D$12,0)+1 ) -> 55 | U14: 72 NO. | V14: LEADS
D15: REFRENCE | E15: =COUNTIFS( '2026-2027'!L:L,D15, '2026-2027'!B:B,">="&EOMONTH($D$12,-1)+1, '2026-2027'!B:B,"<"&EOMONTH($D$12,0)+1 ) -> 5 | F15: =COUNTIFS( '2026-2027'!$L:$L,D15, '2026-2027'!$J:$J,$F$3, '2026-2027'!$B:$B,">="&EOMONTH($D$12,-1)+1, '2026-2027'!$B:$B,"<"&EOMONTH($D$12,0)+1 ) -> 0 | G15: =COUNTIFS( '2026-2027'!$L:$L,D15, '2026-2027'!$J:$J,$G$3, '2026-2027'!$B:$B,">="&EOMONTH($D$12,-1)+1, '2026-2027'!$B:$B,"<"&EOMONTH($D$12,0)+1 ) -> 0 | H15: =COUNTIFS( '2026-2027'!$L:$L,D15, '2026-2027'!$J:$J,$H$3, '2026-2027'!$B:$B,">="&EOMONTH($D$12,-1)+1, '2026-2027'!$B:$B,"<"&EOMONTH($D$12,0)+1 ) -> 0 | I15: =COUNTIFS('2026-2027'!$L:$L,D15,'2026-2027'!$J:$J,$I$3,'2026-2027'!$B:$B,">="&EOMONTH($D$12,-1)+1, '2026-2027'!$B:$B,"<"&EOMONTH($D$12,0)+1 ) -> 0 | J15: =COUNTIFS('2026-2027'!$L:$L,D15,'2026-2027'!$J:$J,$J$3, '2026-2027'!$B:$B,">="&EOMONTH($D$12,-1)+1, '2026-2027'!$B:$B,"<"&EOMONTH($D$12,0)+1 ) -> 0 | K15: =COUNTIFS('2026-2027'!$L:$L,D15,'2026-2027'!$J:$J,$K$3, '2026-2027'!$B:$B,">="&EOMONTH($D$12,-1)+1, '2026-2027'!$B:$B,"<"&EOMONTH($D$12,0)+1 ) -> 0 | L15: =COUNTIFS('2026-2027'!$L:$L,D15,'2026-2027'!$J:$J,$L$3, '2026-2027'!$B:$B,">="&EOMONTH($D$12,-1)+1, '2026-2027'!$B:$B,"<"&EOMONTH($D$12,0)+1 ) -> 0 | M15: =COUNTIFS('2026-2027'!$L:$L,D15,'2026-2027'!$J:$J,$M$3, '2026-2027'!$B:$B,">="&EOMONTH($D$12,-1)+1, '2026-2027'!$B:$B,"<"&EOMONTH($D$12,0)+1 ) -> 0 | N15: =COUNTIFS( '2026-2027'!$J:$J,N14, '2026-2027'!$B:$B,">="&EOMONTH($D$12,-1)+1, '2026-2027'!$B:$B,"<"&EOMONTH($D$12,0)+1 ) -> 0 | O15: =COUNTIFS('2026-2027'!$L:$L,D15,'2026-2027'!$J:$J,$O$3, '2026-2027'!$B:$B,">="&EOMONTH($D$12,-1)+1, '2026-2027'!$B:$B,"<"&EOMONTH($D$12,0)+1 ) -> 0 | P15: =COUNTIFS('2026-2027'!$L:$L,D15,'2026-2027'!$J:$J,$P$3, '2026-2027'!$B:$B,">="&EOMONTH($D$12,-1)+1, '2026-2027'!$B:$B,"<"&EOMONTH($D$12,0)+1 ) -> 0 | Q15: =COUNTIFS('2026-2027'!$L:$L,D15,'2026-2027'!$J:$J,$Q$3, '2026-2027'!$B:$B,">="&EOMONTH($D$12,-1)+1, '2026-2027'!$B:$B,"<"&EOMONTH($D$12,0)+1 ) -> 5 | S15: =E14-H14-J14-N14-O14-P14-M14 -> 132
D16: EXISTING CUS. | E16: =COUNTIFS( '2026-2027'!L:L,D16, '2026-2027'!B:B,">="&EOMONTH($D$12,-1)+1, '2026-2027'!B:B,"<"&EOMONTH($D$12,0)+1 ) -> 9 | F16: =COUNTIFS( '2026-2027'!$L:$L,D16, '2026-2027'!$J:$J,$F$3, '2026-2027'!$B:$B,">="&EOMONTH($D$12,-1)+1, '2026-2027'!$B:$B,"<"&EOMONTH($D$12,0)+1 ) -> 0 | G16: =COUNTIFS( '2026-2027'!$L:$L,D16, '2026-2027'!$J:$J,$G$3, '2026-2027'!$B:$B,">="&EOMONTH($D$12,-1)+1, '2026-2027'!$B:$B,"<"&EOMONTH($D$12,0)+1 ) -> 0 | H16: =COUNTIFS( '2026-2027'!$L:$L,D16, '2026-2027'!$J:$J,$H$3, '2026-2027'!$B:$B,">="&EOMONTH($D$12,-1)+1, '2026-2027'!$B:$B,"<"&EOMONTH($D$12,0)+1 ) -> 0 | I16: =COUNTIFS('2026-2027'!$L:$L,D16,'2026-2027'!$J:$J,$I$3,'2026-2027'!$B:$B,">="&EOMONTH($D$12,-1)+1, '2026-2027'!$B:$B,"<"&EOMONTH($D$12,0)+1 ) -> 0 | J16: =COUNTIFS('2026-2027'!$L:$L,D16,'2026-2027'!$J:$J,$J$3, '2026-2027'!$B:$B,">="&EOMONTH($D$12,-1)+1, '2026-2027'!$B:$B,"<"&EOMONTH($D$12,0)+1 ) -> 0 | K16: =COUNTIFS('2026-2027'!$L:$L,D16,'2026-2027'!$J:$J,$K$3, '2026-2027'!$B:$B,">="&EOMONTH($D$12,-1)+1, '2026-2027'!$B:$B,"<"&EOMONTH($D$12,0)+1 ) -> 0 | L16: =COUNTIFS('2026-2027'!$L:$L,D16,'2026-2027'!$J:$J,$L$3, '2026-2027'!$B:$B,">="&EOMONTH($D$12,-1)+1, '2026-2027'!$B:$B,"<"&EOMONTH($D$12,0)+1 ) -> 0 | M16: =COUNTIFS('2026-2027'!$L:$L,D16,'2026-2027'!$J:$J,$M$3, '2026-2027'!$B:$B,">="&EOMONTH($D$12,-1)+1, '2026-2027'!$B:$B,"<"&EOMONTH($D$12,0)+1 ) -> 0 | N16: =COUNTIFS( '2026-2027'!$J:$J,N15, '2026-2027'!$B:$B,">="&EOMONTH($D$12,-1)+1, '2026-2027'!$B:$B,"<"&EOMONTH($D$12,0)+1 ) -> 0 | O16: =COUNTIFS('2026-2027'!$L:$L,D16,'2026-2027'!$J:$J,$O$3, '2026-2027'!$B:$B,">="&EOMONTH($D$12,-1)+1, '2026-2027'!$B:$B,"<"&EOMONTH($D$12,0)+1 ) -> 0 | P16: =COUNTIFS('2026-2027'!$L:$L,D16,'2026-2027'!$J:$J,$P$3, '2026-2027'!$B:$B,">="&EOMONTH($D$12,-1)+1, '2026-2027'!$B:$B,"<"&EOMONTH($D$12,0)+1 ) -> 0 | Q16: =COUNTIFS('2026-2027'!$L:$L,D16,'2026-2027'!$J:$J,$Q$3, '2026-2027'!$B:$B,">="&EOMONTH($D$12,-1)+1, '2026-2027'!$B:$B,"<"&EOMONTH($D$12,0)+1 ) -> 8 | S16: =Q14+L14+K14+I14+G14+F14 -> 128
D17: MAIL | E17: =COUNTIFS( '2026-2027'!L:L,D17, '2026-2027'!B:B,">="&EOMONTH($D$12,-1)+1, '2026-2027'!B:B,"<"&EOMONTH($D$12,0)+1 ) -> 31 | F17: =COUNTIFS( '2026-2027'!$L:$L,D17, '2026-2027'!$J:$J,$F$3, '2026-2027'!$B:$B,">="&EOMONTH($D$12,-1)+1, '2026-2027'!$B:$B,"<"&EOMONTH($D$12,0)+1 ) -> 0 | G17: =COUNTIFS( '2026-2027'!$L:$L,D17, '2026-2027'!$J:$J,$G$3, '2026-2027'!$B:$B,">="&EOMONTH($D$12,-1)+1, '2026-2027'!$B:$B,"<"&EOMONTH($D$12,0)+1 ) -> 3 | H17: =COUNTIFS( '2026-2027'!$L:$L,D17, '2026-2027'!$J:$J,$H$3, '2026-2027'!$B:$B,">="&EOMONTH($D$12,-1)+1, '2026-2027'!$B:$B,"<"&EOMONTH($D$12,0)+1 ) -> 0 | I17: =COUNTIFS('2026-2027'!$L:$L,D17,'2026-2027'!$J:$J,$I$3,'2026-2027'!$B:$B,">="&EOMONTH($D$12,-1)+1, '2026-2027'!$B:$B,"<"&EOMONTH($D$12,0)+1 ) -> 0 | J17: =COUNTIFS('2026-2027'!$L:$L,D17,'2026-2027'!$J:$J,$J$3, '2026-2027'!$B:$B,">="&EOMONTH($D$12,-1)+1, '2026-2027'!$B:$B,"<"&EOMONTH($D$12,0)+1 ) -> 1 | K17: =COUNTIFS('2026-2027'!$L:$L,D17,'2026-2027'!$J:$J,$K$3, '2026-2027'!$B:$B,">="&EOMONTH($D$12,-1)+1, '2026-2027'!$B:$B,"<"&EOMONTH($D$12,0)+1 ) -> 0 | L17: =COUNTIFS('2026-2027'!$L:$L,D17,'2026-2027'!$J:$J,$L$3, '2026-2027'!$B:$B,">="&EOMONTH($D$12,-1)+1, '2026-2027'!$B:$B,"<"&EOMONTH($D$12,0)+1 ) -> 2 | M17: =COUNTIFS('2026-2027'!$L:$L,D17,'2026-2027'!$J:$J,$M$3, '2026-2027'!$B:$B,">="&EOMONTH($D$12,-1)+1, '2026-2027'!$B:$B,"<"&EOMONTH($D$12,0)+1 ) -> 0 | N17: =COUNTIFS( '2026-2027'!$J:$J,N16, '2026-2027'!$B:$B,">="&EOMONTH($D$12,-1)+1, '2026-2027'!$B:$B,"<"&EOMONTH($D$12,0)+1 ) -> 0 | O17: =COUNTIFS('2026-2027'!$L:$L,D17,'2026-2027'!$J:$J,$O$3, '2026-2027'!$B:$B,">="&EOMONTH($D$12,-1)+1, '2026-2027'!$B:$B,"<"&EOMONTH($D$12,0)+1 ) -> 0 | P17: =COUNTIFS('2026-2027'!$L:$L,D17,'2026-2027'!$J:$J,$P$3, '2026-2027'!$B:$B,">="&EOMONTH($D$12,-1)+1, '2026-2027'!$B:$B,"<"&EOMONTH($D$12,0)+1 ) -> 0 | Q17: =COUNTIFS('2026-2027'!$L:$L,D17,'2026-2027'!$J:$J,$Q$3, '2026-2027'!$B:$B,">="&EOMONTH($D$12,-1)+1, '2026-2027'!$B:$B,"<"&EOMONTH($D$12,0)+1 ) -> 22
D18: INDIAMART | E18: =COUNTIFS( '2026-2027'!L:L,D18, '2026-2027'!B:B,">="&EOMONTH($D$12,-1)+1, '2026-2027'!B:B,"<"&EOMONTH($D$12,0)+1 ) -> 139 | F18: =COUNTIFS( '2026-2027'!$L:$L,D18, '2026-2027'!$J:$J,$F$3, '2026-2027'!$B:$B,">="&EOMONTH($D$12,-1)+1, '2026-2027'!$B:$B,"<"&EOMONTH($D$12,0)+1 ) -> 6 | G18: =COUNTIFS( '2026-2027'!$L:$L,D18, '2026-2027'!$J:$J,$G$3, '2026-2027'!$B:$B,">="&EOMONTH($D$12,-1)+1, '2026-2027'!$B:$B,"<"&EOMONTH($D$12,0)+1 ) -> 0 | H18: =COUNTIFS( '2026-2027'!$L:$L,D18, '2026-2027'!$J:$J,$H$3, '2026-2027'!$B:$B,">="&EOMONTH($D$12,-1)+1, '2026-2027'!$B:$B,"<"&EOMONTH($D$12,0)+1 ) -> 1 | I18: =COUNTIFS('2026-2027'!$L:$L,D18,'2026-2027'!$J:$J,$I$3,'2026-2027'!$B:$B,">="&EOMONTH($D$12,-1)+1, '2026-2027'!$B:$B,"<"&EOMONTH($D$12,0)+1 ) -> 18 | J18: =COUNTIFS('2026-2027'!$L:$L,D18,'2026-2027'!$J:$J,$J$3, '2026-2027'!$B:$B,">="&EOMONTH($D$12,-1)+1, '2026-2027'!$B:$B,"<"&EOMONTH($D$12,0)+1 ) -> 14 | K18: =COUNTIFS('2026-2027'!$L:$L,D18,'2026-2027'!$J:$J,$K$3, '2026-2027'!$B:$B,">="&EOMONTH($D$12,-1)+1, '2026-2027'!$B:$B,"<"&EOMONTH($D$12,0)+1 ) -> 2 | L18: =COUNTIFS('2026-2027'!$L:$L,D18,'2026-2027'!$J:$J,$L$3, '2026-2027'!$B:$B,">="&EOMONTH($D$12,-1)+1, '2026-2027'!$B:$B,"<"&EOMONTH($D$12,0)+1 ) -> 13 | M18: =COUNTIFS('2026-2027'!$L:$L,D18,'2026-2027'!$J:$J,$M$3, '2026-2027'!$B:$B,">="&EOMONTH($D$12,-1)+1, '2026-2027'!$B:$B,"<"&EOMONTH($D$12,0)+1 ) -> 33 | N18: =COUNTIFS( '2026-2027'!$J:$J,N17, '2026-2027'!$B:$B,">="&EOMONTH($D$12,-1)+1, '2026-2027'!$B:$B,"<"&EOMONTH($D$12,0)+1 ) -> 0 | O18: =COUNTIFS('2026-2027'!$L:$L,D18,'2026-2027'!$J:$J,$O$3, '2026-2027'!$B:$B,">="&EOMONTH($D$12,-1)+1, '2026-2027'!$B:$B,"<"&EOMONTH($D$12,0)+1 ) -> 29 | P18: =COUNTIFS('2026-2027'!$L:$L,D18,'2026-2027'!$J:$J,$P$3, '2026-2027'!$B:$B,">="&EOMONTH($D$12,-1)+1, '2026-2027'!$B:$B,"<"&EOMONTH($D$12,0)+1 ) -> 4 | Q18: =COUNTIFS('2026-2027'!$L:$L,D18,'2026-2027'!$J:$J,$Q$3, '2026-2027'!$B:$B,">="&EOMONTH($D$12,-1)+1, '2026-2027'!$B:$B,"<"&EOMONTH($D$12,0)+1 ) -> 16
D19: OUT SOURCE | E19: =COUNTIFS( '2026-2027'!L:L,D19, '2026-2027'!B:B,">="&EOMONTH($D$12,-1)+1, '2026-2027'!B:B,"<"&EOMONTH($D$12,0)+1 ) -> 1 | F19: =COUNTIFS( '2026-2027'!$L:$L,D19, '2026-2027'!$J:$J,$F$3, '2026-2027'!$B:$B,">="&EOMONTH($D$12,-1)+1, '2026-2027'!$B:$B,"<"&EOMONTH($D$12,0)+1 ) -> 0 | G19: =COUNTIFS( '2026-2027'!$L:$L,D19, '2026-2027'!$J:$J,$G$3, '2026-2027'!$B:$B,">="&EOMONTH($D$12,-1)+1, '2026-2027'!$B:$B,"<"&EOMONTH($D$12,0)+1 ) -> 0 | H19: =COUNTIFS( '2026-2027'!$L:$L,D19, '2026-2027'!$J:$J,$H$3, '2026-2027'!$B:$B,">="&EOMONTH($D$12,-1)+1, '2026-2027'!$B:$B,"<"&EOMONTH($D$12,0)+1 ) -> 0 | I19: =COUNTIFS('2026-2027'!$L:$L,D19,'2026-2027'!$J:$J,$I$3,'2026-2027'!$B:$B,">="&EOMONTH($D$12,-1)+1, '2026-2027'!$B:$B,"<"&EOMONTH($D$12,0)+1 ) -> 1 | J19: =COUNTIFS('2026-2027'!$L:$L,D19,'2026-2027'!$J:$J,$J$3, '2026-2027'!$B:$B,">="&EOMONTH($D$12,-1)+1, '2026-2027'!$B:$B,"<"&EOMONTH($D$12,0)+1 ) -> 0 | K19: =COUNTIFS('2026-2027'!$L:$L,D19,'2026-2027'!$J:$J,$K$3, '2026-2027'!$B:$B,">="&EOMONTH($D$12,-1)+1, '2026-2027'!$B:$B,"<"&EOMONTH($D$12,0)+1 ) -> 0 | L19: =COUNTIFS('2026-2027'!$L:$L,D19,'2026-2027'!$J:$J,$L$3, '2026-2027'!$B:$B,">="&EOMONTH($D$12,-1)+1, '2026-2027'!$B:$B,"<"&EOMONTH($D$12,0)+1 ) -> 0 | M19: =COUNTIFS('2026-2027'!$L:$L,D19,'2026-2027'!$J:$J,$M$3, '2026-2027'!$B:$B,">="&EOMONTH($D$12,-1)+1, '2026-2027'!$B:$B,"<"&EOMONTH($D$12,0)+1 ) -> 0 | N19: =COUNTIFS( '2026-2027'!$J:$J,N18, '2026-2027'!$B:$B,">="&EOMONTH($D$12,-1)+1, '2026-2027'!$B:$B,"<"&EOMONTH($D$12,0)+1 ) -> 0 | O19: =COUNTIFS('2026-2027'!$L:$L,D19,'2026-2027'!$J:$J,$O$3, '2026-2027'!$B:$B,">="&EOMONTH($D$12,-1)+1, '2026-2027'!$B:$B,"<"&EOMONTH($D$12,0)+1 ) -> 0 | P19: =COUNTIFS('2026-2027'!$L:$L,D19,'2026-2027'!$J:$J,$P$3, '2026-2027'!$B:$B,">="&EOMONTH($D$12,-1)+1, '2026-2027'!$B:$B,"<"&EOMONTH($D$12,0)+1 ) -> 0 | Q19: =COUNTIFS('2026-2027'!$L:$L,D19,'2026-2027'!$J:$J,$Q$3, '2026-2027'!$B:$B,">="&EOMONTH($D$12,-1)+1, '2026-2027'!$B:$B,"<"&EOMONTH($D$12,0)+1 ) -> 0
D20: TRADEINDIA | E20: =COUNTIFS( '2026-2027'!L:L,D20, '2026-2027'!B:B,">="&EOMONTH($D$12,-1)+1, '2026-2027'!B:B,"<"&EOMONTH($D$12,0)+1 ) -> 102 | F20: =COUNTIFS( '2026-2027'!$L:$L,D20, '2026-2027'!$J:$J,$F$3, '2026-2027'!$B:$B,">="&EOMONTH($D$12,-1)+1, '2026-2027'!$B:$B,"<"&EOMONTH($D$12,0)+1 ) -> 2 | G20: =COUNTIFS( '2026-2027'!$L:$L,D20, '2026-2027'!$J:$J,$G$3, '2026-2027'!$B:$B,">="&EOMONTH($D$12,-1)+1, '2026-2027'!$B:$B,"<"&EOMONTH($D$12,0)+1 ) -> 0 | H20: =COUNTIFS( '2026-2027'!$L:$L,D20, '2026-2027'!$J:$J,$H$3, '2026-2027'!$B:$B,">="&EOMONTH($D$12,-1)+1, '2026-2027'!$B:$B,"<"&EOMONTH($D$12,0)+1 ) -> 1 | I20: =COUNTIFS('2026-2027'!$L:$L,D20,'2026-2027'!$J:$J,$I$3,'2026-2027'!$B:$B,">="&EOMONTH($D$12,-1)+1, '2026-2027'!$B:$B,"<"&EOMONTH($D$12,0)+1 ) -> 19 | J20: =COUNTIFS('2026-2027'!$L:$L,D20,'2026-2027'!$J:$J,$J$3, '2026-2027'!$B:$B,">="&EOMONTH($D$12,-1)+1, '2026-2027'!$B:$B,"<"&EOMONTH($D$12,0)+1 ) -> 15 | K20: =COUNTIFS('2026-2027'!$L:$L,D20,'2026-2027'!$J:$J,$K$3, '2026-2027'!$B:$B,">="&EOMONTH($D$12,-1)+1, '2026-2027'!$B:$B,"<"&EOMONTH($D$12,0)+1 ) -> 0 | L20: =COUNTIFS('2026-2027'!$L:$L,D20,'2026-2027'!$J:$J,$L$3, '2026-2027'!$B:$B,">="&EOMONTH($D$12,-1)+1, '2026-2027'!$B:$B,"<"&EOMONTH($D$12,0)+1 ) -> 7 | M20: =COUNTIFS('2026-2027'!$L:$L,D20,'2026-2027'!$J:$J,$M$3, '2026-2027'!$B:$B,">="&EOMONTH($D$12,-1)+1, '2026-2027'!$B:$B,"<"&EOMONTH($D$12,0)+1 ) -> 21 | N20: =COUNTIFS( '2026-2027'!$J:$J,N19, '2026-2027'!$B:$B,">="&EOMONTH($D$12,-1)+1, '2026-2027'!$B:$B,"<"&EOMONTH($D$12,0)+1 ) -> 0 | O20: =COUNTIFS('2026-2027'!$L:$L,D20,'2026-2027'!$J:$J,$O$3, '2026-2027'!$B:$B,">="&EOMONTH($D$12,-1)+1, '2026-2027'!$B:$B,"<"&EOMONTH($D$12,0)+1 ) -> 26 | P20: =COUNTIFS('2026-2027'!$L:$L,D20,'2026-2027'!$J:$J,$P$3, '2026-2027'!$B:$B,">="&EOMONTH($D$12,-1)+1, '2026-2027'!$B:$B,"<"&EOMONTH($D$12,0)+1 ) -> 1 | Q20: =COUNTIFS('2026-2027'!$L:$L,D20,'2026-2027'!$J:$J,$Q$3, '2026-2027'!$B:$B,">="&EOMONTH($D$12,-1)+1, '2026-2027'!$B:$B,"<"&EOMONTH($D$12,0)+1 ) -> 4
D22: LEAD OWNER
D23: LEAD SOURCES | F23: NEW | G23: WIN | H23: LOST | I23: CONTACTED | J23: NOT INTERESTED | K23: SITE VISIT REQ. | L23: QUOTATION REQ. | M23: NOT RECEIVED | N23: CLOSED | O23: FAKE | P23: FULFILLED | Q23: QUOTATION SHARED | S23: =D22 -> LEAD OWNER
D24: MALLESH | E24: =COUNTIFS( '2026-2027'!M:M,D24, '2026-2027'!B:B,">="&EOMONTH($D$12,-1)+1, '2026-2027'!B:B,"<"&EOMONTH($D$12,0)+1 ) -> 8 | F24: =COUNTIFS( '2026-2027'!$M:$M,D24, '2026-2027'!$J:$J,$F$3, '2026-2027'!$B:$B,">="&EOMONTH($D$12,-1)+1, '2026-2027'!$B:$B,"<"&EOMONTH($D$12,0)+1 ) -> 0 | G24: =COUNTIFS( '2026-2027'!$M:$M,D24, '2026-2027'!$J:$J,$G$3, '2026-2027'!$B:$B,">="&EOMONTH($D$12,-1)+1, '2026-2027'!$B:$B,"<"&EOMONTH($D$12,0)+1 ) -> 0 | H24: =COUNTIFS( '2026-2027'!$M:$M,D24, '2026-2027'!$J:$J,$H$3, '2026-2027'!$B:$B,">="&EOMONTH($D$12,-1)+1, '2026-2027'!$B:$B,"<"&EOMONTH($D$12,0)+1 ) -> 0 | I24: =COUNTIFS('2026-2027'!$M:$M,D24,'2026-2027'!$J:$J,$I$3,'2026-2027'!$B:$B,">="&EOMONTH($D$12,-1)+1, '2026-2027'!$B:$B,"<"&EOMONTH($D$12,0)+1 ) -> 1 | J24: =COUNTIFS('2026-2027'!$M:$M,D24,'2026-2027'!$J:$J,$J$3, '2026-2027'!$B:$B,">="&EOMONTH($D$12,-1)+1, '2026-2027'!$B:$B,"<"&EOMONTH($D$12,0)+1 ) -> 0 | K24: =COUNTIFS('2026-2027'!$M:$M,D24,'2026-2027'!$J:$J,$K$3, '2026-2027'!$B:$B,">="&EOMONTH($D$12,-1)+1, '2026-2027'!$B:$B,"<"&EOMONTH($D$12,0)+1 ) -> 0 | L24: =COUNTIFS('2026-2027'!$M:$M,D24,'2026-2027'!$J:$J,$L$3, '2026-2027'!$B:$B,">="&EOMONTH($D$12,-1)+1, '2026-2027'!$B:$B,"<"&EOMONTH($D$12,0)+1 ) -> 0 | M24: =COUNTIFS('2026-2027'!$M:$M,D24,'2026-2027'!$J:$J,$M$3, '2026-2027'!$B:$B,">="&EOMONTH($D$12,-1)+1, '2026-2027'!$B:$B,"<"&EOMONTH($D$12,0)+1 ) -> 0 | N24: =COUNTIFS('2026-2027'!$M:$M,E24,'2026-2027'!$J:$J,$M$3, '2026-2027'!$B:$B,">="&EOMONTH($D$12,-1)+1, '2026-2027'!$B:$B,"<"&EOMONTH($D$12,0)+1 ) -> 0 | O24: =COUNTIFS('2026-2027'!$M:$M,D24,'2026-2027'!$J:$J,$O$3, '2026-2027'!$B:$B,">="&EOMONTH($D$12,-1)+1, '2026-2027'!$B:$B,"<"&EOMONTH($D$12,0)+1 ) -> 0 | P24: =COUNTIFS('2026-2027'!$M:$M,D24,'2026-2027'!$J:$J,$P$3, '2026-2027'!$B:$B,">="&EOMONTH($D$12,-1)+1, '2026-2027'!$B:$B,"<"&EOMONTH($D$12,0)+1 ) -> 0 | Q24: =COUNTIFS('2026-2027'!$M:$M,D24,'2026-2027'!$J:$J,$Q$3, '2026-2027'!$B:$B,">="&EOMONTH($D$12,-1)+1, '2026-2027'!$B:$B,"<"&EOMONTH($D$12,0)+1 ) -> 7
D25: RAVI | E25: =COUNTIFS( '2026-2027'!M:M,D25, '2026-2027'!B:B,">="&EOMONTH($D$12,-1)+1, '2026-2027'!B:B,"<"&EOMONTH($D$12,0)+1 ) -> 34 | F25: =COUNTIFS( '2026-2027'!$M:$M,D25, '2026-2027'!$J:$J,$F$3, '2026-2027'!$B:$B,">="&EOMONTH($D$12,-1)+1, '2026-2027'!$B:$B,"<"&EOMONTH($D$12,0)+1 ) -> 4 | G25: =COUNTIFS( '2026-2027'!$M:$M,D25, '2026-2027'!$J:$J,$G$3, '2026-2027'!$B:$B,">="&EOMONTH($D$12,-1)+1, '2026-2027'!$B:$B,"<"&EOMONTH($D$12,0)+1 ) -> 1 | H25: =COUNTIFS( '2026-2027'!$M:$M,D25, '2026-2027'!$J:$J,$H$3, '2026-2027'!$B:$B,">="&EOMONTH($D$12,-1)+1, '2026-2027'!$B:$B,"<"&EOMONTH($D$12,0)+1 ) -> 0 | I25: =COUNTIFS('2026-2027'!$M:$M,D25,'2026-2027'!$J:$J,$I$3,'2026-2027'!$B:$B,">="&EOMONTH($D$12,-1)+1, '2026-2027'!$B:$B,"<"&EOMONTH($D$12,0)+1 ) -> 0 | J25: =COUNTIFS('2026-2027'!$M:$M,D25,'2026-2027'!$J:$J,$J$3, '2026-2027'!$B:$B,">="&EOMONTH($D$12,-1)+1, '2026-2027'!$B:$B,"<"&EOMONTH($D$12,0)+1 ) -> 0 | K25: =COUNTIFS('2026-2027'!$M:$M,D25,'2026-2027'!$J:$J,$K$3, '2026-2027'!$B:$B,">="&EOMONTH($D$12,-1)+1, '2026-2027'!$B:$B,"<"&EOMONTH($D$12,0)+1 ) -> 0 | L25: =COUNTIFS('2026-2027'!$M:$M,D25,'2026-2027'!$J:$J,$L$3, '2026-2027'!$B:$B,">="&EOMONTH($D$12,-1)+1, '2026-2027'!$B:$B,"<"&EOMONTH($D$12,0)+1 ) -> 2 | M25: =COUNTIFS('2026-2027'!$M:$M,D25,'2026-2027'!$J:$J,$M$3, '2026-2027'!$B:$B,">="&EOMONTH($D$12,-1)+1, '2026-2027'!$B:$B,"<"&EOMONTH($D$12,0)+1 ) -> 0 | O25: =COUNTIFS('2026-2027'!$M:$M,D25,'2026-2027'!$J:$J,$O$3, '2026-2027'!$B:$B,">="&EOMONTH($D$12,-1)+1, '2026-2027'!$B:$B,"<"&EOMONTH($D$12,0)+1 ) -> 0 | P25: =COUNTIFS('2026-2027'!$M:$M,D25,'2026-2027'!$J:$J,$P$3, '2026-2027'!$B:$B,">="&EOMONTH($D$12,-1)+1, '2026-2027'!$B:$B,"<"&EOMONTH($D$12,0)+1 ) -> 0 | Q25: =COUNTIFS('2026-2027'!$M:$M,D25,'2026-2027'!$J:$J,$Q$3, '2026-2027'!$B:$B,">="&EOMONTH($D$12,-1)+1, '2026-2027'!$B:$B,"<"&EOMONTH($D$12,0)+1 ) -> 23
D26: HARSH | E26: =COUNTIFS( '2026-2027'!M:M,D26, '2026-2027'!B:B,">="&EOMONTH($D$12,-1)+1, '2026-2027'!B:B,"<"&EOMONTH($D$12,0)+1 ) -> 0 | F26: =COUNTIFS( '2026-2027'!$M:$M,D26, '2026-2027'!$J:$J,$F$3, '2026-2027'!$B:$B,">="&EOMONTH($D$12,-1)+1, '2026-2027'!$B:$B,"<"&EOMONTH($D$12,0)+1 ) -> 0 | G26: =COUNTIFS( '2026-2027'!$M:$M,D26, '2026-2027'!$J:$J,$G$3, '2026-2027'!$B:$B,">="&EOMONTH($D$12,-1)+1, '2026-2027'!$B:$B,"<"&EOMONTH($D$12,0)+1 ) -> 0 | H26: =COUNTIFS( '2026-2027'!$M:$M,D26, '2026-2027'!$J:$J,$H$3, '2026-2027'!$B:$B,">="&EOMONTH($D$12,-1)+1, '2026-2027'!$B:$B,"<"&EOMONTH($D$12,0)+1 ) -> 0 | I26: =COUNTIFS('2026-2027'!$M:$M,D26,'2026-2027'!$J:$J,$I$3,'2026-2027'!$B:$B,">="&EOMONTH($D$12,-1)+1, '2026-2027'!$B:$B,"<"&EOMONTH($D$12,0)+1 ) -> 0 | J26: =COUNTIFS('2026-2027'!$M:$M,D26,'2026-2027'!$J:$J,$J$3, '2026-2027'!$B:$B,">="&EOMONTH($D$12,-1)+1, '2026-2027'!$B:$B,"<"&EOMONTH($D$12,0)+1 ) -> 0 | K26: =COUNTIFS('2026-2027'!$M:$M,D26,'2026-2027'!$J:$J,$K$3, '2026-2027'!$B:$B,">="&EOMONTH($D$12,-1)+1, '2026-2027'!$B:$B,"<"&EOMONTH($D$12,0)+1 ) -> 0 | L26: =COUNTIFS('2026-2027'!$M:$M,D26,'2026-2027'!$J:$J,$L$3, '2026-2027'!$B:$B,">="&EOMONTH($D$12,-1)+1, '2026-2027'!$B:$B,"<"&EOMONTH($D$12,0)+1 ) -> 0 | M26: =COUNTIFS('2026-2027'!$M:$M,D26,'2026-2027'!$J:$J,$M$3, '2026-2027'!$B:$B,">="&EOMONTH($D$12,-1)+1, '2026-2027'!$B:$B,"<"&EOMONTH($D$12,0)+1 ) -> 0 | O26: =COUNTIFS('2026-2027'!$M:$M,D26,'2026-2027'!$J:$J,$O$3, '2026-2027'!$B:$B,">="&EOMONTH($D$12,-1)+1, '2026-2027'!$B:$B,"<"&EOMONTH($D$12,0)+1 ) -> 0 | P26: =COUNTIFS('2026-2027'!$M:$M,D26,'2026-2027'!$J:$J,$P$3, '2026-2027'!$B:$B,">="&EOMONTH($D$12,-1)+1, '2026-2027'!$B:$B,"<"&EOMONTH($D$12,0)+1 ) -> 0 | Q26: =COUNTIFS('2026-2027'!$M:$M,D26,'2026-2027'!$J:$J,$Q$3, '2026-2027'!$B:$B,">="&EOMONTH($D$12,-1)+1, '2026-2027'!$B:$B,"<"&EOMONTH($D$12,0)+1 ) -> 0
D27: VIVEK | E27: =COUNTIFS( '2026-2027'!M:M,D27, '2026-2027'!B:B,">="&EOMONTH($D$12,-1)+1, '2026-2027'!B:B,"<"&EOMONTH($D$12,0)+1 ) -> 177 | F27: =COUNTIFS( '2026-2027'!$M:$M,D27, '2026-2027'!$J:$J,$F$3, '2026-2027'!$B:$B,">="&EOMONTH($D$12,-1)+1, '2026-2027'!$B:$B,"<"&EOMONTH($D$12,0)+1 ) -> 1 | G27: =COUNTIFS( '2026-2027'!$M:$M,D27, '2026-2027'!$J:$J,$G$3, '2026-2027'!$B:$B,">="&EOMONTH($D$12,-1)+1, '2026-2027'!$B:$B,"<"&EOMONTH($D$12,0)+1 ) -> 0 | H27: =COUNTIFS( '2026-2027'!$M:$M,D27, '2026-2027'!$J:$J,$H$3, '2026-2027'!$B:$B,">="&EOMONTH($D$12,-1)+1, '2026-2027'!$B:$B,"<"&EOMONTH($D$12,0)+1 ) -> 1 | I27: =COUNTIFS('2026-2027'!$M:$M,D27,'2026-2027'!$J:$J,$I$3,'2026-2027'!$B:$B,">="&EOMONTH($D$12,-1)+1, '2026-2027'!$B:$B,"<"&EOMONTH($D$12,0)+1 ) -> 33 | J27: =COUNTIFS('2026-2027'!$M:$M,D27,'2026-2027'!$J:$J,$J$3, '2026-2027'!$B:$B,">="&EOMONTH($D$12,-1)+1, '2026-2027'!$B:$B,"<"&EOMONTH($D$12,0)+1 ) -> 26 | K27: =COUNTIFS('2026-2027'!$M:$M,D27,'2026-2027'!$J:$J,$K$3, '2026-2027'!$B:$B,">="&EOMONTH($D$12,-1)+1, '2026-2027'!$B:$B,"<"&EOMONTH($D$12,0)+1 ) -> 1 | L27: =COUNTIFS('2026-2027'!$M:$M,D27,'2026-2027'!$J:$J,$L$3, '2026-2027'!$B:$B,">="&EOMONTH($D$12,-1)+1, '2026-2027'!$B:$B,"<"&EOMONTH($D$12,0)+1 ) -> 12 | M27: =COUNTIFS('2026-2027'!$M:$M,D27,'2026-2027'!$J:$J,$M$3, '2026-2027'!$B:$B,">="&EOMONTH($D$12,-1)+1, '2026-2027'!$B:$B,"<"&EOMONTH($D$12,0)+1 ) -> 43 | O27: =COUNTIFS('2026-2027'!$M:$M,D27,'2026-2027'!$J:$J,$O$3, '2026-2027'!$B:$B,">="&EOMONTH($D$12,-1)+1, '2026-2027'!$B:$B,"<"&EOMONTH($D$12,0)+1 ) -> 42 | P27: =COUNTIFS('2026-2027'!$M:$M,D27,'2026-2027'!$J:$J,$P$3, '2026-2027'!$B:$B,">="&EOMONTH($D$12,-1)+1, '2026-2027'!$B:$B,"<"&EOMONTH($D$12,0)+1 ) -> 1 | Q27: =COUNTIFS('2026-2027'!$M:$M,D27,'2026-2027'!$J:$J,$Q$3, '2026-2027'!$B:$B,">="&EOMONTH($D$12,-1)+1, '2026-2027'!$B:$B,"<"&EOMONTH($D$12,0)+1 ) -> 9
D28: SAKSHI | E28: =COUNTIFS( '2026-2027'!M:M,D28, '2026-2027'!B:B,">="&EOMONTH($D$12,-1)+1, '2026-2027'!B:B,"<"&EOMONTH($D$12,0)+1 ) -> 64 | F28: =COUNTIFS( '2026-2027'!$M:$M,D28, '2026-2027'!$J:$J,$F$3, '2026-2027'!$B:$B,">="&EOMONTH($D$12,-1)+1, '2026-2027'!$B:$B,"<"&EOMONTH($D$12,0)+1 ) -> 1 | G28: =COUNTIFS( '2026-2027'!$M:$M,D28, '2026-2027'!$J:$J,$G$3, '2026-2027'!$B:$B,">="&EOMONTH($D$12,-1)+1, '2026-2027'!$B:$B,"<"&EOMONTH($D$12,0)+1 ) -> 2 | H28: =COUNTIFS( '2026-2027'!$M:$M,D28, '2026-2027'!$J:$J,$H$3, '2026-2027'!$B:$B,">="&EOMONTH($D$12,-1)+1, '2026-2027'!$B:$B,"<"&EOMONTH($D$12,0)+1 ) -> 1 | I28: =COUNTIFS('2026-2027'!$M:$M,D28,'2026-2027'!$J:$J,$I$3,'2026-2027'!$B:$B,">="&EOMONTH($D$12,-1)+1, '2026-2027'!$B:$B,"<"&EOMONTH($D$12,0)+1 ) -> 4 | J28: =COUNTIFS('2026-2027'!$M:$M,D28,'2026-2027'!$J:$J,$J$3, '2026-2027'!$B:$B,">="&EOMONTH($D$12,-1)+1, '2026-2027'!$B:$B,"<"&EOMONTH($D$12,0)+1 ) -> 4 | K28: =COUNTIFS('2026-2027'!$M:$M,D28,'2026-2027'!$J:$J,$K$3, '2026-2027'!$B:$B,">="&EOMONTH($D$12,-1)+1, '2026-2027'!$B:$B,"<"&EOMONTH($D$12,0)+1 ) -> 1 | L28: =COUNTIFS('2026-2027'!$M:$M,D28,'2026-2027'!$J:$J,$L$3, '2026-2027'!$B:$B,">="&EOMONTH($D$12,-1)+1, '2026-2027'!$B:$B,"<"&EOMONTH($D$12,0)+1 ) -> 6 | M28: =COUNTIFS('2026-2027'!$M:$M,D28,'2026-2027'!$J:$J,$M$3, '2026-2027'!$B:$B,">="&EOMONTH($D$12,-1)+1, '2026-2027'!$B:$B,"<"&EOMONTH($D$12,0)+1 ) -> 11 | O28: =COUNTIFS('2026-2027'!$M:$M,D28,'2026-2027'!$J:$J,$O$3, '2026-2027'!$B:$B,">="&EOMONTH($D$12,-1)+1, '2026-2027'!$B:$B,"<"&EOMONTH($D$12,0)+1 ) -> 13 | P28: =COUNTIFS('2026-2027'!$M:$M,D28,'2026-2027'!$J:$J,$P$3, '2026-2027'!$B:$B,">="&EOMONTH($D$12,-1)+1, '2026-2027'!$B:$B,"<"&EOMONTH($D$12,0)+1 ) -> 4 | Q28: =COUNTIFS('2026-2027'!$M:$M,D28,'2026-2027'!$J:$J,$Q$3, '2026-2027'!$B:$B,">="&EOMONTH($D$12,-1)+1, '2026-2027'!$B:$B,"<"&EOMONTH($D$12,0)+1 ) -> 16
D30: PRODUCTS
D31: LEAD SOURCES | F31: NEW | G31: WIN | H31: LOST | I31: CONTACTED | J31: NOT INTERESTED | K31: SITE VISIT REQ. | L31: QUOTATION REQ. | M31: NOT RECEIVED | N31: CLOSED | O31: FAKE | P31: FULFILLED | Q31: QUOTATION SHARED | S31: =D30 -> PRODUCTS
D32: Modification | E32: =COUNTIFS( '2026-2027'!F:F,D32, '2026-2027'!B:B,">="&EOMONTH($D$12,-1)+1, '2026-2027'!B:B,"<"&EOMONTH($D$12,0)+1 ) -> 2 | F32: =COUNTIFS( '2026-2027'!$F:$F,$D$32, '2026-2027'!$J:$J,$F$3, '2026-2027'!$B:$B,">="&EOMONTH($D$12,-1)+1, '2026-2027'!$B:$B,"<"&EOMONTH($D$12,0)+1 ) -> 1 | G32: =COUNTIFS( '2026-2027'!$F:$F,$D32, '2026-2027'!$J:$J,G3, '2026-2027'!$B:$B,">="&EOMONTH($D$12,-1)+1, '2026-2027'!$B:$B,"<"&EOMONTH($D$12,0)+1 ) -> 0 | H32: =COUNTIFS( '2026-2027'!$F:$F,$D32, '2026-2027'!$J:$J,$H$3, '2026-2027'!$B:$B,">="&EOMONTH($D$12,-1)+1, '2026-2027'!$B:$B,"<"&EOMONTH($D$12,0)+1 ) -> 0 | I32: =COUNTIFS( '2026-2027'!$F:$F,$D32, '2026-2027'!$J:$J,$I$3, '2026-2027'!$B:$B,">="&EOMONTH($D$12,-1)+1, '2026-2027'!$B:$B,"<"&EOMONTH($D$12,0)+1 ) -> 0 | J32: =COUNTIFS( '2026-2027'!$F:$F,$D32, '2026-2027'!$J:$J,$J$3, '2026-2027'!$B:$B,">="&EOMONTH($D$12,-1)+1, '2026-2027'!$B:$B,"<"&EOMONTH($D$12,0)+1 ) -> 0 | K32: =COUNTIFS( '2026-2027'!$F:$F,$D32, '2026-2027'!$J:$J,$K$3, '2026-2027'!$B:$B,">="&EOMONTH($D$12,-1)+1, '2026-2027'!$B:$B,"<"&EOMONTH($D$12,0)+1 ) -> 0 | L32: =COUNTIFS( '2026-2027'!$F:$F,$D32, '2026-2027'!$J:$J,$L$3, '2026-2027'!$B:$B,">="&EOMONTH($D$12,-1)+1, '2026-2027'!$B:$B,"<"&EOMONTH($D$12,0)+1 ) -> 0 | M32: =COUNTIFS( '2026-2027'!$F:$F,$D32, '2026-2027'!$J:$J,$M$3, '2026-2027'!$B:$B,">="&EOMONTH($D$12,-1)+1, '2026-2027'!$B:$B,"<"&EOMONTH($D$12,0)+1 ) -> 0 | O32: =COUNTIFS( '2026-2027'!$F:$F,$D32, '2026-2027'!$J:$J,$O$3, '2026-2027'!$B:$B,">="&EOMONTH($D$12,-1)+1, '2026-2027'!$B:$B,"<"&EOMONTH($D$12,0)+1 ) -> 0 | P32: =COUNTIFS( '2026-2027'!$F:$F,$D32, '2026-2027'!$J:$J,$P$3, '2026-2027'!$B:$B,">="&EOMONTH($D$12,-1)+1, '2026-2027'!$B:$B,"<"&EOMONTH($D$12,0)+1 ) -> 0 | Q32: =COUNTIFS( '2026-2027'!$F:$F,$D32, '2026-2027'!$J:$J,$Q$3, '2026-2027'!$B:$B,">="&EOMONTH($D$12,-1)+1, '2026-2027'!$B:$B,"<"&EOMONTH($D$12,0)+1 ) -> 1
D33: LCS | E33: =COUNTIFS( '2026-2027'!F:F,D33, '2026-2027'!B:B,">="&EOMONTH($D$12,-1)+1, '2026-2027'!B:B,"<"&EOMONTH($D$12,0)+1 ) -> 18 | F33: =COUNTIFS( '2026-2027'!$F:$F,D33, '2026-2027'!$J:$J,$F$3, '2026-2027'!$B:$B,">="&EOMONTH($D$12,-1)+1, '2026-2027'!$B:$B,"<"&EOMONTH($D$12,0)+1 ) -> 0 | G33: =COUNTIFS( '2026-2027'!$F:$F,$D33, '2026-2027'!$J:$J,$G$3, '2026-2027'!$B:$B,">="&EOMONTH($D$12,-1)+1, '2026-2027'!$B:$B,"<"&EOMONTH($D$12,0)+1 ) -> 1 | H33: =COUNTIFS( '2026-2027'!$F:$F,$D33, '2026-2027'!$J:$J,$H$3, '2026-2027'!$B:$B,">="&EOMONTH($D$12,-1)+1, '2026-2027'!$B:$B,"<"&EOMONTH($D$12,0)+1 ) -> 0 | I33: =COUNTIFS( '2026-2027'!$F:$F,$D33, '2026-2027'!$J:$J,$I$3, '2026-2027'!$B:$B,">="&EOMONTH($D$12,-1)+1, '2026-2027'!$B:$B,"<"&EOMONTH($D$12,0)+1 ) -> 1 | J33: =COUNTIFS( '2026-2027'!$F:$F,$D33, '2026-2027'!$J:$J,$J$3, '2026-2027'!$B:$B,">="&EOMONTH($D$12,-1)+1, '2026-2027'!$B:$B,"<"&EOMONTH($D$12,0)+1 ) -> 1 | K33: =COUNTIFS( '2026-2027'!$F:$F,$D33, '2026-2027'!$J:$J,$K$3, '2026-2027'!$B:$B,">="&EOMONTH($D$12,-1)+1, '2026-2027'!$B:$B,"<"&EOMONTH($D$12,0)+1 ) -> 0 | L33: =COUNTIFS( '2026-2027'!$F:$F,$D33, '2026-2027'!$J:$J,$L$3, '2026-2027'!$B:$B,">="&EOMONTH($D$12,-1)+1, '2026-2027'!$B:$B,"<"&EOMONTH($D$12,0)+1 ) -> 0 | M33: =COUNTIFS( '2026-2027'!$F:$F,$D33, '2026-2027'!$J:$J,$M$3, '2026-2027'!$B:$B,">="&EOMONTH($D$12,-1)+1, '2026-2027'!$B:$B,"<"&EOMONTH($D$12,0)+1 ) -> 4 | O33: =COUNTIFS( '2026-2027'!$F:$F,$D33, '2026-2027'!$J:$J,$O$3, '2026-2027'!$B:$B,">="&EOMONTH($D$12,-1)+1, '2026-2027'!$B:$B,"<"&EOMONTH($D$12,0)+1 ) -> 0 | P33: =COUNTIFS( '2026-2027'!$F:$F,$D33, '2026-2027'!$J:$J,$P$3, '2026-2027'!$B:$B,">="&EOMONTH($D$12,-1)+1, '2026-2027'!$B:$B,"<"&EOMONTH($D$12,0)+1 ) -> 0 | Q33: =COUNTIFS( '2026-2027'!$F:$F,$D33, '2026-2027'!$J:$J,$Q$3, '2026-2027'!$B:$B,">="&EOMONTH($D$12,-1)+1, '2026-2027'!$B:$B,"<"&EOMONTH($D$12,0)+1 ) -> 10
D34: Monorail | E34: =COUNTIFS( '2026-2027'!F:F,D34, '2026-2027'!B:B,">="&EOMONTH($D$12,-1)+1, '2026-2027'!B:B,"<"&EOMONTH($D$12,0)+1 ) -> 1 | F34: =COUNTIFS( '2026-2027'!$F:$F,D34, '2026-2027'!$J:$J,$F$3, '2026-2027'!$B:$B,">="&EOMONTH($D$12,-1)+1, '2026-2027'!$B:$B,"<"&EOMONTH($D$12,0)+1 ) -> 0 | G34: =COUNTIFS( '2026-2027'!$F:$F,$D34, '2026-2027'!$J:$J,$G$3, '2026-2027'!$B:$B,">="&EOMONTH($D$12,-1)+1, '2026-2027'!$B:$B,"<"&EOMONTH($D$12,0)+1 ) -> 0 | H34: =COUNTIFS( '2026-2027'!$F:$F,$D34, '2026-2027'!$J:$J,$H$3, '2026-2027'!$B:$B,">="&EOMONTH($D$12,-1)+1, '2026-2027'!$B:$B,"<"&EOMONTH($D$12,0)+1 ) -> 0 | I34: =COUNTIFS( '2026-2027'!$F:$F,$D34, '2026-2027'!$J:$J,$I$3, '2026-2027'!$B:$B,">="&EOMONTH($D$12,-1)+1, '2026-2027'!$B:$B,"<"&EOMONTH($D$12,0)+1 ) -> 1 | J34: =COUNTIFS( '2026-2027'!$F:$F,$D34, '2026-2027'!$J:$J,$J$3, '2026-2027'!$B:$B,">="&EOMONTH($D$12,-1)+1, '2026-2027'!$B:$B,"<"&EOMONTH($D$12,0)+1 ) -> 0 | K34: =COUNTIFS( '2026-2027'!$F:$F,$D34, '2026-2027'!$J:$J,$K$3, '2026-2027'!$B:$B,">="&EOMONTH($D$12,-1)+1, '2026-2027'!$B:$B,"<"&EOMONTH($D$12,0)+1 ) -> 0 | L34: =COUNTIFS( '2026-2027'!$F:$F,$D34, '2026-2027'!$J:$J,$L$3, '2026-2027'!$B:$B,">="&EOMONTH($D$12,-1)+1, '2026-2027'!$B:$B,"<"&EOMONTH($D$12,0)+1 ) -> 0 | M34: =COUNTIFS( '2026-2027'!$F:$F,$D34, '2026-2027'!$J:$J,$M$3, '2026-2027'!$B:$B,">="&EOMONTH($D$12,-1)+1, '2026-2027'!$B:$B,"<"&EOMONTH($D$12,0)+1 ) -> 0 | O34: =COUNTIFS( '2026-2027'!$F:$F,$D34, '2026-2027'!$J:$J,$O$3, '2026-2027'!$B:$B,">="&EOMONTH($D$12,-1)+1, '2026-2027'!$B:$B,"<"&EOMONTH($D$12,0)+1 ) -> 0 | P34: =COUNTIFS( '2026-2027'!$F:$F,$D34, '2026-2027'!$J:$J,$P$3, '2026-2027'!$B:$B,">="&EOMONTH($D$12,-1)+1, '2026-2027'!$B:$B,"<"&EOMONTH($D$12,0)+1 ) -> 0 | Q34: =COUNTIFS( '2026-2027'!$F:$F,$D34, '2026-2027'!$J:$J,$Q$3, '2026-2027'!$B:$B,">="&EOMONTH($D$12,-1)+1, '2026-2027'!$B:$B,"<"&EOMONTH($D$12,0)+1 ) -> 0
D35: EOT Crane | E35: =COUNTIFS( '2026-2027'!F:F,D35, '2026-2027'!B:B,">="&EOMONTH($D$12,-1)+1, '2026-2027'!B:B,"<"&EOMONTH($D$12,0)+1 ) -> 90 | F35: =COUNTIFS( '2026-2027'!$F:$F,D35, '2026-2027'!$J:$J,$F$3, '2026-2027'!$B:$B,">="&EOMONTH($D$12,-1)+1, '2026-2027'!$B:$B,"<"&EOMONTH($D$12,0)+1 ) -> 2 | G35: =COUNTIFS( '2026-2027'!$F:$F,$D35, '2026-2027'!$J:$J,$G$3, '2026-2027'!$B:$B,">="&EOMONTH($D$12,-1)+1, '2026-2027'!$B:$B,"<"&EOMONTH($D$12,0)+1 ) -> 0 | H35: =COUNTIFS( '2026-2027'!$F:$F,$D35, '2026-2027'!$J:$J,$H$3, '2026-2027'!$B:$B,">="&EOMONTH($D$12,-1)+1, '2026-2027'!$B:$B,"<"&EOMONTH($D$12,0)+1 ) -> 0 | I35: =COUNTIFS( '2026-2027'!$F:$F,$D35, '2026-2027'!$J:$J,$I$3, '2026-2027'!$B:$B,">="&EOMONTH($D$12,-1)+1, '2026-2027'!$B:$B,"<"&EOMONTH($D$12,0)+1 ) -> 15 | J35: =COUNTIFS( '2026-2027'!$F:$F,$D35, '2026-2027'!$J:$J,$J$3, '2026-2027'!$B:$B,">="&EOMONTH($D$12,-1)+1, '2026-2027'!$B:$B,"<"&EOMONTH($D$12,0)+1 ) -> 9 | K35: =COUNTIFS( '2026-2027'!$F:$F,$D35, '2026-2027'!$J:$J,$K$3, '2026-2027'!$B:$B,">="&EOMONTH($D$12,-1)+1, '2026-2027'!$B:$B,"<"&EOMONTH($D$12,0)+1 ) -> 0 | L35: =COUNTIFS( '2026-2027'!$F:$F,$D35, '2026-2027'!$J:$J,$L$3, '2026-2027'!$B:$B,">="&EOMONTH($D$12,-1)+1, '2026-2027'!$B:$B,"<"&EOMONTH($D$12,0)+1 ) -> 8 | M35: =COUNTIFS( '2026-2027'!$F:$F,$D35, '2026-2027'!$J:$J,$M$3, '2026-2027'!$B:$B,">="&EOMONTH($D$12,-1)+1, '2026-2027'!$B:$B,"<"&EOMONTH($D$12,0)+1 ) -> 18 | O35: =COUNTIFS( '2026-2027'!$F:$F,$D35, '2026-2027'!$J:$J,$O$3, '2026-2027'!$B:$B,">="&EOMONTH($D$12,-1)+1, '2026-2027'!$B:$B,"<"&EOMONTH($D$12,0)+1 ) -> 14 | P35: =COUNTIFS( '2026-2027'!$F:$F,$D35, '2026-2027'!$J:$J,$P$3, '2026-2027'!$B:$B,">="&EOMONTH($D$12,-1)+1, '2026-2027'!$B:$B,"<"&EOMONTH($D$12,0)+1 ) -> 0 | Q35: =COUNTIFS( '2026-2027'!$F:$F,$D35, '2026-2027'!$J:$J,$Q$3, '2026-2027'!$B:$B,">="&EOMONTH($D$12,-1)+1, '2026-2027'!$B:$B,"<"&EOMONTH($D$12,0)+1 ) -> 18
D36: Jib Crane | E36: =COUNTIFS( '2026-2027'!F:F,D36, '2026-2027'!B:B,">="&EOMONTH($D$12,-1)+1, '2026-2027'!B:B,"<"&EOMONTH($D$12,0)+1 ) -> 53 | F36: =COUNTIFS( '2026-2027'!$F:$F,D36, '2026-2027'!$J:$J,$F$3, '2026-2027'!$B:$B,">="&EOMONTH($D$12,-1)+1, '2026-2027'!$B:$B,"<"&EOMONTH($D$12,0)+1 ) -> 1 | G36: =COUNTIFS( '2026-2027'!$F:$F,$D36, '2026-2027'!$J:$J,$G$3, '2026-2027'!$B:$B,">="&EOMONTH($D$12,-1)+1, '2026-2027'!$B:$B,"<"&EOMONTH($D$12,0)+1 ) -> 2 | H36: =COUNTIFS( '2026-2027'!$F:$F,$D36, '2026-2027'!$J:$J,$H$3, '2026-2027'!$B:$B,">="&EOMONTH($D$12,-1)+1, '2026-2027'!$B:$B,"<"&EOMONTH($D$12,0)+1 ) -> 0 | I36: =COUNTIFS( '2026-2027'!$F:$F,$D36, '2026-2027'!$J:$J,$I$3, '2026-2027'!$B:$B,">="&EOMONTH($D$12,-1)+1, '2026-2027'!$B:$B,"<"&EOMONTH($D$12,0)+1 ) -> 7 | J36: =COUNTIFS( '2026-2027'!$F:$F,$D36, '2026-2027'!$J:$J,$J$3, '2026-2027'!$B:$B,">="&EOMONTH($D$12,-1)+1, '2026-2027'!$B:$B,"<"&EOMONTH($D$12,0)+1 ) -> 10 | K36: =COUNTIFS( '2026-2027'!$F:$F,$D36, '2026-2027'!$J:$J,$K$3, '2026-2027'!$B:$B,">="&EOMONTH($D$12,-1)+1, '2026-2027'!$B:$B,"<"&EOMONTH($D$12,0)+1 ) -> 0 | L36: =COUNTIFS( '2026-2027'!$F:$F,$D36, '2026-2027'!$J:$J,$L$3, '2026-2027'!$B:$B,">="&EOMONTH($D$12,-1)+1, '2026-2027'!$B:$B,"<"&EOMONTH($D$12,0)+1 ) -> 5 | M36: =COUNTIFS( '2026-2027'!$F:$F,$D36, '2026-2027'!$J:$J,$M$3, '2026-2027'!$B:$B,">="&EOMONTH($D$12,-1)+1, '2026-2027'!$B:$B,"<"&EOMONTH($D$12,0)+1 ) -> 10 | O36: =COUNTIFS( '2026-2027'!$F:$F,$D36, '2026-2027'!$J:$J,$O$3, '2026-2027'!$B:$B,">="&EOMONTH($D$12,-1)+1, '2026-2027'!$B:$B,"<"&EOMONTH($D$12,0)+1 ) -> 6 | P36: =COUNTIFS( '2026-2027'!$F:$F,$D36, '2026-2027'!$J:$J,$P$3, '2026-2027'!$B:$B,">="&EOMONTH($D$12,-1)+1, '2026-2027'!$B:$B,"<"&EOMONTH($D$12,0)+1 ) -> 0 | Q36: =COUNTIFS( '2026-2027'!$F:$F,$D36, '2026-2027'!$J:$J,$Q$3, '2026-2027'!$B:$B,">="&EOMONTH($D$12,-1)+1, '2026-2027'!$B:$B,"<"&EOMONTH($D$12,0)+1 ) -> 11
D37: Hoist | E37: =COUNTIFS( '2026-2027'!F:F,D37, '2026-2027'!B:B,">="&EOMONTH($D$12,-1)+1, '2026-2027'!B:B,"<"&EOMONTH($D$12,0)+1 ) -> 61 | F37: =COUNTIFS( '2026-2027'!$F:$F,D37, '2026-2027'!$J:$J,$F$3, '2026-2027'!$B:$B,">="&EOMONTH($D$12,-1)+1, '2026-2027'!$B:$B,"<"&EOMONTH($D$12,0)+1 ) -> 1 | G37: =COUNTIFS( '2026-2027'!$F:$F,$D37, '2026-2027'!$J:$J,$G$3, '2026-2027'!$B:$B,">="&EOMONTH($D$12,-1)+1, '2026-2027'!$B:$B,"<"&EOMONTH($D$12,0)+1 ) -> 0 | H37: =COUNTIFS( '2026-2027'!$F:$F,$D37, '2026-2027'!$J:$J,$H$3, '2026-2027'!$B:$B,">="&EOMONTH($D$12,-1)+1, '2026-2027'!$B:$B,"<"&EOMONTH($D$12,0)+1 ) -> 2 | I37: =COUNTIFS( '2026-2027'!$F:$F,$D37, '2026-2027'!$J:$J,$I$3, '2026-2027'!$B:$B,">="&EOMONTH($D$12,-1)+1, '2026-2027'!$B:$B,"<"&EOMONTH($D$12,0)+1 ) -> 5 | J37: =COUNTIFS( '2026-2027'!$F:$F,$D37, '2026-2027'!$J:$J,$J$3, '2026-2027'!$B:$B,">="&EOMONTH($D$12,-1)+1, '2026-2027'!$B:$B,"<"&EOMONTH($D$12,0)+1 ) -> 5 | K37: =COUNTIFS( '2026-2027'!$F:$F,$D37, '2026-2027'!$J:$J,$K$3, '2026-2027'!$B:$B,">="&EOMONTH($D$12,-1)+1, '2026-2027'!$B:$B,"<"&EOMONTH($D$12,0)+1 ) -> 1 | L37: =COUNTIFS( '2026-2027'!$F:$F,$D37, '2026-2027'!$J:$J,$L$3, '2026-2027'!$B:$B,">="&EOMONTH($D$12,-1)+1, '2026-2027'!$B:$B,"<"&EOMONTH($D$12,0)+1 ) -> 5 | M37: =COUNTIFS( '2026-2027'!$F:$F,$D37, '2026-2027'!$J:$J,$M$3, '2026-2027'!$B:$B,">="&EOMONTH($D$12,-1)+1, '2026-2027'!$B:$B,"<"&EOMONTH($D$12,0)+1 ) -> 12 | O37: =COUNTIFS( '2026-2027'!$F:$F,$D37, '2026-2027'!$J:$J,$O$3, '2026-2027'!$B:$B,">="&EOMONTH($D$12,-1)+1, '2026-2027'!$B:$B,"<"&EOMONTH($D$12,0)+1 ) -> 16 | P37: =COUNTIFS( '2026-2027'!$F:$F,$D37, '2026-2027'!$J:$J,$P$3, '2026-2027'!$B:$B,">="&EOMONTH($D$12,-1)+1, '2026-2027'!$B:$B,"<"&EOMONTH($D$12,0)+1 ) -> 4 | Q37: =COUNTIFS( '2026-2027'!$F:$F,$D37, '2026-2027'!$J:$J,$Q$3, '2026-2027'!$B:$B,">="&EOMONTH($D$12,-1)+1, '2026-2027'!$B:$B,"<"&EOMONTH($D$12,0)+1 ) -> 9
D38: Gantry Crane | E38: =COUNTIFS( '2026-2027'!F:F,D38, '2026-2027'!B:B,">="&EOMONTH($D$12,-1)+1, '2026-2027'!B:B,"<"&EOMONTH($D$12,0)+1 ) -> 15 | F38: =COUNTIFS( '2026-2027'!$F:$F,D38, '2026-2027'!$J:$J,$F$3, '2026-2027'!$B:$B,">="&EOMONTH($D$12,-1)+1, '2026-2027'!$B:$B,"<"&EOMONTH($D$12,0)+1 ) -> 0 | G38: =COUNTIFS( '2026-2027'!$F:$F,$D38, '2026-2027'!$J:$J,$G$3, '2026-2027'!$B:$B,">="&EOMONTH($D$12,-1)+1, '2026-2027'!$B:$B,"<"&EOMONTH($D$12,0)+1 ) -> 0 | H38: =COUNTIFS( '2026-2027'!$F:$F,$D38, '2026-2027'!$J:$J,$H$3, '2026-2027'!$B:$B,">="&EOMONTH($D$12,-1)+1, '2026-2027'!$B:$B,"<"&EOMONTH($D$12,0)+1 ) -> 0 | I38: =COUNTIFS( '2026-2027'!$F:$F,$D38, '2026-2027'!$J:$J,$I$3, '2026-2027'!$B:$B,">="&EOMONTH($D$12,-1)+1, '2026-2027'!$B:$B,"<"&EOMONTH($D$12,0)+1 ) -> 1 | J38: =COUNTIFS( '2026-2027'!$F:$F,$D38, '2026-2027'!$J:$J,$J$3, '2026-2027'!$B:$B,">="&EOMONTH($D$12,-1)+1, '2026-2027'!$B:$B,"<"&EOMONTH($D$12,0)+1 ) -> 2 | K38: =COUNTIFS( '2026-2027'!$F:$F,$D38, '2026-2027'!$J:$J,$K$3, '2026-2027'!$B:$B,">="&EOMONTH($D$12,-1)+1, '2026-2027'!$B:$B,"<"&EOMONTH($D$12,0)+1 ) -> 1 | L38: =COUNTIFS( '2026-2027'!$F:$F,$D38, '2026-2027'!$J:$J,$L$3, '2026-2027'!$B:$B,">="&EOMONTH($D$12,-1)+1, '2026-2027'!$B:$B,"<"&EOMONTH($D$12,0)+1 ) -> 2 | M38: =COUNTIFS( '2026-2027'!$F:$F,$D38, '2026-2027'!$J:$J,$M$3, '2026-2027'!$B:$B,">="&EOMONTH($D$12,-1)+1, '2026-2027'!$B:$B,"<"&EOMONTH($D$12,0)+1 ) -> 2 | O38: =COUNTIFS( '2026-2027'!$F:$F,$D38, '2026-2027'!$J:$J,$O$3, '2026-2027'!$B:$B,">="&EOMONTH($D$12,-1)+1, '2026-2027'!$B:$B,"<"&EOMONTH($D$12,0)+1 ) -> 5 | P38: =COUNTIFS( '2026-2027'!$F:$F,$D38, '2026-2027'!$J:$J,$P$3, '2026-2027'!$B:$B,">="&EOMONTH($D$12,-1)+1, '2026-2027'!$B:$B,"<"&EOMONTH($D$12,0)+1 ) -> 0 | Q38: =COUNTIFS( '2026-2027'!$F:$F,$D38, '2026-2027'!$J:$J,$Q$3, '2026-2027'!$B:$B,">="&EOMONTH($D$12,-1)+1, '2026-2027'!$B:$B,"<"&EOMONTH($D$12,0)+1 ) -> 1
D39: Manipulator | E39: =COUNTIFS( '2026-2027'!F:F,D39, '2026-2027'!B:B,">="&EOMONTH($D$12,-1)+1, '2026-2027'!B:B,"<"&EOMONTH($D$12,0)+1 ) -> 12 | F39: =COUNTIFS( '2026-2027'!$F:$F,D39, '2026-2027'!$J:$J,$F$3, '2026-2027'!$B:$B,">="&EOMONTH($D$12,-1)+1, '2026-2027'!$B:$B,"<"&EOMONTH($D$12,0)+1 ) -> 1 | G39: =COUNTIFS( '2026-2027'!$F:$F,$D39, '2026-2027'!$J:$J,$G$3, '2026-2027'!$B:$B,">="&EOMONTH($D$12,-1)+1, '2026-2027'!$B:$B,"<"&EOMONTH($D$12,0)+1 ) -> 0 | H39: =COUNTIFS( '2026-2027'!$F:$F,$D39, '2026-2027'!$J:$J,$H$3, '2026-2027'!$B:$B,">="&EOMONTH($D$12,-1)+1, '2026-2027'!$B:$B,"<"&EOMONTH($D$12,0)+1 ) -> 0 | I39: =COUNTIFS( '2026-2027'!$F:$F,$D39, '2026-2027'!$J:$J,$I$3, '2026-2027'!$B:$B,">="&EOMONTH($D$12,-1)+1, '2026-2027'!$B:$B,"<"&EOMONTH($D$12,0)+1 ) -> 5 | J39: =COUNTIFS( '2026-2027'!$F:$F,$D39, '2026-2027'!$J:$J,$J$3, '2026-2027'!$B:$B,">="&EOMONTH($D$12,-1)+1, '2026-2027'!$B:$B,"<"&EOMONTH($D$12,0)+1 ) -> 0 | K39: =COUNTIFS( '2026-2027'!$F:$F,$D39, '2026-2027'!$J:$J,$K$3, '2026-2027'!$B:$B,">="&EOMONTH($D$12,-1)+1, '2026-2027'!$B:$B,"<"&EOMONTH($D$12,0)+1 ) -> 0 | L39: =COUNTIFS( '2026-2027'!$F:$F,$D39, '2026-2027'!$J:$J,$L$3, '2026-2027'!$B:$B,">="&EOMONTH($D$12,-1)+1, '2026-2027'!$B:$B,"<"&EOMONTH($D$12,0)+1 ) -> 0 | M39: =COUNTIFS( '2026-2027'!$F:$F,$D39, '2026-2027'!$J:$J,$M$3, '2026-2027'!$B:$B,">="&EOMONTH($D$12,-1)+1, '2026-2027'!$B:$B,"<"&EOMONTH($D$12,0)+1 ) -> 3 | O39: =COUNTIFS( '2026-2027'!$F:$F,$D39, '2026-2027'!$J:$J,$O$3, '2026-2027'!$B:$B,">="&EOMONTH($D$12,-1)+1, '2026-2027'!$B:$B,"<"&EOMONTH($D$12,0)+1 ) -> 2 | P39: =COUNTIFS( '2026-2027'!$F:$F,$D39, '2026-2027'!$J:$J,$P$3, '2026-2027'!$B:$B,">="&EOMONTH($D$12,-1)+1, '2026-2027'!$B:$B,"<"&EOMONTH($D$12,0)+1 ) -> 0 | Q39: =COUNTIFS( '2026-2027'!$F:$F,$D39, '2026-2027'!$J:$J,$Q$3, '2026-2027'!$B:$B,">="&EOMONTH($D$12,-1)+1, '2026-2027'!$B:$B,"<"&EOMONTH($D$12,0)+1 ) -> 0
D40: Scissor Lifter | E40: =COUNTIFS( '2026-2027'!F:F,D40, '2026-2027'!B:B,">="&EOMONTH($D$12,-1)+1, '2026-2027'!B:B,"<"&EOMONTH($D$12,0)+1 ) -> 1 | F40: =COUNTIFS( '2026-2027'!$F:$F,D40, '2026-2027'!$J:$J,$F$3, '2026-2027'!$B:$B,">="&EOMONTH($D$12,-1)+1, '2026-2027'!$B:$B,"<"&EOMONTH($D$12,0)+1 ) -> 0 | G40: =COUNTIFS( '2026-2027'!$F:$F,$D40, '2026-2027'!$J:$J,$G$3, '2026-2027'!$B:$B,">="&EOMONTH($D$12,-1)+1, '2026-2027'!$B:$B,"<"&EOMONTH($D$12,0)+1 ) -> 0 | H40: =COUNTIFS( '2026-2027'!$F:$F,$D40, '2026-2027'!$J:$J,$H$3, '2026-2027'!$B:$B,">="&EOMONTH($D$12,-1)+1, '2026-2027'!$B:$B,"<"&EOMONTH($D$12,0)+1 ) -> 0 | I40: =COUNTIFS( '2026-2027'!$F:$F,$D40, '2026-2027'!$J:$J,$I$3, '2026-2027'!$B:$B,">="&EOMONTH($D$12,-1)+1, '2026-2027'!$B:$B,"<"&EOMONTH($D$12,0)+1 ) -> 0 | J40: =COUNTIFS( '2026-2027'!$F:$F,$D40, '2026-2027'!$J:$J,$J$3, '2026-2027'!$B:$B,">="&EOMONTH($D$12,-1)+1, '2026-2027'!$B:$B,"<"&EOMONTH($D$12,0)+1 ) -> 0 | K40: =COUNTIFS( '2026-2027'!$F:$F,$D40, '2026-2027'!$J:$J,$K$3, '2026-2027'!$B:$B,">="&EOMONTH($D$12,-1)+1, '2026-2027'!$B:$B,"<"&EOMONTH($D$12,0)+1 ) -> 0 | L40: =COUNTIFS( '2026-2027'!$F:$F,$D40, '2026-2027'!$J:$J,$L$3, '2026-2027'!$B:$B,">="&EOMONTH($D$12,-1)+1, '2026-2027'!$B:$B,"<"&EOMONTH($D$12,0)+1 ) -> 0 | M40: =COUNTIFS( '2026-2027'!$F:$F,$D40, '2026-2027'!$J:$J,$M$3, '2026-2027'!$B:$B,">="&EOMONTH($D$12,-1)+1, '2026-2027'!$B:$B,"<"&EOMONTH($D$12,0)+1 ) -> 0 | O40: =COUNTIFS( '2026-2027'!$F:$F,$D40, '2026-2027'!$J:$J,$O$3, '2026-2027'!$B:$B,">="&EOMONTH($D$12,-1)+1, '2026-2027'!$B:$B,"<"&EOMONTH($D$12,0)+1 ) -> 0 | P40: =COUNTIFS( '2026-2027'!$F:$F,$D40, '2026-2027'!$J:$J,$P$3, '2026-2027'!$B:$B,">="&EOMONTH($D$12,-1)+1, '2026-2027'!$B:$B,"<"&EOMONTH($D$12,0)+1 ) -> 0 | Q40: =COUNTIFS( '2026-2027'!$F:$F,$D40, '2026-2027'!$J:$J,$Q$3, '2026-2027'!$B:$B,">="&EOMONTH($D$12,-1)+1, '2026-2027'!$B:$B,"<"&EOMONTH($D$12,0)+1 ) -> 1
D41: Others | E41: =COUNTIFS( '2026-2027'!F:F,D41, '2026-2027'!B:B,">="&EOMONTH($D$12,-1)+1, '2026-2027'!B:B,"<"&EOMONTH($D$12,0)+1 ) -> 31 | F41: =COUNTIFS( '2026-2027'!$F:$F,D41, '2026-2027'!$J:$J,$F$3, '2026-2027'!$B:$B,">="&EOMONTH($D$12,-1)+1, '2026-2027'!$B:$B,"<"&EOMONTH($D$12,0)+1 ) -> 2 | G41: =COUNTIFS( '2026-2027'!$F:$F,$D41, '2026-2027'!$J:$J,$G$3, '2026-2027'!$B:$B,">="&EOMONTH($D$12,-1)+1, '2026-2027'!$B:$B,"<"&EOMONTH($D$12,0)+1 ) -> 0 | H41: =COUNTIFS( '2026-2027'!$F:$F,$D41, '2026-2027'!$J:$J,$H$3, '2026-2027'!$B:$B,">="&EOMONTH($D$12,-1)+1, '2026-2027'!$B:$B,"<"&EOMONTH($D$12,0)+1 ) -> 0 | I41: =COUNTIFS( '2026-2027'!$F:$F,$D41, '2026-2027'!$J:$J,$I$3, '2026-2027'!$B:$B,">="&EOMONTH($D$12,-1)+1, '2026-2027'!$B:$B,"<"&EOMONTH($D$12,0)+1 ) -> 2 | J41: =COUNTIFS( '2026-2027'!$F:$F,$D41, '2026-2027'!$J:$J,$J$3, '2026-2027'!$B:$B,">="&EOMONTH($D$12,-1)+1, '2026-2027'!$B:$B,"<"&EOMONTH($D$12,0)+1 ) -> 2 | K41: =COUNTIFS( '2026-2027'!$F:$F,$D41, '2026-2027'!$J:$J,$K$3, '2026-2027'!$B:$B,">="&EOMONTH($D$12,-1)+1, '2026-2027'!$B:$B,"<"&EOMONTH($D$12,0)+1 ) -> 0 | L41: =COUNTIFS( '2026-2027'!$F:$F,$D41, '2026-2027'!$J:$J,$L$3, '2026-2027'!$B:$B,">="&EOMONTH($D$12,-1)+1, '2026-2027'!$B:$B,"<"&EOMONTH($D$12,0)+1 ) -> 2 | M41: =COUNTIFS( '2026-2027'!$F:$F,$D41, '2026-2027'!$J:$J,$M$3, '2026-2027'!$B:$B,">="&EOMONTH($D$12,-1)+1, '2026-2027'!$B:$B,"<"&EOMONTH($D$12,0)+1 ) -> 4 | O41: =COUNTIFS( '2026-2027'!$F:$F,$D41, '2026-2027'!$J:$J,$O$3, '2026-2027'!$B:$B,">="&EOMONTH($D$12,-1)+1, '2026-2027'!$B:$B,"<"&EOMONTH($D$12,0)+1 ) -> 12 | P41: =COUNTIFS( '2026-2027'!$F:$F,$D41, '2026-2027'!$J:$J,$P$3, '2026-2027'!$B:$B,">="&EOMONTH($D$12,-1)+1, '2026-2027'!$B:$B,"<"&EOMONTH($D$12,0)+1 ) -> 1 | Q41: =COUNTIFS( '2026-2027'!$F:$F,$D41, '2026-2027'!$J:$J,$Q$3, '2026-2027'!$B:$B,">="&EOMONTH($D$12,-1)+1, '2026-2027'!$B:$B,"<"&EOMONTH($D$12,0)+1 ) -> 4
D42: Underslung | E42: =COUNTIFS( '2026-2027'!F:F,D42, '2026-2027'!B:B,">="&EOMONTH($D$12,-1)+1, '2026-2027'!B:B,"<"&EOMONTH($D$12,0)+1 ) -> 2 | F42: =COUNTIFS( '2026-2027'!$F:$F,D42, '2026-2027'!$J:$J,$F$3, '2026-2027'!$B:$B,">="&EOMONTH($D$12,-1)+1, '2026-2027'!$B:$B,"<"&EOMONTH($D$12,0)+1 ) -> 0 | G42: =COUNTIFS( '2026-2027'!$F:$F,$D42, '2026-2027'!$J:$J,$G$3, '2026-2027'!$B:$B,">="&EOMONTH($D$12,-1)+1, '2026-2027'!$B:$B,"<"&EOMONTH($D$12,0)+1 ) -> 0 | H42: =COUNTIFS( '2026-2027'!$F:$F,$D42, '2026-2027'!$J:$J,$H$3, '2026-2027'!$B:$B,">="&EOMONTH($D$12,-1)+1, '2026-2027'!$B:$B,"<"&EOMONTH($D$12,0)+1 ) -> 0 | I42: =COUNTIFS( '2026-2027'!$F:$F,$D42, '2026-2027'!$J:$J,$I$3, '2026-2027'!$B:$B,">="&EOMONTH($D$12,-1)+1, '2026-2027'!$B:$B,"<"&EOMONTH($D$12,0)+1 ) -> 1 | J42: =COUNTIFS( '2026-2027'!$F:$F,$D42, '2026-2027'!$J:$J,$J$3, '2026-2027'!$B:$B,">="&EOMONTH($D$12,-1)+1, '2026-2027'!$B:$B,"<"&EOMONTH($D$12,0)+1 ) -> 0 | K42: =COUNTIFS( '2026-2027'!$F:$F,$D42, '2026-2027'!$J:$J,$K$3, '2026-2027'!$B:$B,">="&EOMONTH($D$12,-1)+1, '2026-2027'!$B:$B,"<"&EOMONTH($D$12,0)+1 ) -> 0 | L42: =COUNTIFS( '2026-2027'!$F:$F,$D42, '2026-2027'!$J:$J,$L$3, '2026-2027'!$B:$B,">="&EOMONTH($D$12,-1)+1, '2026-2027'!$B:$B,"<"&EOMONTH($D$12,0)+1 ) -> 0 | M42: =COUNTIFS( '2026-2027'!$F:$F,$D42, '2026-2027'!$J:$J,$M$3, '2026-2027'!$B:$B,">="&EOMONTH($D$12,-1)+1, '2026-2027'!$B:$B,"<"&EOMONTH($D$12,0)+1 ) -> 1 | O42: =COUNTIFS( '2026-2027'!$F:$F,$D42, '2026-2027'!$J:$J,$O$3, '2026-2027'!$B:$B,">="&EOMONTH($D$12,-1)+1, '2026-2027'!$B:$B,"<"&EOMONTH($D$12,0)+1 ) -> 0 | P42: =COUNTIFS( '2026-2027'!$F:$F,$D42, '2026-2027'!$J:$J,$P$3, '2026-2027'!$B:$B,">="&EOMONTH($D$12,-1)+1, '2026-2027'!$B:$B,"<"&EOMONTH($D$12,0)+1 ) -> 0 | Q42: =COUNTIFS( '2026-2027'!$F:$F,$D42, '2026-2027'!$J:$J,$Q$3, '2026-2027'!$B:$B,">="&EOMONTH($D$12,-1)+1, '2026-2027'!$B:$B,"<"&EOMONTH($D$12,0)+1 ) -> 0
D43: Goliath | E43: =COUNTIFS( '2026-2027'!F:F,D43, '2026-2027'!B:B,">="&EOMONTH($D$12,-1)+1, '2026-2027'!B:B,"<"&EOMONTH($D$12,0)+1 ) -> 0 | F43: =COUNTIFS( '2026-2027'!$F:$F,D43, '2026-2027'!$J:$J,$F$3, '2026-2027'!$B:$B,">="&EOMONTH($D$12,-1)+1, '2026-2027'!$B:$B,"<"&EOMONTH($D$12,0)+1 ) -> 0 | G43: =COUNTIFS( '2026-2027'!$F:$F,$D43, '2026-2027'!$J:$J,$G$3, '2026-2027'!$B:$B,">="&EOMONTH($D$12,-1)+1, '2026-2027'!$B:$B,"<"&EOMONTH($D$12,0)+1 ) -> 0 | H43: =COUNTIFS( '2026-2027'!$F:$F,$D43, '2026-2027'!$J:$J,$H$3, '2026-2027'!$B:$B,">="&EOMONTH($D$12,-1)+1, '2026-2027'!$B:$B,"<"&EOMONTH($D$12,0)+1 ) -> 0 | I43: =COUNTIFS( '2026-2027'!$F:$F,$D43, '2026-2027'!$J:$J,$I$3, '2026-2027'!$B:$B,">="&EOMONTH($D$12,-1)+1, '2026-2027'!$B:$B,"<"&EOMONTH($D$12,0)+1 ) -> 0 | J43: =COUNTIFS( '2026-2027'!$F:$F,$D43, '2026-2027'!$J:$J,$J$3, '2026-2027'!$B:$B,">="&EOMONTH($D$12,-1)+1, '2026-2027'!$B:$B,"<"&EOMONTH($D$12,0)+1 ) -> 0 | K43: =COUNTIFS( '2026-2027'!$F:$F,$D43, '2026-2027'!$J:$J,$K$3, '2026-2027'!$B:$B,">="&EOMONTH($D$12,-1)+1, '2026-2027'!$B:$B,"<"&EOMONTH($D$12,0)+1 ) -> 0 | L43: =COUNTIFS( '2026-2027'!$F:$F,$D43, '2026-2027'!$J:$J,$L$3, '2026-2027'!$B:$B,">="&EOMONTH($D$12,-1)+1, '2026-2027'!$B:$B,"<"&EOMONTH($D$12,0)+1 ) -> 0 | M43: =COUNTIFS( '2026-2027'!$F:$F,$D43, '2026-2027'!$J:$J,$M$3, '2026-2027'!$B:$B,">="&EOMONTH($D$12,-1)+1, '2026-2027'!$B:$B,"<"&EOMONTH($D$12,0)+1 ) -> 0 | O43: =COUNTIFS( '2026-2027'!$F:$F,$D43, '2026-2027'!$J:$J,$O$3, '2026-2027'!$B:$B,">="&EOMONTH($D$12,-1)+1, '2026-2027'!$B:$B,"<"&EOMONTH($D$12,0)+1 ) -> 0 | P43: =COUNTIFS( '2026-2027'!$F:$F,$D43, '2026-2027'!$J:$J,$P$3, '2026-2027'!$B:$B,">="&EOMONTH($D$12,-1)+1, '2026-2027'!$B:$B,"<"&EOMONTH($D$12,0)+1 ) -> 0 | Q43: =COUNTIFS( '2026-2027'!$F:$F,$D43, '2026-2027'!$J:$J,$Q$3, '2026-2027'!$B:$B,">="&EOMONTH($D$12,-1)+1, '2026-2027'!$B:$B,"<"&EOMONTH($D$12,0)+1 ) -> 0
D45: LEAD SOURCES | F45: NEW | G45: WIN | H45: LOST | I45: CONTACTED | J45: NOT INTERESTED | K45: SITE VISIT REQ. | L45: QUOTATION REQ. | M45: NOT RECEIVED | N45: CLOSED | O45: FAKE | P45: FULFILLED | Q45: QUOTATION SHARED
D46: DATA | E46: =SUMIFS('2026-2027'!$P:$P, '2026-2027'!$B:$B, ">=" & EOMONTH($D$12,-1) + 1, '2026-2027'!$B:$B, "<" & EOMONTH($D$12,0) + 1) -> 1.9608383e+08 | F46: =SUMIFS('2026-2027'!$P:$P, '2026-2027'!$J:$J, F45, '2026-2027'!$B:$B, ">=" & EOMONTH($D$12,-1) + 1, '2026-2027'!$B:$B, "<" & EOMONTH($D$12,0) + 1) -> 4900000 | G46: =SUMIFS('2026-2027'!$P:$P, '2026-2027'!$J:$J,G45, '2026-2027'!$B:$B,">="&EOMONTH($D$12,-1)+1, '2026-2027'!$B:$B,"<"&EOMONTH($D$12,0)+1 ) -> 2030000 | H46: =SUMIFS('2026-2027'!$P:$P, '2026-2027'!$J:$J,H45, '2026-2027'!$B:$B,">="&EOMONTH($D$12,-1)+1, '2026-2027'!$B:$B,"<"&EOMONTH($D$12,0)+1 ) -> 170000 | I46: =SUMIFS('2026-2027'!$P:$P, '2026-2027'!$J:$J,I45, '2026-2027'!$B:$B,">="&EOMONTH($D$12,-1)+1, '2026-2027'!$B:$B,"<"&EOMONTH($D$12,0)+1 ) -> 0 | J46: =SUMIFS('2026-2027'!$P:$P, '2026-2027'!$J:$J,J45, '2026-2027'!$B:$B,">="&EOMONTH($D$12,-1)+1, '2026-2027'!$B:$B,"<"&EOMONTH($D$12,0)+1 ) -> 0 | K46: =SUMIFS('2026-2027'!$P:$P, '2026-2027'!$J:$J,K45, '2026-2027'!$B:$B,">="&EOMONTH($D$12,-1)+1, '2026-2027'!$B:$B,"<"&EOMONTH($D$12,0)+1 ) -> 0 | L46: =SUMIFS('2026-2027'!$P:$P, '2026-2027'!$J:$J,L45, '2026-2027'!$B:$B,">="&EOMONTH($D$12,-1)+1, '2026-2027'!$B:$B,"<"&EOMONTH($D$12,0)+1 ) -> 0 | M46: =SUMIFS('2026-2027'!$P:$P, '2026-2027'!$J:$J,M45, '2026-2027'!$B:$B,">="&EOMONTH($D$12,-1)+1, '2026-2027'!$B:$B,"<"&EOMONTH($D$12,0)+1 ) -> 0 | N46: =SUMIFS('2026-2027'!$P:$P, '2026-2027'!$J:$J,N45, '2026-2027'!$B:$B,">="&EOMONTH($D$12,-1)+1, '2026-2027'!$B:$B,"<"&EOMONTH($D$12,0)+1 ) -> 0 | ... Q46: =SUMIFS('2026-2027'!$P:$P, '2026-2027'!$J:$J,Q45, '2026-2027'!$B:$B,">="&EOMONTH($D$12,-1)+1, '2026-2027'!$B:$B,"<"&EOMONTH($D$12,0)+1 ) -> 1.7019119e+08
D47: REFRENCE | E47: =COUNTIFS( '2026-2027'!L:L,D47, '2026-2027'!B:B,">="&EOMONTH($D$12,-1)+1, '2026-2027'!B:B,"<"&EOMONTH($D$12,0)+1 ) -> 5 | F47: =COUNTIFS( '2026-2027'!$L:$L,D47, '2026-2027'!$J:$J,$F$3, '2026-2027'!$B:$B,">="&EOMONTH($D$12,-1)+1, '2026-2027'!$B:$B,"<"&EOMONTH($D$12,0)+1 ) -> 0 | G47: =COUNTIFS( '2026-2027'!$L:$L,D47, '2026-2027'!$J:$J,$G$3, '2026-2027'!$B:$B,">="&EOMONTH($D$12,-1)+1, '2026-2027'!$B:$B,"<"&EOMONTH($D$12,0)+1 ) -> 0 | H47: =COUNTIFS( '2026-2027'!$L:$L,D47, '2026-2027'!$J:$J,$H$3, '2026-2027'!$B:$B,">="&EOMONTH($D$12,-1)+1, '2026-2027'!$B:$B,"<"&EOMONTH($D$12,0)+1 ) -> 0 | I47: =COUNTIFS('2026-2027'!$L:$L,D47,'2026-2027'!$J:$J,$I$3,'2026-2027'!$B:$B,">="&EOMONTH($D$12,-1)+1, '2026-2027'!$B:$B,"<"&EOMONTH($D$12,0)+1 ) -> 0 | J47: =COUNTIFS('2026-2027'!$L:$L,D47,'2026-2027'!$J:$J,$J$3, '2026-2027'!$B:$B,">="&EOMONTH($D$12,-1)+1, '2026-2027'!$B:$B,"<"&EOMONTH($D$12,0)+1 ) -> 0 | K47: =COUNTIFS('2026-2027'!$L:$L,D47,'2026-2027'!$J:$J,$K$3, '2026-2027'!$B:$B,">="&EOMONTH($D$12,-1)+1, '2026-2027'!$B:$B,"<"&EOMONTH($D$12,0)+1 ) -> 0 | L47: =COUNTIFS('2026-2027'!$L:$L,D47,'2026-2027'!$J:$J,$L$3, '2026-2027'!$B:$B,">="&EOMONTH($D$12,-1)+1, '2026-2027'!$B:$B,"<"&EOMONTH($D$12,0)+1 ) -> 0 | M47: =COUNTIFS('2026-2027'!$L:$L,D47,'2026-2027'!$J:$J,$M$3, '2026-2027'!$B:$B,">="&EOMONTH($D$12,-1)+1, '2026-2027'!$B:$B,"<"&EOMONTH($D$12,0)+1 ) -> 0 | N47: =SUMIFS('2026-2027'!$P:$P, '2026-2027'!$J:$J,N46, '2026-2027'!$B:$B,">="&EOMONTH($D$12,-1)+1, '2026-2027'!$B:$B,"<"&EOMONTH($D$12,0)+1 ) -> 0 | O47: =COUNTIFS('2026-2027'!$L:$L,D47,'2026-2027'!$J:$J,$O$3, '2026-2027'!$B:$B,">="&EOMONTH($D$12,-1)+1, '2026-2027'!$B:$B,"<"&EOMONTH($D$12,0)+1 ) -> 0 | P47: =SUMIFS('2026-2027'!$P:$P,'2026-2027'!$L:$L,D47,'2026-2027'!$J:$J,$P$3, '2026-2027'!$B:$B,">="&EOMONTH($D$12,-1)+1, '2026-2027'!$B:$B,"<"&EOMONTH($D$12,0)+1 ) -> 0 | Q47: =SUMIFS('2026-2027'!$P:$P,'2026-2027'!$L:$L,D47,'2026-2027'!$J:$J,$Q$3, '2026-2027'!$B:$B,">="&EOMONTH($D$12,-1)+1, '2026-2027'!$B:$B,"<"&EOMONTH($D$12,0)+1 ) -> 44049824
D48: EXISTING CUS. | E48: =COUNTIFS( '2026-2027'!L:L,D48, '2026-2027'!B:B,">="&EOMONTH($D$12,-1)+1, '2026-2027'!B:B,"<"&EOMONTH($D$12,0)+1 ) -> 9 | F48: =COUNTIFS( '2026-2027'!$L:$L,D48, '2026-2027'!$J:$J,$F$3, '2026-2027'!$B:$B,">="&EOMONTH($D$12,-1)+1, '2026-2027'!$B:$B,"<"&EOMONTH($D$12,0)+1 ) -> 0 | G48: =COUNTIFS( '2026-2027'!$L:$L,D48, '2026-2027'!$J:$J,$G$3, '2026-2027'!$B:$B,">="&EOMONTH($D$12,-1)+1, '2026-2027'!$B:$B,"<"&EOMONTH($D$12,0)+1 ) -> 0 | H48: =COUNTIFS( '2026-2027'!$L:$L,D48, '2026-2027'!$J:$J,$H$3, '2026-2027'!$B:$B,">="&EOMONTH($D$12,-1)+1, '2026-2027'!$B:$B,"<"&EOMONTH($D$12,0)+1 ) -> 0 | I48: =COUNTIFS('2026-2027'!$L:$L,D48,'2026-2027'!$J:$J,$I$3,'2026-2027'!$B:$B,">="&EOMONTH($D$12,-1)+1, '2026-2027'!$B:$B,"<"&EOMONTH($D$12,0)+1 ) -> 0 | J48: =COUNTIFS('2026-2027'!$L:$L,D48,'2026-2027'!$J:$J,$J$3, '2026-2027'!$B:$B,">="&EOMONTH($D$12,-1)+1, '2026-2027'!$B:$B,"<"&EOMONTH($D$12,0)+1 ) -> 0 | K48: =COUNTIFS('2026-2027'!$L:$L,D48,'2026-2027'!$J:$J,$K$3, '2026-2027'!$B:$B,">="&EOMONTH($D$12,-1)+1, '2026-2027'!$B:$B,"<"&EOMONTH($D$12,0)+1 ) -> 0 | L48: =COUNTIFS('2026-2027'!$L:$L,D48,'2026-2027'!$J:$J,$L$3, '2026-2027'!$B:$B,">="&EOMONTH($D$12,-1)+1, '2026-2027'!$B:$B,"<"&EOMONTH($D$12,0)+1 ) -> 0 | M48: =COUNTIFS('2026-2027'!$L:$L,D48,'2026-2027'!$J:$J,$M$3, '2026-2027'!$B:$B,">="&EOMONTH($D$12,-1)+1, '2026-2027'!$B:$B,"<"&EOMONTH($D$12,0)+1 ) -> 0 | N48: =SUMIFS('2026-2027'!$P:$P, '2026-2027'!$J:$J,N47, '2026-2027'!$B:$B,">="&EOMONTH($D$12,-1)+1, '2026-2027'!$B:$B,"<"&EOMONTH($D$12,0)+1 ) -> 0 | O48: =COUNTIFS('2026-2027'!$L:$L,D48,'2026-2027'!$J:$J,$O$3, '2026-2027'!$B:$B,">="&EOMONTH($D$12,-1)+1, '2026-2027'!$B:$B,"<"&EOMONTH($D$12,0)+1 ) -> 0 | P48: =COUNTIFS('2026-2027'!$L:$L,D48,'2026-2027'!$J:$J,$P$3, '2026-2027'!$B:$B,">="&EOMONTH($D$12,-1)+1, '2026-2027'!$B:$B,"<"&EOMONTH($D$12,0)+1 ) -> 0 | Q48: =SUMIFS('2026-2027'!$P:$P,'2026-2027'!$L:$L,D48,'2026-2027'!$J:$J,$Q$3, '2026-2027'!$B:$B,">="&EOMONTH($D$12,-1)+1, '2026-2027'!$B:$B,"<"&EOMONTH($D$12,0)+1 ) -> 6293785
D49: MAIL | E49: =COUNTIFS( '2026-2027'!L:L,D49, '2026-2027'!B:B,">="&EOMONTH($D$12,-1)+1, '2026-2027'!B:B,"<"&EOMONTH($D$12,0)+1 ) -> 31 | F49: =COUNTIFS( '2026-2027'!$L:$L,D49, '2026-2027'!$J:$J,$F$3, '2026-2027'!$B:$B,">="&EOMONTH($D$12,-1)+1, '2026-2027'!$B:$B,"<"&EOMONTH($D$12,0)+1 ) -> 0 | G49: =COUNTIFS( '2026-2027'!$L:$L,D49, '2026-2027'!$J:$J,$G$3, '2026-2027'!$B:$B,">="&EOMONTH($D$12,-1)+1, '2026-2027'!$B:$B,"<"&EOMONTH($D$12,0)+1 ) -> 3 | H49: =COUNTIFS( '2026-2027'!$L:$L,D49, '2026-2027'!$J:$J,$H$3, '2026-2027'!$B:$B,">="&EOMONTH($D$12,-1)+1, '2026-2027'!$B:$B,"<"&EOMONTH($D$12,0)+1 ) -> 0 | I49: =COUNTIFS('2026-2027'!$L:$L,D49,'2026-2027'!$J:$J,$I$3,'2026-2027'!$B:$B,">="&EOMONTH($D$12,-1)+1, '2026-2027'!$B:$B,"<"&EOMONTH($D$12,0)+1 ) -> 0 | J49: =COUNTIFS('2026-2027'!$L:$L,D49,'2026-2027'!$J:$J,$J$3, '2026-2027'!$B:$B,">="&EOMONTH($D$12,-1)+1, '2026-2027'!$B:$B,"<"&EOMONTH($D$12,0)+1 ) -> 1 | K49: =COUNTIFS('2026-2027'!$L:$L,D49,'2026-2027'!$J:$J,$K$3, '2026-2027'!$B:$B,">="&EOMONTH($D$12,-1)+1, '2026-2027'!$B:$B,"<"&EOMONTH($D$12,0)+1 ) -> 0 | L49: =COUNTIFS('2026-2027'!$L:$L,D49,'2026-2027'!$J:$J,$L$3, '2026-2027'!$B:$B,">="&EOMONTH($D$12,-1)+1, '2026-2027'!$B:$B,"<"&EOMONTH($D$12,0)+1 ) -> 2 | M49: =COUNTIFS('2026-2027'!$L:$L,D49,'2026-2027'!$J:$J,$M$3, '2026-2027'!$B:$B,">="&EOMONTH($D$12,-1)+1, '2026-2027'!$B:$B,"<"&EOMONTH($D$12,0)+1 ) -> 0 | N49: =SUMIFS('2026-2027'!$P:$P, '2026-2027'!$J:$J,N48, '2026-2027'!$B:$B,">="&EOMONTH($D$12,-1)+1, '2026-2027'!$B:$B,"<"&EOMONTH($D$12,0)+1 ) -> 0 | O49: =COUNTIFS('2026-2027'!$L:$L,D49,'2026-2027'!$J:$J,$O$3, '2026-2027'!$B:$B,">="&EOMONTH($D$12,-1)+1, '2026-2027'!$B:$B,"<"&EOMONTH($D$12,0)+1 ) -> 0 | P49: =COUNTIFS('2026-2027'!$L:$L,D49,'2026-2027'!$J:$J,$P$3, '2026-2027'!$B:$B,">="&EOMONTH($D$12,-1)+1, '2026-2027'!$B:$B,"<"&EOMONTH($D$12,0)+1 ) -> 0 | Q49: =SUMIFS('2026-2027'!$P:$P,'2026-2027'!$L:$L,D49,'2026-2027'!$J:$J,$Q$3, '2026-2027'!$B:$B,">="&EOMONTH($D$12,-1)+1, '2026-2027'!$B:$B,"<"&EOMONTH($D$12,0)+1 ) -> 80893670
D50: INDIAMART | E50: =COUNTIFS( '2026-2027'!L:L,D50, '2026-2027'!B:B,">="&EOMONTH($D$12,-1)+1, '2026-2027'!B:B,"<"&EOMONTH($D$12,0)+1 ) -> 139 | F50: =COUNTIFS( '2026-2027'!$L:$L,D50, '2026-2027'!$J:$J,$F$3, '2026-2027'!$B:$B,">="&EOMONTH($D$12,-1)+1, '2026-2027'!$B:$B,"<"&EOMONTH($D$12,0)+1 ) -> 6 | G50: =COUNTIFS( '2026-2027'!$L:$L,D50, '2026-2027'!$J:$J,$G$3, '2026-2027'!$B:$B,">="&EOMONTH($D$12,-1)+1, '2026-2027'!$B:$B,"<"&EOMONTH($D$12,0)+1 ) -> 0 | H50: =COUNTIFS( '2026-2027'!$L:$L,D50, '2026-2027'!$J:$J,$H$3, '2026-2027'!$B:$B,">="&EOMONTH($D$12,-1)+1, '2026-2027'!$B:$B,"<"&EOMONTH($D$12,0)+1 ) -> 1 | I50: =COUNTIFS('2026-2027'!$L:$L,D50,'2026-2027'!$J:$J,$I$3,'2026-2027'!$B:$B,">="&EOMONTH($D$12,-1)+1, '2026-2027'!$B:$B,"<"&EOMONTH($D$12,0)+1 ) -> 18 | J50: =COUNTIFS('2026-2027'!$L:$L,D50,'2026-2027'!$J:$J,$J$3, '2026-2027'!$B:$B,">="&EOMONTH($D$12,-1)+1, '2026-2027'!$B:$B,"<"&EOMONTH($D$12,0)+1 ) -> 14 | K50: =COUNTIFS('2026-2027'!$L:$L,D50,'2026-2027'!$J:$J,$K$3, '2026-2027'!$B:$B,">="&EOMONTH($D$12,-1)+1, '2026-2027'!$B:$B,"<"&EOMONTH($D$12,0)+1 ) -> 2 | L50: =COUNTIFS('2026-2027'!$L:$L,D50,'2026-2027'!$J:$J,$L$3, '2026-2027'!$B:$B,">="&EOMONTH($D$12,-1)+1, '2026-2027'!$B:$B,"<"&EOMONTH($D$12,0)+1 ) -> 13 | M50: =COUNTIFS('2026-2027'!$L:$L,D50,'2026-2027'!$J:$J,$M$3, '2026-2027'!$B:$B,">="&EOMONTH($D$12,-1)+1, '2026-2027'!$B:$B,"<"&EOMONTH($D$12,0)+1 ) -> 33 | N50: =SUMIFS('2026-2027'!$P:$P, '2026-2027'!$J:$J,N49, '2026-2027'!$B:$B,">="&EOMONTH($D$12,-1)+1, '2026-2027'!$B:$B,"<"&EOMONTH($D$12,0)+1 ) -> 0 | O50: =COUNTIFS('2026-2027'!$L:$L,D50,'2026-2027'!$J:$J,$O$3, '2026-2027'!$B:$B,">="&EOMONTH($D$12,-1)+1, '2026-2027'!$B:$B,"<"&EOMONTH($D$12,0)+1 ) -> 29 | P50: =COUNTIFS('2026-2027'!$L:$L,D50,'2026-2027'!$J:$J,$P$3, '2026-2027'!$B:$B,">="&EOMONTH($D$12,-1)+1, '2026-2027'!$B:$B,"<"&EOMONTH($D$12,0)+1 ) -> 4 | Q50: =SUMIFS('2026-2027'!$P:$P,'2026-2027'!$L:$L,D50,'2026-2027'!$J:$J,$Q$3, '2026-2027'!$B:$B,">="&EOMONTH($D$12,-1)+1, '2026-2027'!$B:$B,"<"&EOMONTH($D$12,0)+1 ) -> 38765386
D51: OUT SOURCE | E51: =COUNTIFS( '2026-2027'!L:L,D51, '2026-2027'!B:B,">="&EOMONTH($D$12,-1)+1, '2026-2027'!B:B,"<"&EOMONTH($D$12,0)+1 ) -> 1 | F51: =COUNTIFS( '2026-2027'!$L:$L,D51, '2026-2027'!$J:$J,$F$3, '2026-2027'!$B:$B,">="&EOMONTH($D$12,-1)+1, '2026-2027'!$B:$B,"<"&EOMONTH($D$12,0)+1 ) -> 0 | G51: =COUNTIFS( '2026-2027'!$L:$L,D51, '2026-2027'!$J:$J,$G$3, '2026-2027'!$B:$B,">="&EOMONTH($D$12,-1)+1, '2026-2027'!$B:$B,"<"&EOMONTH($D$12,0)+1 ) -> 0 | H51: =COUNTIFS( '2026-2027'!$L:$L,D51, '2026-2027'!$J:$J,$H$3, '2026-2027'!$B:$B,">="&EOMONTH($D$12,-1)+1, '2026-2027'!$B:$B,"<"&EOMONTH($D$12,0)+1 ) -> 0 | I51: =COUNTIFS('2026-2027'!$L:$L,D51,'2026-2027'!$J:$J,$I$3,'2026-2027'!$B:$B,">="&EOMONTH($D$12,-1)+1, '2026-2027'!$B:$B,"<"&EOMONTH($D$12,0)+1 ) -> 1 | J51: =COUNTIFS('2026-2027'!$L:$L,D51,'2026-2027'!$J:$J,$J$3, '2026-2027'!$B:$B,">="&EOMONTH($D$12,-1)+1, '2026-2027'!$B:$B,"<"&EOMONTH($D$12,0)+1 ) -> 0 | K51: =COUNTIFS('2026-2027'!$L:$L,D51,'2026-2027'!$J:$J,$K$3, '2026-2027'!$B:$B,">="&EOMONTH($D$12,-1)+1, '2026-2027'!$B:$B,"<"&EOMONTH($D$12,0)+1 ) -> 0 | L51: =COUNTIFS('2026-2027'!$L:$L,D51,'2026-2027'!$J:$J,$L$3, '2026-2027'!$B:$B,">="&EOMONTH($D$12,-1)+1, '2026-2027'!$B:$B,"<"&EOMONTH($D$12,0)+1 ) -> 0 | M51: =COUNTIFS('2026-2027'!$L:$L,D51,'2026-2027'!$J:$J,$M$3, '2026-2027'!$B:$B,">="&EOMONTH($D$12,-1)+1, '2026-2027'!$B:$B,"<"&EOMONTH($D$12,0)+1 ) -> 0 | N51: =SUMIFS('2026-2027'!$P:$P, '2026-2027'!$J:$J,N50, '2026-2027'!$B:$B,">="&EOMONTH($D$12,-1)+1, '2026-2027'!$B:$B,"<"&EOMONTH($D$12,0)+1 ) -> 0 | O51: =COUNTIFS('2026-2027'!$L:$L,D51,'2026-2027'!$J:$J,$O$3, '2026-2027'!$B:$B,">="&EOMONTH($D$12,-1)+1, '2026-2027'!$B:$B,"<"&EOMONTH($D$12,0)+1 ) -> 0 | P51: =COUNTIFS('2026-2027'!$L:$L,D51,'2026-2027'!$J:$J,$P$3, '2026-2027'!$B:$B,">="&EOMONTH($D$12,-1)+1, '2026-2027'!$B:$B,"<"&EOMONTH($D$12,0)+1 ) -> 0 | Q51: =SUMIFS('2026-2027'!$P:$P,'2026-2027'!$L:$L,D51,'2026-2027'!$J:$J,$Q$3, '2026-2027'!$B:$B,">="&EOMONTH($D$12,-1)+1, '2026-2027'!$B:$B,"<"&EOMONTH($D$12,0)+1 ) -> 0
D52: TRADEINDIA | E52: =COUNTIFS( '2026-2027'!L:L,D52, '2026-2027'!B:B,">="&EOMONTH($D$12,-1)+1, '2026-2027'!B:B,"<"&EOMONTH($D$12,0)+1 ) -> 102 | F52: =COUNTIFS( '2026-2027'!$L:$L,D52, '2026-2027'!$J:$J,$F$3, '2026-2027'!$B:$B,">="&EOMONTH($D$12,-1)+1, '2026-2027'!$B:$B,"<"&EOMONTH($D$12,0)+1 ) -> 2 | G52: =COUNTIFS( '2026-2027'!$L:$L,D52, '2026-2027'!$J:$J,$G$3, '2026-2027'!$B:$B,">="&EOMONTH($D$12,-1)+1, '2026-2027'!$B:$B,"<"&EOMONTH($D$12,0)+1 ) -> 0 | H52: =COUNTIFS( '2026-2027'!$L:$L,D52, '2026-2027'!$J:$J,$H$3, '2026-2027'!$B:$B,">="&EOMONTH($D$12,-1)+1, '2026-2027'!$B:$B,"<"&EOMONTH($D$12,0)+1 ) -> 1 | I52: =COUNTIFS('2026-2027'!$L:$L,D52,'2026-2027'!$J:$J,$I$3,'2026-2027'!$B:$B,">="&EOMONTH($D$12,-1)+1, '2026-2027'!$B:$B,"<"&EOMONTH($D$12,0)+1 ) -> 19 | J52: =COUNTIFS('2026-2027'!$L:$L,D52,'2026-2027'!$J:$J,$J$3, '2026-2027'!$B:$B,">="&EOMONTH($D$12,-1)+1, '2026-2027'!$B:$B,"<"&EOMONTH($D$12,0)+1 ) -> 15 | K52: =COUNTIFS('2026-2027'!$L:$L,D52,'2026-2027'!$J:$J,$K$3, '2026-2027'!$B:$B,">="&EOMONTH($D$12,-1)+1, '2026-2027'!$B:$B,"<"&EOMONTH($D$12,0)+1 ) -> 0 | L52: =COUNTIFS('2026-2027'!$L:$L,D52,'2026-2027'!$J:$J,$L$3, '2026-2027'!$B:$B,">="&EOMONTH($D$12,-1)+1, '2026-2027'!$B:$B,"<"&EOMONTH($D$12,0)+1 ) -> 7 | M52: =COUNTIFS('2026-2027'!$L:$L,D52,'2026-2027'!$J:$J,$M$3, '2026-2027'!$B:$B,">="&EOMONTH($D$12,-1)+1, '2026-2027'!$B:$B,"<"&EOMONTH($D$12,0)+1 ) -> 21 | N52: =SUMIFS('2026-2027'!$P:$P, '2026-2027'!$J:$J,N51, '2026-2027'!$B:$B,">="&EOMONTH($D$12,-1)+1, '2026-2027'!$B:$B,"<"&EOMONTH($D$12,0)+1 ) -> 0 | O52: =COUNTIFS('2026-2027'!$L:$L,D52,'2026-2027'!$J:$J,$O$3, '2026-2027'!$B:$B,">="&EOMONTH($D$12,-1)+1, '2026-2027'!$B:$B,"<"&EOMONTH($D$12,0)+1 ) -> 26 | P52: =COUNTIFS('2026-2027'!$L:$L,D52,'2026-2027'!$J:$J,$P$3, '2026-2027'!$B:$B,">="&EOMONTH($D$12,-1)+1, '2026-2027'!$B:$B,"<"&EOMONTH($D$12,0)+1 ) -> 1 | Q52: =SUMIFS('2026-2027'!$P:$P,'2026-2027'!$L:$L,D52,'2026-2027'!$J:$J,$Q$3, '2026-2027'!$B:$B,">="&EOMONTH($D$12,-1)+1, '2026-2027'!$B:$B,"<"&EOMONTH($D$12,0)+1 ) -> 188524
